[{"stroke_code": 1, "course": "S", "date": "02/12/23", "time": "35.25", "is_pb": 1, "meet_name": "City of St Albans Winter Meet 2023", "wa_points": "271"}, {"stroke_code": 1, "course": "S", "date": "04/12/21", "time": "39.52", "is_pb": 1, "meet_name": "City of St Albans SC Winter Meet 2021", "wa_points": "192"}, {"stroke_code": 1, "course": "S", "date": "09/02/20", "time": "50.23", "is_pb": 1, "meet_name": "Alan Doyle Memorial Meet", "wa_points": "93"}, {"stroke_code": 1, "course": "S", "date": "09/06/24", "time": "35.88", "is_pb": 0, "meet_name": "Verulam SC Summer Club Championships 2024", "wa_points": "257"}, {"stroke_code": 1, "course": "S", "date": "11/07/21", "time": "40.44", "is_pb": 1, "meet_name": "City of St Albans Level 4 Club Champs", "wa_points": "179"}, {"stroke_code": 1, "course": "S", "date": "15/05/21", "time": "42.37", "is_pb": 1, "meet_name": "City of St Albans Swimming Club", "wa_points": "156"}, {"stroke_code": 1, "course": "S", "date": "17/09/22", "time": "37.21", "is_pb": 1, "meet_name": "City of St Albans SC Sprint & Skins Competition", "wa_points": "230"}, {"stroke_code": 1, "course": "S", "date": "18/09/21", "time": "40.43", "is_pb": 1, "meet_name": "City of St Albans Sprint and Skins Competition", "wa_points": "180"}, {"stroke_code": 1, "course": "S", "date": "19/12/20", "time": "44.94", "is_pb": 1, "meet_name": "City of St Albans", "wa_points": "131"}, {"stroke_code": 1, "course": "S", "date": "23/09/23", "time": "35.56", "is_pb": 1, "meet_name": "Co St Albans SC Sprint & Skins Competition 2023", "wa_points": "264"}, {"stroke_code": 1, "course": "S", "date": "25/06/23", "time": "37.00", "is_pb": 1, "meet_name": "City of St Albans SC End of Season Meet 2023", "wa_points": "234"}, {"stroke_code": 2, "course": "S", "date": "04/12/22", "time": "1:24.60", "is_pb": 0, "meet_name": "City of St Albans SC Winter Meet 2022", "wa_points": "209"}, {"stroke_code": 2, "course": "S", "date": "05/12/21", "time": "1:27.11", "is_pb": 1, "meet_name": "City of St Albans SC Winter Meet 2021", "wa_points": "191"}, {"stroke_code": 2, "course": "S", "date": "10/03/24", "time": "1:19.72", "is_pb": 0, "meet_name": "City of St Albans Spring Meet 2024", "wa_points": "250"}, {"stroke_code": 2, "course": "S", "date": "13/03/22", "time": "1:23.48", "is_pb": 1, "meet_name": "City of St Albans SC Spring Meet 2022", "wa_points": "218"}, {"stroke_code": 2, "course": "S", "date": "15/05/21", "time": "1:33.44", "is_pb": 1, "meet_name": "City of St Albans Swimming Club", "wa_points": "155"}, {"stroke_code": 2, "course": "S", "date": "17/09/22", "time": "1:24.60", "is_pb": 0, "meet_name": "City of St Albans SC Sprint & Skins Competition", "wa_points": "209"}, {"stroke_code": 2, "course": "S", "date": "18/09/21", "time": "1:33.47", "is_pb": 0, "meet_name": "City of St Albans Sprint and Skins Competition", "wa_points": "155"}, {"stroke_code": 2, "course": "S", "date": "23/09/23", "time": "1:18.79", "is_pb": 1, "meet_name": "Co St Albans SC Sprint & Skins Competition 2023", "wa_points": "259"}, {"stroke_code": 2, "course": "S", "date": "24/06/23", "time": "1:20.96", "is_pb": 1, "meet_name": "City of St Albans SC End of Season Meet 2023", "wa_points": "239"}, {"stroke_code": 2, "course": "S", "date": "30/09/22", "time": "1:22.90", "is_pb": 1, "meet_name": "City of St Albans SC Level 4 Club Champs", "wa_points": "222"}, {"stroke_code": 7, "course": "S", "date": "04/07/21", "time": "50.96", "is_pb": 1, "meet_name": "City of St Albans Level 4 Club Champs", "wa_points": "172"}, {"stroke_code": 7, "course": "S", "date": "09/06/24", "time": "44.53", "is_pb": 0, "meet_name": "Verulam SC Summer Club Championships 2024", "wa_points": "258"}, {"stroke_code": 7, "course": "S", "date": "10/03/24", "time": "43.88", "is_pb": 1, "meet_name": "City of St Albans Spring Meet 2024", "wa_points": "270"}, {"stroke_code": 7, "course": "S", "date": "13/03/22", "time": "47.71", "is_pb": 1, "meet_name": "City of St Albans SC Spring Meet 2022", "wa_points": "210"}, {"stroke_code": 7, "course": "S", "date": "15/05/21", "time": "51.39", "is_pb": 1, "meet_name": "City of St Albans Swimming Club", "wa_points": "168"}, {"stroke_code": 7, "course": "S", "date": "17/09/22", "time": "46.79", "is_pb": 1, "meet_name": "City of St Albans SC Sprint & Skins Competition", "wa_points": "222"}, {"stroke_code": 7, "course": "S", "date": "18/09/21", "time": "50.99", "is_pb": 0, "meet_name": "City of St Albans Sprint and Skins Competition", "wa_points": "172"}, {"stroke_code": 7, "course": "S", "date": "19/12/20", "time": "55.56", "is_pb": 1, "meet_name": "City of St Albans", "wa_points": "133"}, {"stroke_code": 7, "course": "S", "date": "23/09/23", "time": "44.19", "is_pb": 1, "meet_name": "Co St Albans SC Sprint & Skins Competition 2023", "wa_points": "264"}, {"stroke_code": 7, "course": "S", "date": "24/06/23", "time": "44.61", "is_pb": 1, "meet_name": "City of St Albans SC End of Season Meet 2023", "wa_points": "257"}, {"stroke_code": 8, "course": "S", "date": "04/12/22", "time": "1:42.87", "is_pb": 0, "meet_name": "City of St Albans SC Winter Meet 2022", "wa_points": "222"}, {"stroke_code": 8, "course": "S", "date": "05/12/21", "time": "1:47.77", "is_pb": 1, "meet_name": "City of St Albans SC Winter Meet 2021", "wa_points": "193"}, {"stroke_code": 8, "course": "S", "date": "10/03/24", "time": "1:39.55", "is_pb": 0, "meet_name": "City of St Albans Spring Meet 2024", "wa_points": "245"}, {"stroke_code": 8, "course": "S", "date": "17/09/22", "time": "1:48.56", "is_pb": 0, "meet_name": "City of St Albans SC Sprint & Skins Competition", "wa_points": "189"}, {"stroke_code": 8, "course": "S", "date": "18/09/21", "time": "1:51.61", "is_pb": 1, "meet_name": "City of St Albans Sprint and Skins Competition", "wa_points": "174"}, {"stroke_code": 8, "course": "S", "date": "23/09/23", "time": "1:36.49", "is_pb": 1, "meet_name": "Co St Albans SC Sprint & Skins Competition 2023", "wa_points": "269"}, {"stroke_code": 8, "course": "S", "date": "25/06/23", "time": "1:36.69", "is_pb": 1, "meet_name": "City of St Albans SC End of Season Meet 2023", "wa_points": "268"}, {"stroke_code": 8, "course": "S", "date": "29/09/22", "time": "1:41.35", "is_pb": 1, "meet_name": "City of St Albans SC Level 4 Club Champs", "wa_points": "232"}, {"stroke_code": 9, "course": "S", "date": "02/12/23", "time": "3:31.19", "is_pb": 1, "meet_name": "City of St Albans Winter Meet 2023", "wa_points": "246"}, {"stroke_code": 9, "course": "S", "date": "03/12/22", "time": "3:43.00", "is_pb": 1, "meet_name": "City of St Albans SC Winter Meet 2022", "wa_points": "209"}, {"stroke_code": 10, "course": "S", "date": "09/06/24", "time": "41.37", "is_pb": 1, "meet_name": "Verulam SC Summer Club Championships 2024", "wa_points": "193"}, {"stroke_code": 10, "course": "S", "date": "19/12/20", "time": "57.59", "is_pb": 1, "meet_name": "City of St Albans", "wa_points": "71"}, {"stroke_code": 13, "course": "S", "date": "02/12/23", "time": "43.02", "is_pb": 0, "meet_name": "City of St Albans Winter Meet 2023", "wa_points": "201"}, {"stroke_code": 13, "course": "S", "date": "03/12/22", "time": "45.32", "is_pb": 1, "meet_name": "City of St Albans SC Winter Meet 2022", "wa_points": "172"}, {"stroke_code": 13, "course": "S", "date": "04/07/21", "time": "51.64", "is_pb": 1, "meet_name": "City of St Albans Level 4 Club Champs", "wa_points": "116"}, {"stroke_code": 13, "course": "S", "date": "04/12/21", "time": "49.58", "is_pb": 1, "meet_name": "City of St Albans SC Winter Meet 2021", "wa_points": "131"}, {"stroke_code": 13, "course": "S", "date": "09/06/24", "time": "43.16", "is_pb": 0, "meet_name": "Verulam SC Summer Club Championships 2024", "wa_points": "199"}, {"stroke_code": 13, "course": "S", "date": "13/03/22", "time": "46.08", "is_pb": 1, "meet_name": "City of St Albans SC Spring Meet 2022", "wa_points": "164"}, {"stroke_code": 13, "course": "S", "date": "17/09/22", "time": "46.65", "is_pb": 0, "meet_name": "City of St Albans SC Sprint & Skins Competition", "wa_points": "158"}, {"stroke_code": 13, "course": "S", "date": "18/09/21", "time": "50.23", "is_pb": 1, "meet_name": "City of St Albans Sprint and Skins Competition", "wa_points": "126"}, {"stroke_code": 13, "course": "S", "date": "19/12/20", "time": "53.32", "is_pb": 1, "meet_name": "City of St Albans", "wa_points": "105"}, {"stroke_code": 13, "course": "S", "date": "23/09/23", "time": "42.89", "is_pb": 1, "meet_name": "Co St Albans SC Sprint & Skins Competition 2023", "wa_points": "203"}, {"stroke_code": 18, "course": "S", "date": "03/12/22", "time": "1:36.72", "is_pb": 0, "meet_name": "City of St Albans SC Winter Meet 2022", "wa_points": "184"}, {"stroke_code": 18, "course": "S", "date": "04/12/21", "time": "1:41.97", "is_pb": 1, "meet_name": "City of St Albans SC Winter Meet 2021", "wa_points": "157"}, {"stroke_code": 18, "course": "S", "date": "09/06/24", "time": "1:28.50", "is_pb": 1, "meet_name": "Verulam SC Summer Club Championships 2024", "wa_points": "241"}, {"stroke_code": 18, "course": "S", "date": "17/09/22", "time": "1:35.57", "is_pb": 1, "meet_name": "City of St Albans SC Sprint & Skins Competition", "wa_points": "191"}, {"stroke_code": 18, "course": "S", "date": "18/09/21", "time": "1:45.50", "is_pb": 1, "meet_name": "City of St Albans Sprint and Skins Competition", "wa_points": "142"}, {"stroke_code": 18, "course": "S", "date": "19/12/20", "time": "1:48.40", "is_pb": 1, "meet_name": "City of St Albans", "wa_points": "131"}]