[
  {
    "id": 299,
    "tiref": "1479966",
    "stroke_code": 1,
    "course": "L",
    "date": "16/03/24",
    "time": "34.56",
    "is_pb": 1,
    "meet_name": "Team Luton March Long Course Meet 2024",
    "venue": "Luton",
    "wa_points": "318",
    "round": "H",
    "level": "1"
  },
  {
    "id": 298,
    "tiref": "1479966",
    "stroke_code": 1,
    "course": "L",
    "date": "16/07/22",
    "time": "41.27",
    "is_pb": 1,
    "meet_name": "Team Luton Summer Long Course Meet 2022",
    "venue": "Luton",
    "wa_points": "187",
    "round": "H",
    "level": "3"
  },
  {
    "id": 277,
    "tiref": "1479966",
    "stroke_code": 1,
    "course": "S",
    "date": "01/07/23",
    "time": "38.90",
    "is_pb": 0,
    "meet_name": "Putteridge SC End of Season Summer SC Open 2023",
    "venue": "Luton",
    "wa_points": "202",
    "round": "H",
    "level": "2"
  },
  {
    "id": 279,
    "tiref": "1479966",
    "stroke_code": 1,
    "course": "S",
    "date": "01/10/23",
    "time": "35.58",
    "is_pb": 0,
    "meet_name": "City of St Albans Club Champs 2023",
    "venue": "St Albans",
    "wa_points": "264",
    "round": "F",
    "level": "4"
  },
  {
    "id": 282,
    "tiref": "1479966",
    "stroke_code": 1,
    "course": "S",
    "date": "02/12/23",
    "time": "33.98",
    "is_pb": 1,
    "meet_name": "City of St Albans Winter Meet 2023",
    "venue": "St Albans",
    "wa_points": "303",
    "round": "F",
    "level": "3"
  },
  {
    "id": 284,
    "tiref": "1479966",
    "stroke_code": 1,
    "course": "S",
    "date": "03/03/24",
    "time": "33.56",
    "is_pb": 1,
    "meet_name": "Watford SC Regional Qualifier 2024",
    "venue": "Watford",
    "wa_points": "314",
    "round": "F",
    "level": "3"
  },
  {
    "id": 276,
    "tiref": "1479966",
    "stroke_code": 1,
    "course": "S",
    "date": "03/06/23",
    "time": "37.15",
    "is_pb": 0,
    "meet_name": "Harlow Penguins 2023 10th Eric Shepherd Open Meet",
    "venue": "Harlow",
    "wa_points": "232",
    "round": "H",
    "level": "3"
  },
  {
    "id": 285,
    "tiref": "1479966",
    "stroke_code": 1,
    "course": "S",
    "date": "07/06/24",
    "time": "33.32",
    "is_pb": 1,
    "meet_name": "Herts & St Albans SSA Primary Schools Champs 2024",
    "venue": "St Albans",
    "wa_points": "321",
    "round": "F",
    "level": "4"
  },
  {
    "id": 280,
    "tiref": "1479966",
    "stroke_code": 1,
    "course": "S",
    "date": "07/10/23",
    "time": "35.30",
    "is_pb": 1,
    "meet_name": "Hatfield SC Regional Qualifier Oct 2023",
    "venue": "Hatfield",
    "wa_points": "270",
    "round": "H",
    "level": "3"
  },
  {
    "id": 289,
    "tiref": "1479966",
    "stroke_code": 1,
    "course": "S",
    "date": "08/03/25",
    "time": "32.10",
    "is_pb": 1,
    "meet_name": "City of St Albans Spring Meet 2025",
    "venue": "St Albans",
    "wa_points": "359",
    "round": "F",
    "level": "3"
  },
  {
    "id": 296,
    "tiref": "1479966",
    "stroke_code": 1,
    "course": "S",
    "date": "08/03/26",
    "time": "31.57",
    "is_pb": 0,
    "meet_name": "Watford SC Regional Qualifier Open Meet",
    "venue": "Watford",
    "wa_points": "378",
    "round": "F",
    "level": "3"
  },
  {
    "id": 273,
    "tiref": "1479966",
    "stroke_code": 1,
    "course": "S",
    "date": "11/03/23",
    "time": "37.76",
    "is_pb": 1,
    "meet_name": "Basildon & Phoenix Spring Regional Qualifier 2023",
    "venue": "Basildon",
    "wa_points": "221",
    "round": "H",
    "level": "3"
  },
  {
    "id": 268,
    "tiref": "1479966",
    "stroke_code": 1,
    "course": "S",
    "date": "11/07/21",
    "time": "52.97",
    "is_pb": 1,
    "meet_name": "Hertford Mini Club Championships",
    "venue": "Haileybury",
    "wa_points": "80",
    "round": "F",
    "level": "4"
  },
  {
    "id": 297,
    "tiref": "1479966",
    "stroke_code": 1,
    "course": "S",
    "date": "14/03/26",
    "time": "30.64",
    "is_pb": 1,
    "meet_name": "City of St Albans Spring Meet 2026",
    "venue": "St Albans",
    "wa_points": "413",
    "round": "F",
    "level": "3"
  },
  {
    "id": 291,
    "tiref": "1479966",
    "stroke_code": 1,
    "course": "S",
    "date": "15/06/25",
    "time": "31.96",
    "is_pb": 0,
    "meet_name": "Watford SC The Terry Davies Legacy Meet 2025",
    "venue": "Watford",
    "wa_points": "364",
    "round": "F",
    "level": "3"
  },
  {
    "id": 271,
    "tiref": "1479966",
    "stroke_code": 1,
    "course": "S",
    "date": "16/10/22",
    "time": "40.60",
    "is_pb": 1,
    "meet_name": "Hatfield SC Club Championships 2022",
    "venue": "Hatfield",
    "wa_points": "177",
    "round": "H",
    "level": "4"
  },
  {
    "id": 290,
    "tiref": "1479966",
    "stroke_code": 1,
    "course": "S",
    "date": "17/05/25",
    "time": "31.88",
    "is_pb": 1,
    "meet_name": "Cheshunt SC May Anniversary Meet 2025",
    "venue": "Harlow",
    "wa_points": "367",
    "round": "H",
    "level": "3"
  },
  {
    "id": 275,
    "tiref": "1479966",
    "stroke_code": 1,
    "course": "S",
    "date": "19/05/23",
    "time": "36.18",
    "is_pb": 1,
    "meet_name": "HSSA StASSA Primary Schools Champs 2023",
    "venue": "St Albans",
    "wa_points": "251",
    "round": "F",
    "level": "4"
  },
  {
    "id": 281,
    "tiref": "1479966",
    "stroke_code": 1,
    "course": "S",
    "date": "19/11/23",
    "time": "35.06",
    "is_pb": 1,
    "meet_name": "Watford SC County Qualifier 2023",
    "venue": "Watford",
    "wa_points": "276",
    "round": "F",
    "level": "3"
  },
  {
    "id": 292,
    "tiref": "1479966",
    "stroke_code": 1,
    "course": "S",
    "date": "20/09/25",
    "time": "31.13",
    "is_pb": 1,
    "meet_name": "Co St Albans Autumn Meet 2025",
    "venue": "St Albans",
    "wa_points": "394",
    "round": "F",
    "level": "3"
  },
  {
    "id": 270,
    "tiref": "1479966",
    "stroke_code": 1,
    "course": "S",
    "date": "21/05/22",
    "time": "41.00",
    "is_pb": 0,
    "meet_name": "Cheshunt SC Anniversary Open Meet 2022",
    "venue": "Harlow",
    "wa_points": "172",
    "round": "H",
    "level": "3"
  },
  {
    "id": 286,
    "tiref": "1479966",
    "stroke_code": 1,
    "course": "S",
    "date": "21/09/24",
    "time": "33.60",
    "is_pb": 0,
    "meet_name": "Co St Albans Autumn Sprint Meet 2024",
    "venue": "St Albans",
    "wa_points": "313",
    "round": "F",
    "level": "3"
  },
  {
    "id": 278,
    "tiref": "1479966",
    "stroke_code": 1,
    "course": "S",
    "date": "23/09/23",
    "time": "35.34",
    "is_pb": 1,
    "meet_name": "Co St Albans SC Sprint & Skins Competition 2023",
    "venue": "St Albans",
    "wa_points": "269",
    "round": "F",
    "level": "3"
  },
  {
    "id": 295,
    "tiref": "1479966",
    "stroke_code": 1,
    "course": "S",
    "date": "24/01/26",
    "time": "31.00",
    "is_pb": 1,
    "meet_name": "SE Hertfordshire County Championships 2026",
    "venue": "St Albans",
    "wa_points": "399",
    "round": "H",
    "level": "2"
  },
  {
    "id": 288,
    "tiref": "1479966",
    "stroke_code": 1,
    "course": "S",
    "date": "25/01/25",
    "time": "32.56",
    "is_pb": 1,
    "meet_name": "Swim England Hertfordshire County Championships 25",
    "venue": "St Albans",
    "wa_points": "344",
    "round": "H",
    "level": "2"
  },
  {
    "id": 274,
    "tiref": "1479966",
    "stroke_code": 1,
    "course": "S",
    "date": "25/03/23",
    "time": "37.12",
    "is_pb": 1,
    "meet_name": "Hatfield SC Regional Qualifier 2023",
    "venue": "Hatfield",
    "wa_points": "232",
    "round": "H",
    "level": "3"
  },
  {
    "id": 293,
    "tiref": "1479966",
    "stroke_code": 1,
    "course": "S",
    "date": "25/10/25",
    "time": "32.08",
    "is_pb": 0,
    "meet_name": "Cheshunt SC 20th Annual Open Meet 2025",
    "venue": "Harlow",
    "wa_points": "360",
    "round": "H",
    "level": "3"
  },
  {
    "id": 269,
    "tiref": "1479966",
    "stroke_code": 1,
    "course": "S",
    "date": "26/03/22",
    "time": "40.69",
    "is_pb": 1,
    "meet_name": "Hatfield SC Regional Qualifier",
    "venue": "Hatfield",
    "wa_points": "176",
    "round": "H",
    "level": "3"
  },
  {
    "id": 272,
    "tiref": "1479966",
    "stroke_code": 1,
    "course": "S",
    "date": "26/11/22",
    "time": "39.18",
    "is_pb": 1,
    "meet_name": "Hatfield SC County Qualifier November 2022",
    "venue": "Hatfield",
    "wa_points": "197",
    "round": "H",
    "level": "3"
  },
  {
    "id": 283,
    "tiref": "1479966",
    "stroke_code": 1,
    "course": "S",
    "date": "27/01/24",
    "time": "33.83",
    "is_pb": 1,
    "meet_name": "SE Hertfordshire County Championships 2024",
    "venue": "Borehamwood",
    "wa_points": "307",
    "round": "H",
    "level": "2"
  },
  {
    "id": 294,
    "tiref": "1479966",
    "stroke_code": 1,
    "course": "S",
    "date": "29/11/25",
    "time": "31.90",
    "is_pb": 0,
    "meet_name": "City of St Albans SC Winter Meet 2025",
    "venue": "St Albans",
    "wa_points": "366",
    "round": "F",
    "level": "3"
  },
  {
    "id": 287,
    "tiref": "1479966",
    "stroke_code": 1,
    "course": "S",
    "date": "30/11/24",
    "time": "32.77",
    "is_pb": 1,
    "meet_name": "City of St Albans SC Winter Open Meet 2024",
    "venue": "St Albans",
    "wa_points": "338",
    "round": "F",
    "level": "3"
  },
  {
    "id": 325,
    "tiref": "1479966",
    "stroke_code": 2,
    "course": "L",
    "date": "16/03/24",
    "time": "1:16.38",
    "is_pb": 1,
    "meet_name": "Team Luton March Long Course Meet 2024",
    "venue": "Luton",
    "wa_points": "310",
    "round": "H",
    "level": "1"
  },
  {
    "id": 324,
    "tiref": "1479966",
    "stroke_code": 2,
    "course": "L",
    "date": "16/07/22",
    "time": "1:33.97",
    "is_pb": 1,
    "meet_name": "Team Luton Summer Long Course Meet 2022",
    "venue": "Luton",
    "wa_points": "166",
    "round": "H",
    "level": "3"
  },
  {
    "id": 312,
    "tiref": "1479966",
    "stroke_code": 2,
    "course": "S",
    "date": "02/03/24",
    "time": "1:14.28",
    "is_pb": 0,
    "meet_name": "Watford SC Regional Qualifier 2024",
    "venue": "Watford",
    "wa_points": "309",
    "round": "F",
    "level": "3"
  },
  {
    "id": 305,
    "tiref": "1479966",
    "stroke_code": 2,
    "course": "S",
    "date": "02/07/23",
    "time": "1:22.46",
    "is_pb": 0,
    "meet_name": "Putteridge SC End of Season Summer SC Open 2023",
    "venue": "Luton",
    "wa_points": "226",
    "round": "H",
    "level": "2"
  },
  {
    "id": 304,
    "tiref": "1479966",
    "stroke_code": 2,
    "course": "S",
    "date": "03/06/23",
    "time": "1:22.22",
    "is_pb": 1,
    "meet_name": "Harlow Penguins 2023 10th Eric Shepherd Open Meet",
    "venue": "Harlow",
    "wa_points": "228",
    "round": "H",
    "level": "3"
  },
  {
    "id": 310,
    "tiref": "1479966",
    "stroke_code": 2,
    "course": "S",
    "date": "03/12/23",
    "time": "1:15.33",
    "is_pb": 0,
    "meet_name": "City of St Albans Winter Meet 2023",
    "venue": "St Albans",
    "wa_points": "296",
    "round": "F",
    "level": "3"
  },
  {
    "id": 323,
    "tiref": "1479966",
    "stroke_code": 2,
    "course": "S",
    "date": "07/03/26",
    "time": "1:08.94",
    "is_pb": 1,
    "meet_name": "Watford SC Regional Qualifier Open Meet",
    "venue": "Watford",
    "wa_points": "387",
    "round": "F",
    "level": "3"
  },
  {
    "id": 308,
    "tiref": "1479966",
    "stroke_code": 2,
    "course": "S",
    "date": "08/10/23",
    "time": "1:14.88",
    "is_pb": 1,
    "meet_name": "Hatfield SC Regional Qualifier Oct 2023",
    "venue": "Hatfield",
    "wa_points": "302",
    "round": "H",
    "level": "3"
  },
  {
    "id": 316,
    "tiref": "1479966",
    "stroke_code": 2,
    "course": "S",
    "date": "09/03/25",
    "time": "1:09.50",
    "is_pb": 1,
    "meet_name": "City of St Albans Spring Meet 2025",
    "venue": "St Albans",
    "wa_points": "377",
    "round": "F",
    "level": "3"
  },
  {
    "id": 313,
    "tiref": "1479966",
    "stroke_code": 2,
    "course": "S",
    "date": "10/03/24",
    "time": "1:14.00",
    "is_pb": 0,
    "meet_name": "City of St Albans Spring Meet 2024",
    "venue": "St Albans",
    "wa_points": "313",
    "round": "F",
    "level": "3"
  },
  {
    "id": 302,
    "tiref": "1479966",
    "stroke_code": 2,
    "course": "S",
    "date": "12/03/23",
    "time": "1:25.03",
    "is_pb": 1,
    "meet_name": "Basildon & Phoenix Spring Regional Qualifier 2023",
    "venue": "Basildon",
    "wa_points": "206",
    "round": "H",
    "level": "3"
  },
  {
    "id": 317,
    "tiref": "1479966",
    "stroke_code": 2,
    "course": "S",
    "date": "15/03/25",
    "time": "1:10.65",
    "is_pb": 0,
    "meet_name": "Watford SC Regional Qualifier",
    "venue": "Garston",
    "wa_points": "359",
    "round": "F",
    "level": "3"
  },
  {
    "id": 319,
    "tiref": "1479966",
    "stroke_code": 2,
    "course": "S",
    "date": "15/06/25",
    "time": "1:10.64",
    "is_pb": 0,
    "meet_name": "Watford SC The Terry Davies Legacy Meet 2025",
    "venue": "Watford",
    "wa_points": "359",
    "round": "F",
    "level": "3"
  },
  {
    "id": 321,
    "tiref": "1479966",
    "stroke_code": 2,
    "course": "S",
    "date": "15/11/25",
    "time": "1:09.62",
    "is_pb": 0,
    "meet_name": "Putteridge SC Winter Short Course Open 2025",
    "venue": "Luton",
    "wa_points": "376",
    "round": "H",
    "level": "3"
  },
  {
    "id": 306,
    "tiref": "1479966",
    "stroke_code": 2,
    "course": "S",
    "date": "16/09/23",
    "time": "1:20.31",
    "is_pb": 1,
    "meet_name": "City of St Albans Club Champs 2023",
    "venue": "St Albans",
    "wa_points": "244",
    "round": "F",
    "level": "4"
  },
  {
    "id": 318,
    "tiref": "1479966",
    "stroke_code": 2,
    "course": "S",
    "date": "17/05/25",
    "time": "1:11.94",
    "is_pb": 0,
    "meet_name": "Cheshunt SC May Anniversary Meet 2025",
    "venue": "Harlow",
    "wa_points": "340",
    "round": "H",
    "level": "3"
  },
  {
    "id": 309,
    "tiref": "1479966",
    "stroke_code": 2,
    "course": "S",
    "date": "18/11/23",
    "time": "1:13.83",
    "is_pb": 1,
    "meet_name": "Watford SC County Qualifier 2023",
    "venue": "Watford",
    "wa_points": "315",
    "round": "F",
    "level": "3"
  },
  {
    "id": 311,
    "tiref": "1479966",
    "stroke_code": 2,
    "course": "S",
    "date": "20/01/24",
    "time": "1:16.52",
    "is_pb": 0,
    "meet_name": "SE Hertfordshire County Championships 2024",
    "venue": "Borehamwood",
    "wa_points": "283",
    "round": "H",
    "level": "2"
  },
  {
    "id": 320,
    "tiref": "1479966",
    "stroke_code": 2,
    "course": "S",
    "date": "20/09/25",
    "time": "1:10.84",
    "is_pb": 0,
    "meet_name": "Co St Albans Autumn Meet 2025",
    "venue": "St Albans",
    "wa_points": "356",
    "round": "F",
    "level": "3"
  },
  {
    "id": 300,
    "tiref": "1479966",
    "stroke_code": 2,
    "course": "S",
    "date": "21/05/22",
    "time": "1:38.37",
    "is_pb": 1,
    "meet_name": "Cheshunt SC Anniversary Open Meet 2022",
    "venue": "Harlow",
    "wa_points": "133",
    "round": "H",
    "level": "3"
  },
  {
    "id": 314,
    "tiref": "1479966",
    "stroke_code": 2,
    "course": "S",
    "date": "21/09/24",
    "time": "1:14.34",
    "is_pb": 0,
    "meet_name": "Co St Albans Autumn Sprint Meet 2024",
    "venue": "St Albans",
    "wa_points": "308",
    "round": "F",
    "level": "3"
  },
  {
    "id": 307,
    "tiref": "1479966",
    "stroke_code": 2,
    "course": "S",
    "date": "23/09/23",
    "time": "1:16.39",
    "is_pb": 1,
    "meet_name": "Co St Albans SC Sprint & Skins Competition 2023",
    "venue": "St Albans",
    "wa_points": "284",
    "round": "F",
    "level": "3"
  },
  {
    "id": 315,
    "tiref": "1479966",
    "stroke_code": 2,
    "course": "S",
    "date": "24/11/24",
    "time": "1:14.92",
    "is_pb": 0,
    "meet_name": "Hatfield County Qualifier November 2024",
    "venue": "Hatfield",
    "wa_points": "301",
    "round": "H",
    "level": "3"
  },
  {
    "id": 303,
    "tiref": "1479966",
    "stroke_code": 2,
    "course": "S",
    "date": "26/03/23",
    "time": "1:22.51",
    "is_pb": 1,
    "meet_name": "Hatfield SC Regional Qualifier 2023",
    "venue": "Hatfield",
    "wa_points": "225",
    "round": "H",
    "level": "3"
  },
  {
    "id": 301,
    "tiref": "1479966",
    "stroke_code": 2,
    "course": "S",
    "date": "27/11/22",
    "time": "1:33.68",
    "is_pb": 1,
    "meet_name": "Hatfield SC County Qualifier November 2022",
    "venue": "Hatfield",
    "wa_points": "154",
    "round": "H",
    "level": "3"
  },
  {
    "id": 322,
    "tiref": "1479966",
    "stroke_code": 2,
    "course": "S",
    "date": "30/11/25",
    "time": "1:10.40",
    "is_pb": 0,
    "meet_name": "City of St Albans SC Winter Meet 2025",
    "venue": "St Albans",
    "wa_points": "363",
    "round": "F",
    "level": "3"
  },
  {
    "id": 338,
    "tiref": "1479966",
    "stroke_code": 3,
    "course": "L",
    "date": "17/07/22",
    "time": "3:16.66",
    "is_pb": 1,
    "meet_name": "Team Luton Summer Long Course Meet 2022",
    "venue": "Luton",
    "wa_points": "185",
    "round": "H",
    "level": "3"
  },
  {
    "id": 330,
    "tiref": "1479966",
    "stroke_code": 3,
    "course": "S",
    "date": "07/10/23",
    "time": "2:46.22",
    "is_pb": 1,
    "meet_name": "Hatfield SC Regional Qualifier Oct 2023",
    "venue": "Hatfield",
    "wa_points": "292",
    "round": "H",
    "level": "3"
  },
  {
    "id": 335,
    "tiref": "1479966",
    "stroke_code": 3,
    "course": "S",
    "date": "08/03/25",
    "time": "2:36.48",
    "is_pb": 0,
    "meet_name": "City of St Albans Spring Meet 2025",
    "venue": "St Albans",
    "wa_points": "350",
    "round": "F",
    "level": "3"
  },
  {
    "id": 327,
    "tiref": "1479966",
    "stroke_code": 3,
    "course": "S",
    "date": "11/03/23",
    "time": "3:02.60",
    "is_pb": 1,
    "meet_name": "Basildon & Phoenix Spring Regional Qualifier 2023",
    "venue": "Basildon",
    "wa_points": "220",
    "round": "H",
    "level": "3"
  },
  {
    "id": 336,
    "tiref": "1479966",
    "stroke_code": 3,
    "course": "S",
    "date": "14/06/25",
    "time": "2:33.17",
    "is_pb": 1,
    "meet_name": "Watford SC The Terry Davies Legacy Meet 2025",
    "venue": "Watford",
    "wa_points": "373",
    "round": "F",
    "level": "3"
  },
  {
    "id": 329,
    "tiref": "1479966",
    "stroke_code": 3,
    "course": "S",
    "date": "16/09/23",
    "time": "2:51.84",
    "is_pb": 1,
    "meet_name": "City of St Albans Club Champs 2023",
    "venue": "St Albans",
    "wa_points": "264",
    "round": "F",
    "level": "4"
  },
  {
    "id": 337,
    "tiref": "1479966",
    "stroke_code": 3,
    "course": "S",
    "date": "16/11/25",
    "time": "2:32.77",
    "is_pb": 1,
    "meet_name": "Putteridge SC Winter Short Course Open 2025",
    "venue": "Luton",
    "wa_points": "376",
    "round": "H",
    "level": "3"
  },
  {
    "id": 331,
    "tiref": "1479966",
    "stroke_code": 3,
    "course": "S",
    "date": "19/11/23",
    "time": "2:42.89",
    "is_pb": 1,
    "meet_name": "Watford SC County Qualifier 2023",
    "venue": "Watford",
    "wa_points": "310",
    "round": "F",
    "level": "3"
  },
  {
    "id": 334,
    "tiref": "1479966",
    "stroke_code": 3,
    "course": "S",
    "date": "25/01/25",
    "time": "2:35.11",
    "is_pb": 1,
    "meet_name": "Swim England Hertfordshire County Championships 25",
    "venue": "St Albans",
    "wa_points": "359",
    "round": "H",
    "level": "2"
  },
  {
    "id": 328,
    "tiref": "1479966",
    "stroke_code": 3,
    "course": "S",
    "date": "26/03/23",
    "time": "3:01.63",
    "is_pb": 1,
    "meet_name": "Hatfield SC Regional Qualifier 2023",
    "venue": "Hatfield",
    "wa_points": "224",
    "round": "H",
    "level": "3"
  },
  {
    "id": 326,
    "tiref": "1479966",
    "stroke_code": 3,
    "course": "S",
    "date": "27/11/22",
    "time": "3:09.94",
    "is_pb": 1,
    "meet_name": "Hatfield SC County Qualifier November 2022",
    "venue": "Hatfield",
    "wa_points": "195",
    "round": "H",
    "level": "3"
  },
  {
    "id": 332,
    "tiref": "1479966",
    "stroke_code": 3,
    "course": "S",
    "date": "28/01/24",
    "time": "2:41.63",
    "is_pb": 1,
    "meet_name": "SE Hertfordshire County Championships 2024",
    "venue": "Borehamwood",
    "wa_points": "317",
    "round": "H",
    "level": "2"
  },
  {
    "id": 333,
    "tiref": "1479966",
    "stroke_code": 3,
    "course": "S",
    "date": "30/11/24",
    "time": "2:38.29",
    "is_pb": 1,
    "meet_name": "City of St Albans SC Winter Open Meet 2024",
    "venue": "St Albans",
    "wa_points": "338",
    "round": "F",
    "level": "3"
  },
  {
    "id": 344,
    "tiref": "1479966",
    "stroke_code": 4,
    "course": "L",
    "date": "11/05/24",
    "time": "5:50.22",
    "is_pb": 1,
    "meet_name": "Swim England East Region LC Championships 2024",
    "venue": "Norwich",
    "wa_points": "298",
    "round": "H",
    "level": "1"
  },
  {
    "id": 343,
    "tiref": "1479966",
    "stroke_code": 4,
    "course": "L",
    "date": "17/03/24",
    "time": "5:58.80",
    "is_pb": 1,
    "meet_name": "Team Luton March Long Course Meet 2024",
    "venue": "Luton",
    "wa_points": "278",
    "round": "H",
    "level": "1"
  },
  {
    "id": 341,
    "tiref": "1479966",
    "stroke_code": 4,
    "course": "S",
    "date": "03/03/24",
    "time": "5:48.36",
    "is_pb": 0,
    "meet_name": "Watford SC Regional Qualifier 2024",
    "venue": "Watford",
    "wa_points": "288",
    "round": "F",
    "level": "3"
  },
  {
    "id": 342,
    "tiref": "1479966",
    "stroke_code": 4,
    "course": "S",
    "date": "10/11/24",
    "time": "5:47.52",
    "is_pb": 0,
    "meet_name": "Co St Albans Long Distance Club Champs 2024",
    "venue": "St Albans",
    "wa_points": "290",
    "round": "F",
    "level": "3"
  },
  {
    "id": 339,
    "tiref": "1479966",
    "stroke_code": 4,
    "course": "S",
    "date": "26/11/23",
    "time": "5:41.63",
    "is_pb": 1,
    "meet_name": "Co St Albans & Watford SCs Joint Club Champs 2023",
    "venue": "St Albans",
    "wa_points": "306",
    "round": "F",
    "level": "3"
  },
  {
    "id": 340,
    "tiref": "1479966",
    "stroke_code": 4,
    "course": "S",
    "date": "27/01/24",
    "time": "5:32.90",
    "is_pb": 1,
    "meet_name": "SE Hertfordshire County Championships 2024",
    "venue": "Borehamwood",
    "wa_points": "330",
    "round": "H",
    "level": "2"
  },
  {
    "id": 352,
    "tiref": "1479966",
    "stroke_code": 7,
    "course": "S",
    "date": "01/07/23",
    "time": "50.47",
    "is_pb": 0,
    "meet_name": "Putteridge SC End of Season Summer SC Open 2023",
    "venue": "Luton",
    "wa_points": "177",
    "round": "H",
    "level": "2"
  },
  {
    "id": 358,
    "tiref": "1479966",
    "stroke_code": 7,
    "course": "S",
    "date": "02/03/24",
    "time": "46.18",
    "is_pb": 0,
    "meet_name": "Watford SC Regional Qualifier 2024",
    "venue": "Watford",
    "wa_points": "231",
    "round": "F",
    "level": "3"
  },
  {
    "id": 356,
    "tiref": "1479966",
    "stroke_code": 7,
    "course": "S",
    "date": "03/12/23",
    "time": "46.67",
    "is_pb": 1,
    "meet_name": "City of St Albans Winter Meet 2023",
    "venue": "St Albans",
    "wa_points": "224",
    "round": "F",
    "level": "3"
  },
  {
    "id": 345,
    "tiref": "1479966",
    "stroke_code": 7,
    "course": "S",
    "date": "04/07/21",
    "time": "1:03.75",
    "is_pb": 1,
    "meet_name": "Hertford Mini Club Championships",
    "venue": "Haileybury",
    "wa_points": "88",
    "round": "F",
    "level": "4"
  },
  {
    "id": 359,
    "tiref": "1479966",
    "stroke_code": 7,
    "course": "S",
    "date": "07/06/24",
    "time": "46.54",
    "is_pb": 0,
    "meet_name": "Herts & St Albans SSA Primary Schools Champs 2024",
    "venue": "St Albans",
    "wa_points": "226",
    "round": "F",
    "level": "4"
  },
  {
    "id": 354,
    "tiref": "1479966",
    "stroke_code": 7,
    "course": "S",
    "date": "08/10/23",
    "time": "48.33",
    "is_pb": 1,
    "meet_name": "Hatfield SC Regional Qualifier Oct 2023",
    "venue": "Hatfield",
    "wa_points": "202",
    "round": "H",
    "level": "3"
  },
  {
    "id": 349,
    "tiref": "1479966",
    "stroke_code": 7,
    "course": "S",
    "date": "09/10/22",
    "time": "55.54",
    "is_pb": 0,
    "meet_name": "Hatfield SC Club Championships 2022",
    "venue": "Hatfield",
    "wa_points": "133",
    "round": "H",
    "level": "4"
  },
  {
    "id": 346,
    "tiref": "1479966",
    "stroke_code": 7,
    "course": "S",
    "date": "10/10/21",
    "time": "1:02.31",
    "is_pb": 1,
    "meet_name": "Hatfield Club Championships 2021",
    "venue": "Hatfield",
    "wa_points": "94",
    "round": "H",
    "level": "4"
  },
  {
    "id": 351,
    "tiref": "1479966",
    "stroke_code": 7,
    "course": "S",
    "date": "12/03/23",
    "time": "50.24",
    "is_pb": 1,
    "meet_name": "Basildon & Phoenix Spring Regional Qualifier 2023",
    "venue": "Basildon",
    "wa_points": "180",
    "round": "H",
    "level": "3"
  },
  {
    "id": 361,
    "tiref": "1479966",
    "stroke_code": 7,
    "course": "S",
    "date": "15/03/25",
    "time": "45.67",
    "is_pb": 0,
    "meet_name": "Watford SC Regional Qualifier",
    "venue": "Garston",
    "wa_points": "239",
    "round": "F",
    "level": "3"
  },
  {
    "id": 355,
    "tiref": "1479966",
    "stroke_code": 7,
    "course": "S",
    "date": "19/11/23",
    "time": "47.53",
    "is_pb": 1,
    "meet_name": "Watford SC County Qualifier 2023",
    "venue": "Watford",
    "wa_points": "212",
    "round": "F",
    "level": "3"
  },
  {
    "id": 348,
    "tiref": "1479966",
    "stroke_code": 7,
    "course": "S",
    "date": "21/05/22",
    "time": "54.78",
    "is_pb": 1,
    "meet_name": "Cheshunt SC Anniversary Open Meet 2022",
    "venue": "Harlow",
    "wa_points": "138",
    "round": "H",
    "level": "3"
  },
  {
    "id": 353,
    "tiref": "1479966",
    "stroke_code": 7,
    "course": "S",
    "date": "23/09/23",
    "time": "49.83",
    "is_pb": 1,
    "meet_name": "Co St Albans SC Sprint & Skins Competition 2023",
    "venue": "St Albans",
    "wa_points": "184",
    "round": "F",
    "level": "3"
  },
  {
    "id": 360,
    "tiref": "1479966",
    "stroke_code": 7,
    "course": "S",
    "date": "24/11/24",
    "time": "44.59",
    "is_pb": 1,
    "meet_name": "Hatfield County Qualifier November 2024",
    "venue": "Hatfield",
    "wa_points": "257",
    "round": "H",
    "level": "3"
  },
  {
    "id": 347,
    "tiref": "1479966",
    "stroke_code": 7,
    "course": "S",
    "date": "27/03/22",
    "time": "57.25",
    "is_pb": 1,
    "meet_name": "Hatfield SC Regional Qualifier",
    "venue": "Hatfield",
    "wa_points": "121",
    "round": "H",
    "level": "3"
  },
  {
    "id": 350,
    "tiref": "1479966",
    "stroke_code": 7,
    "course": "S",
    "date": "27/11/22",
    "time": "54.05",
    "is_pb": 1,
    "meet_name": "Hatfield SC County Qualifier November 2022",
    "venue": "Hatfield",
    "wa_points": "144",
    "round": "H",
    "level": "3"
  },
  {
    "id": 357,
    "tiref": "1479966",
    "stroke_code": 7,
    "course": "S",
    "date": "28/01/24",
    "time": "46.05",
    "is_pb": 1,
    "meet_name": "SE Hertfordshire County Championships 2024",
    "venue": "Borehamwood",
    "wa_points": "233",
    "round": "H",
    "level": "2"
  },
  {
    "id": 366,
    "tiref": "1479966",
    "stroke_code": 8,
    "course": "L",
    "date": "16/07/22",
    "time": "2:01.60",
    "is_pb": 1,
    "meet_name": "Team Luton Summer Long Course Meet 2022",
    "venue": "Luton",
    "wa_points": "146",
    "round": "H",
    "level": "3"
  },
  {
    "id": 363,
    "tiref": "1479966",
    "stroke_code": 8,
    "course": "S",
    "date": "01/10/23",
    "time": "1:49.58",
    "is_pb": 1,
    "meet_name": "City of St Albans Club Champs 2023",
    "venue": "St Albans",
    "wa_points": "184",
    "round": "F",
    "level": "4"
  },
  {
    "id": 362,
    "tiref": "1479966",
    "stroke_code": 8,
    "course": "S",
    "date": "16/10/22",
    "time": "1:59.87",
    "is_pb": 1,
    "meet_name": "Hatfield SC Club Championships 2022",
    "venue": "Hatfield",
    "wa_points": "140",
    "round": "H",
    "level": "4"
  },
  {
    "id": 364,
    "tiref": "1479966",
    "stroke_code": 8,
    "course": "S",
    "date": "18/11/23",
    "time": "1:40.40",
    "is_pb": 1,
    "meet_name": "Watford SC County Qualifier 2023",
    "venue": "Watford",
    "wa_points": "239",
    "round": "F",
    "level": "3"
  },
  {
    "id": 365,
    "tiref": "1479966",
    "stroke_code": 8,
    "course": "S",
    "date": "21/01/24",
    "time": "1:42.88",
    "is_pb": 0,
    "meet_name": "SE Hertfordshire County Championships 2024",
    "venue": "Borehamwood",
    "wa_points": "222",
    "round": "H",
    "level": "2"
  },
  {
    "id": 369,
    "tiref": "1479966",
    "stroke_code": 9,
    "course": "L",
    "date": "17/07/22",
    "time": "4:32.80",
    "is_pb": 1,
    "meet_name": "Team Luton Summer Long Course Meet 2022",
    "venue": "Luton",
    "wa_points": "128",
    "round": "H",
    "level": "3"
  },
  {
    "id": 367,
    "tiref": "1479966",
    "stroke_code": 9,
    "course": "S",
    "date": "27/11/22",
    "time": "4:07.22",
    "is_pb": 1,
    "meet_name": "Hatfield SC County Qualifier November 2022",
    "venue": "Hatfield",
    "wa_points": "153",
    "round": "H",
    "level": "3"
  },
  {
    "id": 368,
    "tiref": "1479966",
    "stroke_code": 9,
    "course": "S",
    "date": "27/11/22",
    "time": "4:08.67",
    "is_pb": 0,
    "meet_name": "Hatfield SC County Qualifier November 2022",
    "venue": "Hatfield",
    "wa_points": "151",
    "round": "F",
    "level": "3"
  },
  {
    "id": 401,
    "tiref": "1479966",
    "stroke_code": 10,
    "course": "L",
    "date": "12/05/24",
    "time": "37.37",
    "is_pb": 1,
    "meet_name": "Swim England East Region LC Championships 2024",
    "venue": "Norwich",
    "wa_points": "279",
    "round": "H",
    "level": "1"
  },
  {
    "id": 400,
    "tiref": "1479966",
    "stroke_code": 10,
    "course": "L",
    "date": "17/07/22",
    "time": "49.38",
    "is_pb": 1,
    "meet_name": "Team Luton Summer Long Course Meet 2022",
    "venue": "Luton",
    "wa_points": "121",
    "round": "H",
    "level": "3"
  },
  {
    "id": 379,
    "tiref": "1479966",
    "stroke_code": 10,
    "course": "S",
    "date": "02/07/23",
    "time": "40.72",
    "is_pb": 1,
    "meet_name": "Putteridge SC End of Season Summer SC Open 2023",
    "venue": "Luton",
    "wa_points": "203",
    "round": "H",
    "level": "2"
  },
  {
    "id": 385,
    "tiref": "1479966",
    "stroke_code": 10,
    "course": "S",
    "date": "03/03/24",
    "time": "37.15",
    "is_pb": 0,
    "meet_name": "Watford SC Regional Qualifier 2024",
    "venue": "Watford",
    "wa_points": "267",
    "round": "F",
    "level": "3"
  },
  {
    "id": 382,
    "tiref": "1479966",
    "stroke_code": 10,
    "course": "S",
    "date": "03/12/23",
    "time": "36.56",
    "is_pb": 1,
    "meet_name": "City of St Albans Winter Meet 2023",
    "venue": "St Albans",
    "wa_points": "280",
    "round": "F",
    "level": "3"
  },
  {
    "id": 386,
    "tiref": "1479966",
    "stroke_code": 10,
    "course": "S",
    "date": "07/06/24",
    "time": "36.77",
    "is_pb": 0,
    "meet_name": "Herts & St Albans SSA Primary Schools Champs 2024",
    "venue": "St Albans",
    "wa_points": "275",
    "round": "F",
    "level": "4"
  },
  {
    "id": 380,
    "tiref": "1479966",
    "stroke_code": 10,
    "course": "S",
    "date": "08/10/23",
    "time": "39.26",
    "is_pb": 1,
    "meet_name": "Hatfield SC Regional Qualifier Oct 2023",
    "venue": "Hatfield",
    "wa_points": "226",
    "round": "H",
    "level": "3"
  },
  {
    "id": 390,
    "tiref": "1479966",
    "stroke_code": 10,
    "course": "S",
    "date": "09/03/25",
    "time": "34.69",
    "is_pb": 1,
    "meet_name": "City of St Albans Spring Meet 2025",
    "venue": "St Albans",
    "wa_points": "328",
    "round": "F",
    "level": "3"
  },
  {
    "id": 373,
    "tiref": "1479966",
    "stroke_code": 10,
    "course": "S",
    "date": "09/10/22",
    "time": "49.08",
    "is_pb": 1,
    "meet_name": "Hatfield SC Club Championships 2022",
    "venue": "Hatfield",
    "wa_points": "116",
    "round": "H",
    "level": "4"
  },
  {
    "id": 370,
    "tiref": "1479966",
    "stroke_code": 10,
    "course": "S",
    "date": "10/10/21",
    "time": "58.56",
    "is_pb": 1,
    "meet_name": "Hatfield Club Championships 2021",
    "venue": "Hatfield",
    "wa_points": "68",
    "round": "H",
    "level": "4"
  },
  {
    "id": 375,
    "tiref": "1479966",
    "stroke_code": 10,
    "course": "S",
    "date": "11/03/23",
    "time": "43.60",
    "is_pb": 1,
    "meet_name": "Basildon & Phoenix Spring Regional Qualifier 2023",
    "venue": "Basildon",
    "wa_points": "165",
    "round": "H",
    "level": "3"
  },
  {
    "id": 393,
    "tiref": "1479966",
    "stroke_code": 10,
    "course": "S",
    "date": "14/06/25",
    "time": "35.16",
    "is_pb": 0,
    "meet_name": "Watford SC The Terry Davies Legacy Meet 2025",
    "venue": "Watford",
    "wa_points": "315",
    "round": "F",
    "level": "3"
  },
  {
    "id": 399,
    "tiref": "1479966",
    "stroke_code": 10,
    "course": "S",
    "date": "15/03/26",
    "time": "33.81",
    "is_pb": 1,
    "meet_name": "City of St Albans Spring Meet 2026",
    "venue": "St Albans",
    "wa_points": "355",
    "round": "F",
    "level": "3"
  },
  {
    "id": 391,
    "tiref": "1479966",
    "stroke_code": 10,
    "course": "S",
    "date": "16/03/25",
    "time": "34.10",
    "is_pb": 1,
    "meet_name": "Watford SC Regional Qualifier",
    "venue": "Garston",
    "wa_points": "346",
    "round": "F",
    "level": "3"
  },
  {
    "id": 396,
    "tiref": "1479966",
    "stroke_code": 10,
    "course": "S",
    "date": "16/11/25",
    "time": "35.04",
    "is_pb": 0,
    "meet_name": "Putteridge SC Winter Short Course Open 2025",
    "venue": "Luton",
    "wa_points": "318",
    "round": "H",
    "level": "3"
  },
  {
    "id": 392,
    "tiref": "1479966",
    "stroke_code": 10,
    "course": "S",
    "date": "17/05/25",
    "time": "36.80",
    "is_pb": 0,
    "meet_name": "Cheshunt SC May Anniversary Meet 2025",
    "venue": "Harlow",
    "wa_points": "275",
    "round": "H",
    "level": "3"
  },
  {
    "id": 381,
    "tiref": "1479966",
    "stroke_code": 10,
    "course": "S",
    "date": "18/11/23",
    "time": "37.64",
    "is_pb": 1,
    "meet_name": "Watford SC County Qualifier 2023",
    "venue": "Watford",
    "wa_points": "257",
    "round": "F",
    "level": "3"
  },
  {
    "id": 377,
    "tiref": "1479966",
    "stroke_code": 10,
    "course": "S",
    "date": "19/05/23",
    "time": "45.10",
    "is_pb": 0,
    "meet_name": "HSSA StASSA Primary Schools Champs 2023",
    "venue": "St Albans",
    "wa_points": "149",
    "round": "F",
    "level": "4"
  },
  {
    "id": 394,
    "tiref": "1479966",
    "stroke_code": 10,
    "course": "S",
    "date": "20/09/25",
    "time": "35.21",
    "is_pb": 0,
    "meet_name": "Co St Albans Autumn Meet 2025",
    "venue": "St Albans",
    "wa_points": "314",
    "round": "F",
    "level": "3"
  },
  {
    "id": 372,
    "tiref": "1479966",
    "stroke_code": 10,
    "course": "S",
    "date": "21/05/22",
    "time": "51.76",
    "is_pb": 1,
    "meet_name": "Cheshunt SC Anniversary Open Meet 2022",
    "venue": "Harlow",
    "wa_points": "98",
    "round": "H",
    "level": "3"
  },
  {
    "id": 387,
    "tiref": "1479966",
    "stroke_code": 10,
    "course": "S",
    "date": "21/09/24",
    "time": "38.48",
    "is_pb": 0,
    "meet_name": "Co St Albans Autumn Sprint Meet 2024",
    "venue": "St Albans",
    "wa_points": "240",
    "round": "F",
    "level": "3"
  },
  {
    "id": 378,
    "tiref": "1479966",
    "stroke_code": 10,
    "course": "S",
    "date": "24/06/23",
    "time": "42.20",
    "is_pb": 1,
    "meet_name": "City of St Albans SC End of Season Meet 2023",
    "venue": "St Albans",
    "wa_points": "182",
    "round": "F",
    "level": "3"
  },
  {
    "id": 388,
    "tiref": "1479966",
    "stroke_code": 10,
    "course": "S",
    "date": "24/11/24",
    "time": "37.86",
    "is_pb": 0,
    "meet_name": "Hatfield County Qualifier November 2024",
    "venue": "Hatfield",
    "wa_points": "252",
    "round": "H",
    "level": "3"
  },
  {
    "id": 398,
    "tiref": "1479966",
    "stroke_code": 10,
    "course": "S",
    "date": "25/01/26",
    "time": "34.20",
    "is_pb": 0,
    "meet_name": "SE Hertfordshire County Championships 2026",
    "venue": "St Albans",
    "wa_points": "342",
    "round": "H",
    "level": "2"
  },
  {
    "id": 376,
    "tiref": "1479966",
    "stroke_code": 10,
    "course": "S",
    "date": "25/03/23",
    "time": "45.55",
    "is_pb": 0,
    "meet_name": "Hatfield SC Regional Qualifier 2023",
    "venue": "Hatfield",
    "wa_points": "145",
    "round": "H",
    "level": "3"
  },
  {
    "id": 395,
    "tiref": "1479966",
    "stroke_code": 10,
    "course": "S",
    "date": "25/10/25",
    "time": "36.29",
    "is_pb": 0,
    "meet_name": "Cheshunt SC 20th Annual Open Meet 2025",
    "venue": "Harlow",
    "wa_points": "287",
    "round": "H",
    "level": "3"
  },
  {
    "id": 389,
    "tiref": "1479966",
    "stroke_code": 10,
    "course": "S",
    "date": "26/01/25",
    "time": "36.68",
    "is_pb": 0,
    "meet_name": "Swim England Hertfordshire County Championships 25",
    "venue": "St Albans",
    "wa_points": "278",
    "round": "H",
    "level": "2"
  },
  {
    "id": 371,
    "tiref": "1479966",
    "stroke_code": 10,
    "course": "S",
    "date": "26/03/22",
    "time": "55.19",
    "is_pb": 1,
    "meet_name": "Hatfield SC Regional Qualifier",
    "venue": "Hatfield",
    "wa_points": "81",
    "round": "H",
    "level": "3"
  },
  {
    "id": 374,
    "tiref": "1479966",
    "stroke_code": 10,
    "course": "S",
    "date": "26/11/22",
    "time": "47.39",
    "is_pb": 1,
    "meet_name": "Hatfield SC County Qualifier November 2022",
    "venue": "Hatfield",
    "wa_points": "128",
    "round": "H",
    "level": "3"
  },
  {
    "id": 383,
    "tiref": "1479966",
    "stroke_code": 10,
    "course": "S",
    "date": "28/01/24",
    "time": "37.99",
    "is_pb": 0,
    "meet_name": "SE Hertfordshire County Championships 2024",
    "venue": "Borehamwood",
    "wa_points": "250",
    "round": "F",
    "level": "2"
  },
  {
    "id": 384,
    "tiref": "1479966",
    "stroke_code": 10,
    "course": "S",
    "date": "28/01/24",
    "time": "38.52",
    "is_pb": 0,
    "meet_name": "SE Hertfordshire County Championships 2024",
    "venue": "Borehamwood",
    "wa_points": "240",
    "round": "H",
    "level": "2"
  },
  {
    "id": 397,
    "tiref": "1479966",
    "stroke_code": 10,
    "course": "S",
    "date": "30/11/25",
    "time": "35.49",
    "is_pb": 0,
    "meet_name": "City of St Albans SC Winter Meet 2025",
    "venue": "St Albans",
    "wa_points": "306",
    "round": "F",
    "level": "3"
  },
  {
    "id": 409,
    "tiref": "1479966",
    "stroke_code": 11,
    "course": "L",
    "date": "17/03/24",
    "time": "1:32.79",
    "is_pb": 1,
    "meet_name": "Team Luton March Long Course Meet 2024",
    "venue": "Luton",
    "wa_points": "203",
    "round": "H",
    "level": "1"
  },
  {
    "id": 404,
    "tiref": "1479966",
    "stroke_code": 11,
    "course": "S",
    "date": "03/12/23",
    "time": "1:29.08",
    "is_pb": 1,
    "meet_name": "City of St Albans Winter Meet 2023",
    "venue": "St Albans",
    "wa_points": "207",
    "round": "F",
    "level": "3"
  },
  {
    "id": 407,
    "tiref": "1479966",
    "stroke_code": 11,
    "course": "S",
    "date": "09/03/24",
    "time": "1:31.06",
    "is_pb": 0,
    "meet_name": "City of St Albans Spring Meet 2024",
    "venue": "St Albans",
    "wa_points": "193",
    "round": "F",
    "level": "3"
  },
  {
    "id": 402,
    "tiref": "1479966",
    "stroke_code": 11,
    "course": "S",
    "date": "16/09/23",
    "time": "1:36.99",
    "is_pb": 1,
    "meet_name": "City of St Albans Club Champs 2023",
    "venue": "St Albans",
    "wa_points": "160",
    "round": "F",
    "level": "4"
  },
  {
    "id": 405,
    "tiref": "1479966",
    "stroke_code": 11,
    "course": "S",
    "date": "20/01/24",
    "time": "1:32.75",
    "is_pb": 0,
    "meet_name": "SE Hertfordshire County Championships 2024",
    "venue": "Borehamwood",
    "wa_points": "183",
    "round": "H",
    "level": "2"
  },
  {
    "id": 406,
    "tiref": "1479966",
    "stroke_code": 11,
    "course": "S",
    "date": "20/01/24",
    "time": "1:33.10",
    "is_pb": 0,
    "meet_name": "SE Hertfordshire County Championships 2024",
    "venue": "Borehamwood",
    "wa_points": "181",
    "round": "F",
    "level": "2"
  },
  {
    "id": 403,
    "tiref": "1479966",
    "stroke_code": 11,
    "course": "S",
    "date": "23/09/23",
    "time": "1:38.07",
    "is_pb": 0,
    "meet_name": "Co St Albans SC Sprint & Skins Competition 2023",
    "venue": "St Albans",
    "wa_points": "155",
    "round": "F",
    "level": "3"
  },
  {
    "id": 408,
    "tiref": "1479966",
    "stroke_code": 11,
    "course": "S",
    "date": "30/11/24",
    "time": "1:29.39",
    "is_pb": 0,
    "meet_name": "City of St Albans SC Winter Open Meet 2024",
    "venue": "St Albans",
    "wa_points": "205",
    "round": "F",
    "level": "3"
  },
  {
    "id": 446,
    "tiref": "1479966",
    "stroke_code": 13,
    "course": "L",
    "date": "16/03/24",
    "time": "41.11",
    "is_pb": 1,
    "meet_name": "Team Luton March Long Course Meet 2024",
    "venue": "Luton",
    "wa_points": "278",
    "round": "H",
    "level": "1"
  },
  {
    "id": 445,
    "tiref": "1479966",
    "stroke_code": 13,
    "course": "L",
    "date": "16/07/22",
    "time": "46.32",
    "is_pb": 1,
    "meet_name": "Team Luton Summer Long Course Meet 2022",
    "venue": "Luton",
    "wa_points": "194",
    "round": "H",
    "level": "3"
  },
  {
    "id": 426,
    "tiref": "1479966",
    "stroke_code": 13,
    "course": "S",
    "date": "02/03/24",
    "time": "40.67",
    "is_pb": 0,
    "meet_name": "Watford SC Regional Qualifier 2024",
    "venue": "Watford",
    "wa_points": "238",
    "round": "F",
    "level": "3"
  },
  {
    "id": 420,
    "tiref": "1479966",
    "stroke_code": 13,
    "course": "S",
    "date": "02/07/23",
    "time": "42.12",
    "is_pb": 1,
    "meet_name": "Putteridge SC End of Season Summer SC Open 2023",
    "venue": "Luton",
    "wa_points": "214",
    "round": "H",
    "level": "2"
  },
  {
    "id": 424,
    "tiref": "1479966",
    "stroke_code": 13,
    "course": "S",
    "date": "02/12/23",
    "time": "40.14",
    "is_pb": 0,
    "meet_name": "City of St Albans Winter Meet 2023",
    "venue": "St Albans",
    "wa_points": "248",
    "round": "F",
    "level": "3"
  },
  {
    "id": 418,
    "tiref": "1479966",
    "stroke_code": 13,
    "course": "S",
    "date": "03/06/23",
    "time": "42.48",
    "is_pb": 1,
    "meet_name": "Harlow Penguins 2023 10th Eric Shepherd Open Meet",
    "venue": "Harlow",
    "wa_points": "209",
    "round": "H",
    "level": "3"
  },
  {
    "id": 414,
    "tiref": "1479966",
    "stroke_code": 13,
    "course": "S",
    "date": "03/12/22",
    "time": "46.86",
    "is_pb": 0,
    "meet_name": "Basildon & Phoenix SC Last Chance County Qualifier",
    "venue": "Basildon",
    "wa_points": "156",
    "round": "H",
    "level": "3"
  },
  {
    "id": 410,
    "tiref": "1479966",
    "stroke_code": 13,
    "course": "S",
    "date": "04/07/21",
    "time": "58.51",
    "is_pb": 1,
    "meet_name": "Hertford Mini Club Championships",
    "venue": "Haileybury",
    "wa_points": "80",
    "round": "F",
    "level": "4"
  },
  {
    "id": 443,
    "tiref": "1479966",
    "stroke_code": 13,
    "course": "S",
    "date": "07/03/26",
    "time": "37.82",
    "is_pb": 0,
    "meet_name": "Watford SC Regional Qualifier Open Meet",
    "venue": "Watford",
    "wa_points": "296",
    "round": "F",
    "level": "3"
  },
  {
    "id": 428,
    "tiref": "1479966",
    "stroke_code": 13,
    "course": "S",
    "date": "07/06/24",
    "time": "40.14",
    "is_pb": 0,
    "meet_name": "Herts & St Albans SSA Primary Schools Champs 2024",
    "venue": "St Albans",
    "wa_points": "248",
    "round": "F",
    "level": "4"
  },
  {
    "id": 434,
    "tiref": "1479966",
    "stroke_code": 13,
    "course": "S",
    "date": "08/03/25",
    "time": "37.36",
    "is_pb": 1,
    "meet_name": "City of St Albans Spring Meet 2025",
    "venue": "St Albans",
    "wa_points": "307",
    "round": "F",
    "level": "3"
  },
  {
    "id": 422,
    "tiref": "1479966",
    "stroke_code": 13,
    "course": "S",
    "date": "08/10/23",
    "time": "39.40",
    "is_pb": 1,
    "meet_name": "Hatfield SC Regional Qualifier Oct 2023",
    "venue": "Hatfield",
    "wa_points": "262",
    "round": "H",
    "level": "3"
  },
  {
    "id": 432,
    "tiref": "1479966",
    "stroke_code": 13,
    "course": "S",
    "date": "08/12/24",
    "time": "39.10",
    "is_pb": 1,
    "meet_name": "Team Luton 2024 Winter Development Meet",
    "venue": "Luton",
    "wa_points": "268",
    "round": "H",
    "level": "3"
  },
  {
    "id": 427,
    "tiref": "1479966",
    "stroke_code": 13,
    "course": "S",
    "date": "09/03/24",
    "time": "39.88",
    "is_pb": 0,
    "meet_name": "City of St Albans Spring Meet 2024",
    "venue": "St Albans",
    "wa_points": "253",
    "round": "F",
    "level": "3"
  },
  {
    "id": 415,
    "tiref": "1479966",
    "stroke_code": 13,
    "course": "S",
    "date": "12/03/23",
    "time": "44.70",
    "is_pb": 1,
    "meet_name": "Basildon & Phoenix Spring Regional Qualifier 2023",
    "venue": "Basildon",
    "wa_points": "179",
    "round": "H",
    "level": "3"
  },
  {
    "id": 444,
    "tiref": "1479966",
    "stroke_code": 13,
    "course": "S",
    "date": "14/03/26",
    "time": "35.47",
    "is_pb": 1,
    "meet_name": "City of St Albans Spring Meet 2026",
    "venue": "St Albans",
    "wa_points": "359",
    "round": "F",
    "level": "3"
  },
  {
    "id": 437,
    "tiref": "1479966",
    "stroke_code": 13,
    "course": "S",
    "date": "14/06/25",
    "time": "38.48",
    "is_pb": 0,
    "meet_name": "Watford SC The Terry Davies Legacy Meet 2025",
    "venue": "Watford",
    "wa_points": "281",
    "round": "F",
    "level": "3"
  },
  {
    "id": 435,
    "tiref": "1479966",
    "stroke_code": 13,
    "course": "S",
    "date": "15/03/25",
    "time": "38.04",
    "is_pb": 0,
    "meet_name": "Watford SC Regional Qualifier",
    "venue": "Garston",
    "wa_points": "291",
    "round": "F",
    "level": "3"
  },
  {
    "id": 440,
    "tiref": "1479966",
    "stroke_code": 13,
    "course": "S",
    "date": "15/11/25",
    "time": "35.78",
    "is_pb": 1,
    "meet_name": "Putteridge SC Winter Short Course Open 2025",
    "venue": "Luton",
    "wa_points": "350",
    "round": "H",
    "level": "3"
  },
  {
    "id": 436,
    "tiref": "1479966",
    "stroke_code": 13,
    "course": "S",
    "date": "17/05/25",
    "time": "37.86",
    "is_pb": 0,
    "meet_name": "Cheshunt SC May Anniversary Meet 2025",
    "venue": "Harlow",
    "wa_points": "295",
    "round": "H",
    "level": "3"
  },
  {
    "id": 417,
    "tiref": "1479966",
    "stroke_code": 13,
    "course": "S",
    "date": "19/05/23",
    "time": "43.58",
    "is_pb": 1,
    "meet_name": "HSSA StASSA Primary Schools Champs 2023",
    "venue": "St Albans",
    "wa_points": "194",
    "round": "F",
    "level": "4"
  },
  {
    "id": 423,
    "tiref": "1479966",
    "stroke_code": 13,
    "course": "S",
    "date": "19/11/23",
    "time": "40.78",
    "is_pb": 0,
    "meet_name": "Watford SC County Qualifier 2023",
    "venue": "Watford",
    "wa_points": "236",
    "round": "F",
    "level": "3"
  },
  {
    "id": 438,
    "tiref": "1479966",
    "stroke_code": 13,
    "course": "S",
    "date": "20/09/25",
    "time": "37.69",
    "is_pb": 0,
    "meet_name": "Co St Albans Autumn Meet 2025",
    "venue": "St Albans",
    "wa_points": "299",
    "round": "F",
    "level": "3"
  },
  {
    "id": 412,
    "tiref": "1479966",
    "stroke_code": 13,
    "course": "S",
    "date": "21/05/22",
    "time": "50.44",
    "is_pb": 0,
    "meet_name": "Cheshunt SC Anniversary Open Meet 2022",
    "venue": "Harlow",
    "wa_points": "125",
    "round": "H",
    "level": "3"
  },
  {
    "id": 429,
    "tiref": "1479966",
    "stroke_code": 13,
    "course": "S",
    "date": "21/09/24",
    "time": "40.23",
    "is_pb": 0,
    "meet_name": "Co St Albans Autumn Sprint Meet 2024",
    "venue": "St Albans",
    "wa_points": "246",
    "round": "F",
    "level": "3"
  },
  {
    "id": 421,
    "tiref": "1479966",
    "stroke_code": 13,
    "course": "S",
    "date": "23/09/23",
    "time": "41.80",
    "is_pb": 1,
    "meet_name": "Co St Albans SC Sprint & Skins Competition 2023",
    "venue": "St Albans",
    "wa_points": "219",
    "round": "F",
    "level": "3"
  },
  {
    "id": 442,
    "tiref": "1479966",
    "stroke_code": 13,
    "course": "S",
    "date": "24/01/26",
    "time": "36.66",
    "is_pb": 0,
    "meet_name": "SE Hertfordshire County Championships 2026",
    "venue": "St Albans",
    "wa_points": "325",
    "round": "H",
    "level": "2"
  },
  {
    "id": 430,
    "tiref": "1479966",
    "stroke_code": 13,
    "course": "S",
    "date": "24/11/24",
    "time": "41.20",
    "is_pb": 0,
    "meet_name": "Hatfield County Qualifier November 2024",
    "venue": "Hatfield",
    "wa_points": "229",
    "round": "H",
    "level": "3"
  },
  {
    "id": 433,
    "tiref": "1479966",
    "stroke_code": 13,
    "course": "S",
    "date": "25/01/25",
    "time": "38.12",
    "is_pb": 1,
    "meet_name": "Swim England Hertfordshire County Championships 25",
    "venue": "St Albans",
    "wa_points": "289",
    "round": "H",
    "level": "2"
  },
  {
    "id": 419,
    "tiref": "1479966",
    "stroke_code": 13,
    "course": "S",
    "date": "25/06/23",
    "time": "43.70",
    "is_pb": 0,
    "meet_name": "City of St Albans SC End of Season Meet 2023",
    "venue": "St Albans",
    "wa_points": "192",
    "round": "F",
    "level": "3"
  },
  {
    "id": 439,
    "tiref": "1479966",
    "stroke_code": 13,
    "course": "S",
    "date": "25/10/25",
    "time": "37.55",
    "is_pb": 0,
    "meet_name": "Cheshunt SC 20th Annual Open Meet 2025",
    "venue": "Harlow",
    "wa_points": "303",
    "round": "H",
    "level": "3"
  },
  {
    "id": 416,
    "tiref": "1479966",
    "stroke_code": 13,
    "course": "S",
    "date": "26/03/23",
    "time": "46.95",
    "is_pb": 0,
    "meet_name": "Hatfield SC Regional Qualifier 2023",
    "venue": "Hatfield",
    "wa_points": "155",
    "round": "H",
    "level": "3"
  },
  {
    "id": 425,
    "tiref": "1479966",
    "stroke_code": 13,
    "course": "S",
    "date": "27/01/24",
    "time": "39.90",
    "is_pb": 0,
    "meet_name": "SE Hertfordshire County Championships 2024",
    "venue": "Borehamwood",
    "wa_points": "252",
    "round": "H",
    "level": "2"
  },
  {
    "id": 411,
    "tiref": "1479966",
    "stroke_code": 13,
    "course": "S",
    "date": "27/03/22",
    "time": "49.44",
    "is_pb": 1,
    "meet_name": "Hatfield SC Regional Qualifier",
    "venue": "Hatfield",
    "wa_points": "132",
    "round": "H",
    "level": "3"
  },
  {
    "id": 413,
    "tiref": "1479966",
    "stroke_code": 13,
    "course": "S",
    "date": "27/11/22",
    "time": "46.04",
    "is_pb": 1,
    "meet_name": "Hatfield SC County Qualifier November 2022",
    "venue": "Hatfield",
    "wa_points": "164",
    "round": "H",
    "level": "3"
  },
  {
    "id": 441,
    "tiref": "1479966",
    "stroke_code": 13,
    "course": "S",
    "date": "29/11/25",
    "time": "36.94",
    "is_pb": 0,
    "meet_name": "City of St Albans SC Winter Meet 2025",
    "venue": "St Albans",
    "wa_points": "318",
    "round": "F",
    "level": "3"
  },
  {
    "id": 431,
    "tiref": "1479966",
    "stroke_code": 13,
    "course": "S",
    "date": "30/11/24",
    "time": "39.82",
    "is_pb": 0,
    "meet_name": "City of St Albans SC Winter Open Meet 2024",
    "venue": "St Albans",
    "wa_points": "254",
    "round": "F",
    "level": "3"
  },
  {
    "id": 454,
    "tiref": "1479966",
    "stroke_code": 14,
    "course": "S",
    "date": "01/07/23",
    "time": "1:29.96",
    "is_pb": 1,
    "meet_name": "Putteridge SC End of Season Summer SC Open 2023",
    "venue": "Luton",
    "wa_points": "216",
    "round": "H",
    "level": "2"
  },
  {
    "id": 458,
    "tiref": "1479966",
    "stroke_code": 14,
    "course": "S",
    "date": "02/03/24",
    "time": "1:26.22",
    "is_pb": 0,
    "meet_name": "Watford SC Regional Qualifier 2024",
    "venue": "Watford",
    "wa_points": "245",
    "round": "F",
    "level": "3"
  },
  {
    "id": 452,
    "tiref": "1479966",
    "stroke_code": 14,
    "course": "S",
    "date": "03/06/23",
    "time": "1:35.62",
    "is_pb": 0,
    "meet_name": "Harlow Penguins 2023 10th Eric Shepherd Open Meet",
    "venue": "Harlow",
    "wa_points": "180",
    "round": "H",
    "level": "3"
  },
  {
    "id": 449,
    "tiref": "1479966",
    "stroke_code": 14,
    "course": "S",
    "date": "03/12/22",
    "time": "1:40.10",
    "is_pb": 0,
    "meet_name": "Basildon & Phoenix SC Last Chance County Qualifier",
    "venue": "Basildon",
    "wa_points": "157",
    "round": "H",
    "level": "3"
  },
  {
    "id": 450,
    "tiref": "1479966",
    "stroke_code": 14,
    "course": "S",
    "date": "11/03/23",
    "time": "1:34.02",
    "is_pb": 1,
    "meet_name": "Basildon & Phoenix Spring Regional Qualifier 2023",
    "venue": "Basildon",
    "wa_points": "189",
    "round": "H",
    "level": "3"
  },
  {
    "id": 460,
    "tiref": "1479966",
    "stroke_code": 14,
    "course": "S",
    "date": "14/06/25",
    "time": "1:20.61",
    "is_pb": 1,
    "meet_name": "Watford SC The Terry Davies Legacy Meet 2025",
    "venue": "Watford",
    "wa_points": "300",
    "round": "F",
    "level": "3"
  },
  {
    "id": 459,
    "tiref": "1479966",
    "stroke_code": 14,
    "course": "S",
    "date": "15/03/25",
    "time": "1:22.39",
    "is_pb": 1,
    "meet_name": "Watford SC Regional Qualifier",
    "venue": "Garston",
    "wa_points": "281",
    "round": "F",
    "level": "3"
  },
  {
    "id": 461,
    "tiref": "1479966",
    "stroke_code": 14,
    "course": "S",
    "date": "16/11/25",
    "time": "1:20.79",
    "is_pb": 0,
    "meet_name": "Putteridge SC Winter Short Course Open 2025",
    "venue": "Luton",
    "wa_points": "298",
    "round": "H",
    "level": "3"
  },
  {
    "id": 455,
    "tiref": "1479966",
    "stroke_code": 14,
    "course": "S",
    "date": "19/11/23",
    "time": "1:24.21",
    "is_pb": 1,
    "meet_name": "Watford SC County Qualifier 2023",
    "venue": "Watford",
    "wa_points": "263",
    "round": "F",
    "level": "3"
  },
  {
    "id": 456,
    "tiref": "1479966",
    "stroke_code": 14,
    "course": "S",
    "date": "21/01/24",
    "time": "1:24.27",
    "is_pb": 0,
    "meet_name": "SE Hertfordshire County Championships 2024",
    "venue": "Borehamwood",
    "wa_points": "263",
    "round": "H",
    "level": "2"
  },
  {
    "id": 457,
    "tiref": "1479966",
    "stroke_code": 14,
    "course": "S",
    "date": "21/01/24",
    "time": "1:27.04",
    "is_pb": 0,
    "meet_name": "SE Hertfordshire County Championships 2024",
    "venue": "Borehamwood",
    "wa_points": "239",
    "round": "F",
    "level": "2"
  },
  {
    "id": 447,
    "tiref": "1479966",
    "stroke_code": 14,
    "course": "S",
    "date": "21/05/22",
    "time": "1:53.09",
    "is_pb": 1,
    "meet_name": "Cheshunt SC Anniversary Open Meet 2022",
    "venue": "Harlow",
    "wa_points": "108",
    "round": "H",
    "level": "3"
  },
  {
    "id": 453,
    "tiref": "1479966",
    "stroke_code": 14,
    "course": "S",
    "date": "24/06/23",
    "time": "1:36.06",
    "is_pb": 0,
    "meet_name": "City of St Albans SC End of Season Meet 2023",
    "venue": "St Albans",
    "wa_points": "177",
    "round": "F",
    "level": "3"
  },
  {
    "id": 451,
    "tiref": "1479966",
    "stroke_code": 14,
    "course": "S",
    "date": "25/03/23",
    "time": "1:35.93",
    "is_pb": 0,
    "meet_name": "Hatfield SC Regional Qualifier 2023",
    "venue": "Hatfield",
    "wa_points": "178",
    "round": "H",
    "level": "3"
  },
  {
    "id": 448,
    "tiref": "1479966",
    "stroke_code": 14,
    "course": "S",
    "date": "26/11/22",
    "time": "1:36.91",
    "is_pb": 1,
    "meet_name": "Hatfield SC County Qualifier November 2022",
    "venue": "Hatfield",
    "wa_points": "173",
    "round": "H",
    "level": "3"
  },
  {
    "id": 462,
    "tiref": "1479966",
    "stroke_code": 14,
    "course": "S",
    "date": "29/11/25",
    "time": "1:21.15",
    "is_pb": 0,
    "meet_name": "City of St Albans SC Winter Meet 2025",
    "venue": "St Albans",
    "wa_points": "294",
    "round": "F",
    "level": "3"
  },
  {
    "id": 464,
    "tiref": "1479966",
    "stroke_code": 15,
    "course": "S",
    "date": "15/03/26",
    "time": "2:49.67",
    "is_pb": 1,
    "meet_name": "City of St Albans Spring Meet 2026",
    "venue": "St Albans",
    "wa_points": "336",
    "round": "F",
    "level": "3"
  },
  {
    "id": 463,
    "tiref": "1479966",
    "stroke_code": 15,
    "course": "S",
    "date": "30/11/25",
    "time": "2:54.00",
    "is_pb": 1,
    "meet_name": "City of St Albans SC Winter Meet 2025",
    "venue": "St Albans",
    "wa_points": "312",
    "round": "F",
    "level": "3"
  },
  {
    "id": 465,
    "tiref": "1479966",
    "stroke_code": 16,
    "course": "S",
    "date": "01/10/23",
    "time": "3:20.04",
    "is_pb": 1,
    "meet_name": "City of St Albans Club Champs 2023",
    "venue": "St Albans",
    "wa_points": "224",
    "round": "F",
    "level": "4"
  },
  {
    "id": 468,
    "tiref": "1479966",
    "stroke_code": 16,
    "course": "S",
    "date": "14/03/26",
    "time": "2:56.03",
    "is_pb": 1,
    "meet_name": "City of St Albans Spring Meet 2026",
    "venue": "St Albans",
    "wa_points": "329",
    "round": "F",
    "level": "3"
  },
  {
    "id": 466,
    "tiref": "1479966",
    "stroke_code": 16,
    "course": "S",
    "date": "27/01/24",
    "time": "3:08.65",
    "is_pb": 1,
    "meet_name": "SE Hertfordshire County Championships 2024",
    "venue": "Borehamwood",
    "wa_points": "268",
    "round": "H",
    "level": "2"
  },
  {
    "id": 467,
    "tiref": "1479966",
    "stroke_code": 16,
    "course": "S",
    "date": "30/11/24",
    "time": "3:10.07",
    "is_pb": 0,
    "meet_name": "City of St Albans SC Winter Open Meet 2024",
    "venue": "St Albans",
    "wa_points": "262",
    "round": "F",
    "level": "3"
  },
  {
    "id": 469,
    "tiref": "1479966",
    "stroke_code": 17,
    "course": "S",
    "date": "10/03/24",
    "time": "6:45.20",
    "is_pb": 1,
    "meet_name": "City of St Albans Spring Meet 2024",
    "venue": "St Albans",
    "wa_points": "250",
    "round": "F",
    "level": "3"
  },
  {
    "id": 472,
    "tiref": "1479966",
    "stroke_code": 18,
    "course": "S",
    "date": "01/07/23",
    "time": "1:35.56",
    "is_pb": 1,
    "meet_name": "Putteridge SC End of Season Summer SC Open 2023",
    "venue": "Luton",
    "wa_points": "191",
    "round": "H",
    "level": "2"
  },
  {
    "id": 477,
    "tiref": "1479966",
    "stroke_code": 18,
    "course": "S",
    "date": "02/12/23",
    "time": "1:29.61",
    "is_pb": 0,
    "meet_name": "City of St Albans Winter Meet 2023",
    "venue": "St Albans",
    "wa_points": "232",
    "round": "F",
    "level": "3"
  },
  {
    "id": 475,
    "tiref": "1479966",
    "stroke_code": 18,
    "course": "S",
    "date": "08/10/23",
    "time": "1:28.76",
    "is_pb": 1,
    "meet_name": "Hatfield SC Regional Qualifier Oct 2023",
    "venue": "Hatfield",
    "wa_points": "239",
    "round": "H",
    "level": "3"
  },
  {
    "id": 482,
    "tiref": "1479966",
    "stroke_code": 18,
    "course": "S",
    "date": "09/03/25",
    "time": "1:22.45",
    "is_pb": 1,
    "meet_name": "City of St Albans Spring Meet 2025",
    "venue": "St Albans",
    "wa_points": "298",
    "round": "F",
    "level": "3"
  },
  {
    "id": 471,
    "tiref": "1479966",
    "stroke_code": 18,
    "course": "S",
    "date": "09/10/22",
    "time": "1:46.46",
    "is_pb": 1,
    "meet_name": "Hatfield SC Club Championships 2022",
    "venue": "Hatfield",
    "wa_points": "138",
    "round": "H",
    "level": "4"
  },
  {
    "id": 479,
    "tiref": "1479966",
    "stroke_code": 18,
    "course": "S",
    "date": "10/03/24",
    "time": "1:27.08",
    "is_pb": 0,
    "meet_name": "City of St Albans Spring Meet 2024",
    "venue": "St Albans",
    "wa_points": "253",
    "round": "F",
    "level": "3"
  },
  {
    "id": 484,
    "tiref": "1479966",
    "stroke_code": 18,
    "course": "S",
    "date": "15/06/25",
    "time": "1:22.44",
    "is_pb": 1,
    "meet_name": "Watford SC The Terry Davies Legacy Meet 2025",
    "venue": "Watford",
    "wa_points": "298",
    "round": "F",
    "level": "3"
  },
  {
    "id": 473,
    "tiref": "1479966",
    "stroke_code": 18,
    "course": "S",
    "date": "16/09/23",
    "time": "1:32.12",
    "is_pb": 1,
    "meet_name": "City of St Albans Club Champs 2023",
    "venue": "St Albans",
    "wa_points": "214",
    "round": "F",
    "level": "4"
  },
  {
    "id": 483,
    "tiref": "1479966",
    "stroke_code": 18,
    "course": "S",
    "date": "17/05/25",
    "time": "1:24.72",
    "is_pb": 0,
    "meet_name": "Cheshunt SC May Anniversary Meet 2025",
    "venue": "Harlow",
    "wa_points": "275",
    "round": "H",
    "level": "3"
  },
  {
    "id": 476,
    "tiref": "1479966",
    "stroke_code": 18,
    "course": "S",
    "date": "18/11/23",
    "time": "1:26.90",
    "is_pb": 1,
    "meet_name": "Watford SC County Qualifier 2023",
    "venue": "Watford",
    "wa_points": "255",
    "round": "F",
    "level": "3"
  },
  {
    "id": 478,
    "tiref": "1479966",
    "stroke_code": 18,
    "course": "S",
    "date": "21/01/24",
    "time": "1:27.54",
    "is_pb": 0,
    "meet_name": "SE Hertfordshire County Championships 2024",
    "venue": "Borehamwood",
    "wa_points": "249",
    "round": "H",
    "level": "2"
  },
  {
    "id": 470,
    "tiref": "1479966",
    "stroke_code": 18,
    "course": "S",
    "date": "21/05/22",
    "time": "1:48.27",
    "is_pb": 1,
    "meet_name": "Cheshunt SC Anniversary Open Meet 2022",
    "venue": "Harlow",
    "wa_points": "131",
    "round": "H",
    "level": "3"
  },
  {
    "id": 480,
    "tiref": "1479966",
    "stroke_code": 18,
    "course": "S",
    "date": "21/09/24",
    "time": "1:26.72",
    "is_pb": 1,
    "meet_name": "Co St Albans Autumn Sprint Meet 2024",
    "venue": "St Albans",
    "wa_points": "256",
    "round": "F",
    "level": "3"
  },
  {
    "id": 474,
    "tiref": "1479966",
    "stroke_code": 18,
    "course": "S",
    "date": "23/09/23",
    "time": "1:31.35",
    "is_pb": 1,
    "meet_name": "Co St Albans SC Sprint & Skins Competition 2023",
    "venue": "St Albans",
    "wa_points": "219",
    "round": "F",
    "level": "3"
  },
  {
    "id": 481,
    "tiref": "1479966",
    "stroke_code": 18,
    "course": "S",
    "date": "24/11/24",
    "time": "1:25.94",
    "is_pb": 1,
    "meet_name": "Hatfield County Qualifier November 2024",
    "venue": "Hatfield",
    "wa_points": "263",
    "round": "H",
    "level": "3"
  },
  {
    "id": 485,
    "tiref": "1479966",
    "stroke_code": 18,
    "course": "S",
    "date": "25/10/25",
    "time": "1:25.88",
    "is_pb": 0,
    "meet_name": "Cheshunt SC 20th Annual Open Meet 2025",
    "venue": "Harlow",
    "wa_points": "264",
    "round": "H",
    "level": "3"
  }
]