[
  {
    "id": 22561,
    "tiref": "1656022",
    "stroke_code": 1,
    "course": "L",
    "date": "11/05/24",
    "time": "33.74",
    "is_pb": 1,
    "meet_name": "Swim England East Region LC Championships 2024",
    "venue": "Norwich",
    "wa_points": "238",
    "round": "H",
    "level": "1"
  },
  {
    "id": 22563,
    "tiref": "1656022",
    "stroke_code": 1,
    "course": "L",
    "date": "15/03/26",
    "time": "29.14",
    "is_pb": 1,
    "meet_name": "Putteridge SC Spring LC National Qualifier 2026",
    "venue": "Luton",
    "wa_points": "369",
    "round": "H",
    "level": "1"
  },
  {
    "id": 22562,
    "tiref": "1656022",
    "stroke_code": 1,
    "course": "L",
    "date": "23/03/25",
    "time": "30.17",
    "is_pb": 1,
    "meet_name": "NUEL SC National Qualifier Open Meet 2025",
    "venue": "London",
    "wa_points": "332",
    "round": "F",
    "level": "1"
  },
  {
    "id": 22538,
    "tiref": "1656022",
    "stroke_code": 1,
    "course": "S",
    "date": "01/10/23",
    "time": "34.84",
    "is_pb": 1,
    "meet_name": "City of St Albans Club Champs 2023",
    "venue": "St Albans",
    "wa_points": "186",
    "round": "F",
    "level": "4"
  },
  {
    "id": 22549,
    "tiref": "1656022",
    "stroke_code": 1,
    "course": "S",
    "date": "01/12/24",
    "time": "30.78",
    "is_pb": 1,
    "meet_name": "City of St Albans SC Winter Open Meet 2024",
    "venue": "St Albans",
    "wa_points": "270",
    "round": "F",
    "level": "3"
  },
  {
    "id": 22543,
    "tiref": "1656022",
    "stroke_code": 1,
    "course": "S",
    "date": "02/03/24",
    "time": "32.43",
    "is_pb": 1,
    "meet_name": "Watford SC Regional Qualifier 2024",
    "venue": "Watford",
    "wa_points": "231",
    "round": "F",
    "level": "3"
  },
  {
    "id": 22530,
    "tiref": "1656022",
    "stroke_code": 1,
    "course": "S",
    "date": "02/10/22",
    "time": "42.46",
    "is_pb": 1,
    "meet_name": "City of St Albans SC Level 4 Club Champs",
    "venue": "St Albans",
    "wa_points": "102",
    "round": "F",
    "level": "4"
  },
  {
    "id": 22540,
    "tiref": "1656022",
    "stroke_code": 1,
    "course": "S",
    "date": "03/12/23",
    "time": "33.36",
    "is_pb": 1,
    "meet_name": "City of St Albans Winter Meet 2023",
    "venue": "St Albans",
    "wa_points": "212",
    "round": "F",
    "level": "3"
  },
  {
    "id": 22555,
    "tiref": "1656022",
    "stroke_code": 1,
    "course": "S",
    "date": "04/10/25",
    "time": "29.05",
    "is_pb": 1,
    "meet_name": "Hatfield Autumn Regional Qualifier October 2025",
    "venue": "Hatfield",
    "wa_points": "321",
    "round": "H",
    "level": "3"
  },
  {
    "id": 22532,
    "tiref": "1656022",
    "stroke_code": 1,
    "course": "S",
    "date": "04/12/22",
    "time": "40.15",
    "is_pb": 1,
    "meet_name": "City of St Albans SC Winter Meet 2022",
    "venue": "St Albans",
    "wa_points": "121",
    "round": "F",
    "level": "3"
  },
  {
    "id": 22548,
    "tiref": "1656022",
    "stroke_code": 1,
    "course": "S",
    "date": "06/07/24",
    "time": "31.93",
    "is_pb": 1,
    "meet_name": "Putteridge SC End of Season Summer Open 2024",
    "venue": "Luton",
    "wa_points": "242",
    "round": "H",
    "level": "3"
  },
  {
    "id": 22554,
    "tiref": "1656022",
    "stroke_code": 1,
    "course": "S",
    "date": "06/07/25",
    "time": "29.85",
    "is_pb": 0,
    "meet_name": "Co St Albans Club Champs 50s & 25s 2025",
    "venue": "St Albans",
    "wa_points": "296",
    "round": "F",
    "level": "4"
  },
  {
    "id": 22560,
    "tiref": "1656022",
    "stroke_code": 1,
    "course": "S",
    "date": "07/03/26",
    "time": "28.06",
    "is_pb": 1,
    "meet_name": "Watford SC Regional Qualifier Open Meet",
    "venue": "Watford",
    "wa_points": "356",
    "round": "F",
    "level": "3"
  },
  {
    "id": 22545,
    "tiref": "1656022",
    "stroke_code": 1,
    "course": "S",
    "date": "07/06/24",
    "time": "32.50",
    "is_pb": 0,
    "meet_name": "Herts & St Albans SSA Primary Schools Champs 2024",
    "venue": "St Albans",
    "wa_points": "229",
    "round": "F",
    "level": "4"
  },
  {
    "id": 22550,
    "tiref": "1656022",
    "stroke_code": 1,
    "course": "S",
    "date": "08/12/24",
    "time": "30.55",
    "is_pb": 1,
    "meet_name": "Team Luton 2024 Winter Development Meet",
    "venue": "Luton",
    "wa_points": "276",
    "round": "H",
    "level": "3"
  },
  {
    "id": 22544,
    "tiref": "1656022",
    "stroke_code": 1,
    "course": "S",
    "date": "10/03/24",
    "time": "32.23",
    "is_pb": 1,
    "meet_name": "City of St Albans Spring Meet 2024",
    "venue": "St Albans",
    "wa_points": "235",
    "round": "F",
    "level": "3"
  },
  {
    "id": 22533,
    "tiref": "1656022",
    "stroke_code": 1,
    "course": "S",
    "date": "12/03/23",
    "time": "38.25",
    "is_pb": 1,
    "meet_name": "City of St Albans Spring Meet 2023",
    "venue": "St Albans",
    "wa_points": "140",
    "round": "F",
    "level": "3"
  },
  {
    "id": 22553,
    "tiref": "1656022",
    "stroke_code": 1,
    "course": "S",
    "date": "15/06/25",
    "time": "29.74",
    "is_pb": 1,
    "meet_name": "Watford SC The Terry Davies Legacy Meet 2025",
    "venue": "Watford",
    "wa_points": "299",
    "round": "F",
    "level": "3"
  },
  {
    "id": 22546,
    "tiref": "1656022",
    "stroke_code": 1,
    "course": "S",
    "date": "16/06/24",
    "time": "32.85",
    "is_pb": 0,
    "meet_name": "Watford Terry Davies Legacy Meet 2024",
    "venue": "Watford",
    "wa_points": "222",
    "round": "F",
    "level": "3"
  },
  {
    "id": 22556,
    "tiref": "1656022",
    "stroke_code": 1,
    "course": "S",
    "date": "16/11/25",
    "time": "29.04",
    "is_pb": 1,
    "meet_name": "Cambridge Grand Prix 2025",
    "venue": "Cambridge",
    "wa_points": "321",
    "round": "H",
    "level": "2"
  },
  {
    "id": 22535,
    "tiref": "1656022",
    "stroke_code": 1,
    "course": "S",
    "date": "17/06/23",
    "time": "37.50",
    "is_pb": 0,
    "meet_name": "ESS Charlie Junior Invitational Meet 2023",
    "venue": "Enfield",
    "wa_points": "149",
    "round": "F",
    "level": "4"
  },
  {
    "id": 22534,
    "tiref": "1656022",
    "stroke_code": 1,
    "course": "S",
    "date": "19/05/23",
    "time": "37.25",
    "is_pb": 1,
    "meet_name": "HSSA StASSA Primary Schools Champs 2023",
    "venue": "St Albans",
    "wa_points": "152",
    "round": "F",
    "level": "4"
  },
  {
    "id": 22539,
    "tiref": "1656022",
    "stroke_code": 1,
    "course": "S",
    "date": "19/11/23",
    "time": "34.46",
    "is_pb": 1,
    "meet_name": "Watford SC County Qualifier 2023",
    "venue": "Watford",
    "wa_points": "192",
    "round": "F",
    "level": "3"
  },
  {
    "id": 22531,
    "tiref": "1656022",
    "stroke_code": 1,
    "course": "S",
    "date": "22/10/22",
    "time": "40.87",
    "is_pb": 1,
    "meet_name": "Cheshunt SC 17th Annual Autumn Open Meet",
    "venue": "Harlow",
    "wa_points": "115",
    "round": "H",
    "level": "3"
  },
  {
    "id": 22547,
    "tiref": "1656022",
    "stroke_code": 1,
    "course": "S",
    "date": "23/06/24",
    "time": "32.24",
    "is_pb": 0,
    "meet_name": "City of St Albans Summer Meet 2024",
    "venue": "St Albans",
    "wa_points": "235",
    "round": "F",
    "level": "3"
  },
  {
    "id": 22537,
    "tiref": "1656022",
    "stroke_code": 1,
    "course": "S",
    "date": "23/09/23",
    "time": "35.35",
    "is_pb": 1,
    "meet_name": "Co St Albans SC Sprint & Skins Competition 2023",
    "venue": "St Albans",
    "wa_points": "178",
    "round": "F",
    "level": "3"
  },
  {
    "id": 22536,
    "tiref": "1656022",
    "stroke_code": 1,
    "course": "S",
    "date": "24/06/23",
    "time": "36.44",
    "is_pb": 1,
    "meet_name": "City of St Albans SC End of Season Meet 2023",
    "venue": "St Albans",
    "wa_points": "162",
    "round": "F",
    "level": "3"
  },
  {
    "id": 22551,
    "tiref": "1656022",
    "stroke_code": 1,
    "course": "S",
    "date": "25/01/25",
    "time": "29.85",
    "is_pb": 1,
    "meet_name": "Swim England Hertfordshire County Championships 25",
    "venue": "St Albans",
    "wa_points": "296",
    "round": "F",
    "level": "2"
  },
  {
    "id": 22552,
    "tiref": "1656022",
    "stroke_code": 1,
    "course": "S",
    "date": "25/01/25",
    "time": "29.97",
    "is_pb": 0,
    "meet_name": "Swim England Hertfordshire County Championships 25",
    "venue": "St Albans",
    "wa_points": "292",
    "round": "H",
    "level": "2"
  },
  {
    "id": 22558,
    "tiref": "1656022",
    "stroke_code": 1,
    "course": "S",
    "date": "25/01/26",
    "time": "28.24",
    "is_pb": 0,
    "meet_name": "SE Hertfordshire County Championships 2026",
    "venue": "St Albans",
    "wa_points": "349",
    "round": "H",
    "level": "2"
  },
  {
    "id": 22559,
    "tiref": "1656022",
    "stroke_code": 1,
    "course": "S",
    "date": "25/01/26",
    "time": "28.32",
    "is_pb": 0,
    "meet_name": "SE Hertfordshire County Championships 2026",
    "venue": "St Albans",
    "wa_points": "346",
    "round": "F",
    "level": "2"
  },
  {
    "id": 22541,
    "tiref": "1656022",
    "stroke_code": 1,
    "course": "S",
    "date": "28/01/24",
    "time": "33.28",
    "is_pb": 1,
    "meet_name": "SE Hertfordshire County Championships 2024",
    "venue": "Borehamwood",
    "wa_points": "213",
    "round": "F",
    "level": "2"
  },
  {
    "id": 22542,
    "tiref": "1656022",
    "stroke_code": 1,
    "course": "S",
    "date": "28/01/24",
    "time": "33.30",
    "is_pb": 0,
    "meet_name": "SE Hertfordshire County Championships 2024",
    "venue": "Borehamwood",
    "wa_points": "213",
    "round": "H",
    "level": "2"
  },
  {
    "id": 22557,
    "tiref": "1656022",
    "stroke_code": 1,
    "course": "S",
    "date": "30/11/25",
    "time": "28.22",
    "is_pb": 1,
    "meet_name": "City of St Albans SC Winter Meet 2025",
    "venue": "St Albans",
    "wa_points": "350",
    "round": "F",
    "level": "3"
  },
  {
    "id": 22586,
    "tiref": "1656022",
    "stroke_code": 2,
    "course": "L",
    "date": "15/03/26",
    "time": "1:03.67",
    "is_pb": 1,
    "meet_name": "Putteridge SC Spring LC National Qualifier 2026",
    "venue": "Luton",
    "wa_points": "387",
    "round": "H",
    "level": "1"
  },
  {
    "id": 22585,
    "tiref": "1656022",
    "stroke_code": 2,
    "course": "L",
    "date": "16/03/25",
    "time": "1:08.51",
    "is_pb": 1,
    "meet_name": "Team Luton March Long Course Meet 2025",
    "venue": "Luton",
    "wa_points": "310",
    "round": "H",
    "level": "1"
  },
  {
    "id": 22584,
    "tiref": "1656022",
    "stroke_code": 2,
    "course": "L",
    "date": "17/03/24",
    "time": "1:15.56",
    "is_pb": 1,
    "meet_name": "Team Luton March Long Course Meet 2024",
    "venue": "Luton",
    "wa_points": "231",
    "round": "H",
    "level": "1"
  },
  {
    "id": 22572,
    "tiref": "1656022",
    "stroke_code": 2,
    "course": "S",
    "date": "02/12/23",
    "time": "1:12.98",
    "is_pb": 1,
    "meet_name": "City of St Albans Winter Meet 2023",
    "venue": "St Albans",
    "wa_points": "231",
    "round": "F",
    "level": "3"
  },
  {
    "id": 22575,
    "tiref": "1656022",
    "stroke_code": 2,
    "course": "S",
    "date": "03/03/24",
    "time": "1:12.95",
    "is_pb": 1,
    "meet_name": "Watford SC Regional Qualifier 2024",
    "venue": "Watford",
    "wa_points": "232",
    "round": "F",
    "level": "3"
  },
  {
    "id": 22582,
    "tiref": "1656022",
    "stroke_code": 2,
    "course": "S",
    "date": "05/10/25",
    "time": "1:03.74",
    "is_pb": 1,
    "meet_name": "Hatfield Autumn Regional Qualifier October 2025",
    "venue": "Hatfield",
    "wa_points": "348",
    "round": "H",
    "level": "3"
  },
  {
    "id": 22583,
    "tiref": "1656022",
    "stroke_code": 2,
    "course": "S",
    "date": "08/03/26",
    "time": "1:01.01",
    "is_pb": 1,
    "meet_name": "Watford SC Regional Qualifier Open Meet",
    "venue": "Watford",
    "wa_points": "397",
    "round": "F",
    "level": "3"
  },
  {
    "id": 22565,
    "tiref": "1656022",
    "stroke_code": 2,
    "course": "S",
    "date": "11/03/23",
    "time": "1:27.90",
    "is_pb": 1,
    "meet_name": "City of St Albans Spring Meet 2023",
    "venue": "St Albans",
    "wa_points": "132",
    "round": "F",
    "level": "3"
  },
  {
    "id": 22577,
    "tiref": "1656022",
    "stroke_code": 2,
    "course": "S",
    "date": "16/06/24",
    "time": "1:11.42",
    "is_pb": 1,
    "meet_name": "Watford Terry Davies Legacy Meet 2024",
    "venue": "Watford",
    "wa_points": "247",
    "round": "F",
    "level": "3"
  },
  {
    "id": 22568,
    "tiref": "1656022",
    "stroke_code": 2,
    "course": "S",
    "date": "16/09/23",
    "time": "1:18.93",
    "is_pb": 1,
    "meet_name": "City of St Albans Club Champs 2023",
    "venue": "St Albans",
    "wa_points": "183",
    "round": "F",
    "level": "4"
  },
  {
    "id": 22576,
    "tiref": "1656022",
    "stroke_code": 2,
    "course": "S",
    "date": "18/05/24",
    "time": "1:12.65",
    "is_pb": 1,
    "meet_name": "Cheshunt SC May Anniversary Meet 2024",
    "venue": "Harlow",
    "wa_points": "235",
    "round": "H",
    "level": "3"
  },
  {
    "id": 22571,
    "tiref": "1656022",
    "stroke_code": 2,
    "course": "S",
    "date": "18/11/23",
    "time": "1:15.83",
    "is_pb": 1,
    "meet_name": "Watford SC County Qualifier 2023",
    "venue": "Watford",
    "wa_points": "206",
    "round": "F",
    "level": "3"
  },
  {
    "id": 22580,
    "tiref": "1656022",
    "stroke_code": 2,
    "course": "S",
    "date": "19/01/25",
    "time": "1:06.31",
    "is_pb": 1,
    "meet_name": "Swim England Hertfordshire County Championships 25",
    "venue": "St Albans",
    "wa_points": "309",
    "round": "H",
    "level": "2"
  },
  {
    "id": 22581,
    "tiref": "1656022",
    "stroke_code": 2,
    "course": "S",
    "date": "19/01/25",
    "time": "1:06.59",
    "is_pb": 0,
    "meet_name": "Swim England Hertfordshire County Championships 25",
    "venue": "St Albans",
    "wa_points": "305",
    "round": "F",
    "level": "2"
  },
  {
    "id": 22566,
    "tiref": "1656022",
    "stroke_code": 2,
    "course": "S",
    "date": "20/05/23",
    "time": "1:27.14",
    "is_pb": 1,
    "meet_name": "Cheshunt SC Anniversary Open Meet 2023",
    "venue": "Harlow",
    "wa_points": "136",
    "round": "H",
    "level": "3"
  },
  {
    "id": 22573,
    "tiref": "1656022",
    "stroke_code": 2,
    "course": "S",
    "date": "21/01/24",
    "time": "1:13.52",
    "is_pb": 0,
    "meet_name": "SE Hertfordshire County Championships 2024",
    "venue": "Borehamwood",
    "wa_points": "226",
    "round": "F",
    "level": "2"
  },
  {
    "id": 22574,
    "tiref": "1656022",
    "stroke_code": 2,
    "course": "S",
    "date": "21/01/24",
    "time": "1:13.80",
    "is_pb": 0,
    "meet_name": "SE Hertfordshire County Championships 2024",
    "venue": "Borehamwood",
    "wa_points": "224",
    "round": "H",
    "level": "2"
  },
  {
    "id": 22578,
    "tiref": "1656022",
    "stroke_code": 2,
    "course": "S",
    "date": "21/09/24",
    "time": "1:10.43",
    "is_pb": 1,
    "meet_name": "Co St Albans Autumn Sprint Meet 2024",
    "venue": "St Albans",
    "wa_points": "258",
    "round": "F",
    "level": "3"
  },
  {
    "id": 22570,
    "tiref": "1656022",
    "stroke_code": 2,
    "course": "S",
    "date": "21/10/23",
    "time": "1:16.85",
    "is_pb": 1,
    "meet_name": "Cheshunt SC 18th Annual Autumn Open Meet 2023",
    "venue": "Harlow",
    "wa_points": "198",
    "round": "H",
    "level": "3"
  },
  {
    "id": 22564,
    "tiref": "1656022",
    "stroke_code": 2,
    "course": "S",
    "date": "22/10/22",
    "time": "1:33.37",
    "is_pb": 1,
    "meet_name": "Cheshunt SC 17th Annual Autumn Open Meet",
    "venue": "Harlow",
    "wa_points": "110",
    "round": "H",
    "level": "3"
  },
  {
    "id": 22569,
    "tiref": "1656022",
    "stroke_code": 2,
    "course": "S",
    "date": "23/09/23",
    "time": "1:17.58",
    "is_pb": 1,
    "meet_name": "Co St Albans SC Sprint & Skins Competition 2023",
    "venue": "St Albans",
    "wa_points": "193",
    "round": "F",
    "level": "3"
  },
  {
    "id": 22567,
    "tiref": "1656022",
    "stroke_code": 2,
    "course": "S",
    "date": "25/06/23",
    "time": "1:21.32",
    "is_pb": 1,
    "meet_name": "City of St Albans SC End of Season Meet 2023",
    "venue": "St Albans",
    "wa_points": "167",
    "round": "F",
    "level": "3"
  },
  {
    "id": 22579,
    "tiref": "1656022",
    "stroke_code": 2,
    "course": "S",
    "date": "30/11/24",
    "time": "1:08.07",
    "is_pb": 1,
    "meet_name": "City of St Albans SC Winter Open Meet 2024",
    "venue": "St Albans",
    "wa_points": "285",
    "round": "F",
    "level": "3"
  },
  {
    "id": 22594,
    "tiref": "1656022",
    "stroke_code": 3,
    "course": "S",
    "date": "01/12/24",
    "time": "2:29.94",
    "is_pb": 1,
    "meet_name": "City of St Albans SC Winter Open Meet 2024",
    "venue": "St Albans",
    "wa_points": "284",
    "round": "F",
    "level": "3"
  },
  {
    "id": 22590,
    "tiref": "1656022",
    "stroke_code": 3,
    "course": "S",
    "date": "03/12/23",
    "time": "2:41.68",
    "is_pb": 1,
    "meet_name": "City of St Albans Winter Meet 2023",
    "venue": "St Albans",
    "wa_points": "226",
    "round": "F",
    "level": "3"
  },
  {
    "id": 22596,
    "tiref": "1656022",
    "stroke_code": 3,
    "course": "S",
    "date": "04/10/25",
    "time": "2:19.51",
    "is_pb": 1,
    "meet_name": "Hatfield Autumn Regional Qualifier October 2025",
    "venue": "Hatfield",
    "wa_points": "353",
    "round": "H",
    "level": "3"
  },
  {
    "id": 22597,
    "tiref": "1656022",
    "stroke_code": 3,
    "course": "S",
    "date": "07/03/26",
    "time": "2:14.65",
    "is_pb": 1,
    "meet_name": "Watford SC Regional Qualifier Open Meet",
    "venue": "Watford",
    "wa_points": "392",
    "round": "F",
    "level": "3"
  },
  {
    "id": 22595,
    "tiref": "1656022",
    "stroke_code": 3,
    "course": "S",
    "date": "09/03/25",
    "time": "2:25.79",
    "is_pb": 1,
    "meet_name": "City of St Albans Spring Meet 2025",
    "venue": "St Albans",
    "wa_points": "309",
    "round": "F",
    "level": "3"
  },
  {
    "id": 22592,
    "tiref": "1656022",
    "stroke_code": 3,
    "course": "S",
    "date": "10/03/24",
    "time": "2:38.20",
    "is_pb": 1,
    "meet_name": "City of St Albans Spring Meet 2024",
    "venue": "St Albans",
    "wa_points": "242",
    "round": "F",
    "level": "3"
  },
  {
    "id": 22587,
    "tiref": "1656022",
    "stroke_code": 3,
    "course": "S",
    "date": "12/03/23",
    "time": "3:05.81",
    "is_pb": 1,
    "meet_name": "City of St Albans Spring Meet 2023",
    "venue": "St Albans",
    "wa_points": "149",
    "round": "F",
    "level": "3"
  },
  {
    "id": 22589,
    "tiref": "1656022",
    "stroke_code": 3,
    "course": "S",
    "date": "19/11/23",
    "time": "2:47.74",
    "is_pb": 1,
    "meet_name": "Watford SC County Qualifier 2023",
    "venue": "Watford",
    "wa_points": "203",
    "round": "F",
    "level": "3"
  },
  {
    "id": 22593,
    "tiref": "1656022",
    "stroke_code": 3,
    "course": "S",
    "date": "23/06/24",
    "time": "2:34.19",
    "is_pb": 1,
    "meet_name": "City of St Albans Summer Meet 2024",
    "venue": "St Albans",
    "wa_points": "261",
    "round": "F",
    "level": "3"
  },
  {
    "id": 22588,
    "tiref": "1656022",
    "stroke_code": 3,
    "course": "S",
    "date": "25/06/23",
    "time": "2:59.63",
    "is_pb": 1,
    "meet_name": "City of St Albans SC End of Season Meet 2023",
    "venue": "St Albans",
    "wa_points": "165",
    "round": "F",
    "level": "3"
  },
  {
    "id": 22591,
    "tiref": "1656022",
    "stroke_code": 3,
    "course": "S",
    "date": "27/01/24",
    "time": "2:43.51",
    "is_pb": 0,
    "meet_name": "SE Hertfordshire County Championships 2024",
    "venue": "Borehamwood",
    "wa_points": "219",
    "round": "H",
    "level": "2"
  },
  {
    "id": 22604,
    "tiref": "1656022",
    "stroke_code": 4,
    "course": "L",
    "date": "12/05/24",
    "time": "5:50.67",
    "is_pb": 1,
    "meet_name": "Swim England East Region LC Championships 2024",
    "venue": "Norwich",
    "wa_points": "246",
    "round": "H",
    "level": "1"
  },
  {
    "id": 22599,
    "tiref": "1656022",
    "stroke_code": 4,
    "course": "S",
    "date": "02/03/24",
    "time": "5:33.76",
    "is_pb": 1,
    "meet_name": "Watford SC Regional Qualifier 2024",
    "venue": "Watford",
    "wa_points": "257",
    "round": "F",
    "level": "3"
  },
  {
    "id": 22603,
    "tiref": "1656022",
    "stroke_code": 4,
    "course": "S",
    "date": "07/12/25",
    "time": "4:49.21",
    "is_pb": 1,
    "meet_name": "Co St Albans & Verulam Joint Club Champs 2025",
    "venue": "St Albans",
    "wa_points": "395",
    "round": "F",
    "level": "3"
  },
  {
    "id": 22602,
    "tiref": "1656022",
    "stroke_code": 4,
    "course": "S",
    "date": "09/03/25",
    "time": "5:07.24",
    "is_pb": 1,
    "meet_name": "City of St Albans Spring Meet 2025",
    "venue": "St Albans",
    "wa_points": "329",
    "round": "F",
    "level": "3"
  },
  {
    "id": 22601,
    "tiref": "1656022",
    "stroke_code": 4,
    "course": "S",
    "date": "10/11/24",
    "time": "5:26.56",
    "is_pb": 1,
    "meet_name": "Co St Albans Long Distance Club Champs 2024",
    "venue": "St Albans",
    "wa_points": "274",
    "round": "F",
    "level": "3"
  },
  {
    "id": 22600,
    "tiref": "1656022",
    "stroke_code": 4,
    "course": "S",
    "date": "23/06/24",
    "time": "5:33.40",
    "is_pb": 1,
    "meet_name": "City of St Albans Summer Meet 2024",
    "venue": "St Albans",
    "wa_points": "258",
    "round": "F",
    "level": "3"
  },
  {
    "id": 22598,
    "tiref": "1656022",
    "stroke_code": 4,
    "course": "S",
    "date": "26/11/23",
    "time": "5:37.13",
    "is_pb": 1,
    "meet_name": "Co St Albans & Watford SCs Joint Club Champs 2023",
    "venue": "St Albans",
    "wa_points": "249",
    "round": "F",
    "level": "3"
  },
  {
    "id": 22605,
    "tiref": "1656022",
    "stroke_code": 5,
    "course": "S",
    "date": "01/11/23",
    "time": "11:59.77",
    "is_pb": 1,
    "meet_name": "Co St Albans & Watford SCs Joint Club Champs 2023",
    "venue": "Watford",
    "wa_points": "229",
    "round": "F",
    "level": "3"
  },
  {
    "id": 22606,
    "tiref": "1656022",
    "stroke_code": 5,
    "course": "S",
    "date": "06/11/24",
    "time": "11:05.63",
    "is_pb": 1,
    "meet_name": "Co St Albans & Watford Joint Club Champs 2024",
    "venue": "Watford",
    "wa_points": "289",
    "round": "F",
    "level": "3"
  },
  {
    "id": 22608,
    "tiref": "1656022",
    "stroke_code": 5,
    "course": "S",
    "date": "10/01/26",
    "time": "9:53.53",
    "is_pb": 1,
    "meet_name": "SE Hertfordshire County Championships 2026",
    "venue": "St Albans",
    "wa_points": "408",
    "round": "H",
    "level": "2"
  },
  {
    "id": 22607,
    "tiref": "1656022",
    "stroke_code": 5,
    "course": "S",
    "date": "12/10/25",
    "time": "10:28.16",
    "is_pb": 1,
    "meet_name": "Co St Albans & Verulam Joint Club Champs 2025",
    "venue": "St Albans",
    "wa_points": "344",
    "round": "F",
    "level": "3"
  },
  {
    "id": 22636,
    "tiref": "1656022",
    "stroke_code": 7,
    "course": "L",
    "date": "05/05/25",
    "time": "38.05",
    "is_pb": 1,
    "meet_name": "SE East Region Long Course Championships 2025",
    "venue": "Norwich",
    "wa_points": "317",
    "round": "H",
    "level": "1"
  },
  {
    "id": 22637,
    "tiref": "1656022",
    "stroke_code": 7,
    "course": "L",
    "date": "05/05/25",
    "time": "38.77",
    "is_pb": 0,
    "meet_name": "SE East Region Long Course Championships 2025",
    "venue": "Norwich",
    "wa_points": "299",
    "round": "F",
    "level": "1"
  },
  {
    "id": 22638,
    "tiref": "1656022",
    "stroke_code": 7,
    "course": "L",
    "date": "14/03/26",
    "time": "35.79",
    "is_pb": 1,
    "meet_name": "Putteridge SC Spring LC National Qualifier 2026",
    "venue": "Luton",
    "wa_points": "381",
    "round": "H",
    "level": "1"
  },
  {
    "id": 22635,
    "tiref": "1656022",
    "stroke_code": 7,
    "course": "L",
    "date": "23/03/25",
    "time": "38.69",
    "is_pb": 1,
    "meet_name": "NUEL SC National Qualifier Open Meet 2025",
    "venue": "London",
    "wa_points": "301",
    "round": "F",
    "level": "1"
  },
  {
    "id": 22639,
    "tiref": "1656022",
    "stroke_code": 7,
    "course": "L",
    "date": "29/03/26",
    "time": "35.33",
    "is_pb": 1,
    "meet_name": "London Legacy Swimming Meet 2026 (Long Course)",
    "venue": "London",
    "wa_points": "396",
    "round": "H",
    "level": "1"
  },
  {
    "id": 22609,
    "tiref": "1656022",
    "stroke_code": 7,
    "course": "S",
    "date": "02/10/22",
    "time": "54.89",
    "is_pb": 1,
    "meet_name": "City of St Albans SC Level 4 Club Champs",
    "venue": "St Albans",
    "wa_points": "93",
    "round": "F",
    "level": "4"
  },
  {
    "id": 22620,
    "tiref": "1656022",
    "stroke_code": 7,
    "course": "S",
    "date": "03/03/24",
    "time": "43.98",
    "is_pb": 1,
    "meet_name": "Watford SC Regional Qualifier 2024",
    "venue": "Watford",
    "wa_points": "182",
    "round": "F",
    "level": "3"
  },
  {
    "id": 22630,
    "tiref": "1656022",
    "stroke_code": 7,
    "course": "S",
    "date": "06/07/25",
    "time": "37.39",
    "is_pb": 0,
    "meet_name": "Co St Albans Club Champs 50s & 25s 2025",
    "venue": "St Albans",
    "wa_points": "297",
    "round": "F",
    "level": "4"
  },
  {
    "id": 22622,
    "tiref": "1656022",
    "stroke_code": 7,
    "course": "S",
    "date": "07/06/24",
    "time": "42.01",
    "is_pb": 1,
    "meet_name": "Herts & St Albans SSA Primary Schools Champs 2024",
    "venue": "St Albans",
    "wa_points": "209",
    "round": "F",
    "level": "4"
  },
  {
    "id": 22611,
    "tiref": "1656022",
    "stroke_code": 7,
    "course": "S",
    "date": "11/03/23",
    "time": "52.88",
    "is_pb": 1,
    "meet_name": "City of St Albans Spring Meet 2023",
    "venue": "St Albans",
    "wa_points": "105",
    "round": "F",
    "level": "3"
  },
  {
    "id": 22623,
    "tiref": "1656022",
    "stroke_code": 7,
    "course": "S",
    "date": "16/06/24",
    "time": "40.72",
    "is_pb": 1,
    "meet_name": "Watford Terry Davies Legacy Meet 2024",
    "venue": "Watford",
    "wa_points": "230",
    "round": "F",
    "level": "3"
  },
  {
    "id": 22616,
    "tiref": "1656022",
    "stroke_code": 7,
    "course": "S",
    "date": "16/09/23",
    "time": "47.42",
    "is_pb": 1,
    "meet_name": "City of St Albans Club Champs 2023",
    "venue": "St Albans",
    "wa_points": "145",
    "round": "F",
    "level": "4"
  },
  {
    "id": 22631,
    "tiref": "1656022",
    "stroke_code": 7,
    "course": "S",
    "date": "16/11/25",
    "time": "36.38",
    "is_pb": 1,
    "meet_name": "Cambridge Grand Prix 2025",
    "venue": "Cambridge",
    "wa_points": "322",
    "round": "H",
    "level": "2"
  },
  {
    "id": 22614,
    "tiref": "1656022",
    "stroke_code": 7,
    "course": "S",
    "date": "17/06/23",
    "time": "48.68",
    "is_pb": 1,
    "meet_name": "ESS Charlie Junior Invitational Meet 2023",
    "venue": "Enfield",
    "wa_points": "134",
    "round": "F",
    "level": "4"
  },
  {
    "id": 22621,
    "tiref": "1656022",
    "stroke_code": 7,
    "course": "S",
    "date": "18/05/24",
    "time": "43.14",
    "is_pb": 1,
    "meet_name": "Cheshunt SC May Anniversary Meet 2024",
    "venue": "Harlow",
    "wa_points": "193",
    "round": "H",
    "level": "3"
  },
  {
    "id": 22612,
    "tiref": "1656022",
    "stroke_code": 7,
    "course": "S",
    "date": "19/05/23",
    "time": "50.29",
    "is_pb": 1,
    "meet_name": "HSSA StASSA Primary Schools Champs 2023",
    "venue": "St Albans",
    "wa_points": "122",
    "round": "F",
    "level": "4"
  },
  {
    "id": 22619,
    "tiref": "1656022",
    "stroke_code": 7,
    "course": "S",
    "date": "19/11/23",
    "time": "45.51",
    "is_pb": 1,
    "meet_name": "Watford SC County Qualifier 2023",
    "venue": "Watford",
    "wa_points": "164",
    "round": "F",
    "level": "3"
  },
  {
    "id": 22613,
    "tiref": "1656022",
    "stroke_code": 7,
    "course": "S",
    "date": "20/05/23",
    "time": "51.47",
    "is_pb": 0,
    "meet_name": "Cheshunt SC Anniversary Open Meet 2023",
    "venue": "Harlow",
    "wa_points": "113",
    "round": "H",
    "level": "3"
  },
  {
    "id": 22629,
    "tiref": "1656022",
    "stroke_code": 7,
    "course": "S",
    "date": "21/06/25",
    "time": "36.65",
    "is_pb": 1,
    "meet_name": "Co St Albans Summer Meet 2025",
    "venue": "St Albans",
    "wa_points": "315",
    "round": "F",
    "level": "3"
  },
  {
    "id": 22618,
    "tiref": "1656022",
    "stroke_code": 7,
    "course": "S",
    "date": "21/10/23",
    "time": "46.60",
    "is_pb": 1,
    "meet_name": "Cheshunt SC 18th Annual Autumn Open Meet 2023",
    "venue": "Harlow",
    "wa_points": "153",
    "round": "H",
    "level": "3"
  },
  {
    "id": 22624,
    "tiref": "1656022",
    "stroke_code": 7,
    "course": "S",
    "date": "22/06/24",
    "time": "40.59",
    "is_pb": 1,
    "meet_name": "City of St Albans Summer Meet 2024",
    "venue": "St Albans",
    "wa_points": "232",
    "round": "F",
    "level": "3"
  },
  {
    "id": 22610,
    "tiref": "1656022",
    "stroke_code": 7,
    "course": "S",
    "date": "22/10/22",
    "time": "58.19",
    "is_pb": 0,
    "meet_name": "Cheshunt SC 17th Annual Autumn Open Meet",
    "venue": "Harlow",
    "wa_points": "78",
    "round": "H",
    "level": "3"
  },
  {
    "id": 22617,
    "tiref": "1656022",
    "stroke_code": 7,
    "course": "S",
    "date": "23/09/23",
    "time": "49.60",
    "is_pb": 0,
    "meet_name": "Co St Albans SC Sprint & Skins Competition 2023",
    "venue": "St Albans",
    "wa_points": "127",
    "round": "F",
    "level": "3"
  },
  {
    "id": 22633,
    "tiref": "1656022",
    "stroke_code": 7,
    "course": "S",
    "date": "24/01/26",
    "time": "34.60",
    "is_pb": 1,
    "meet_name": "SE Hertfordshire County Championships 2026",
    "venue": "St Albans",
    "wa_points": "374",
    "round": "F",
    "level": "2"
  },
  {
    "id": 22634,
    "tiref": "1656022",
    "stroke_code": 7,
    "course": "S",
    "date": "24/01/26",
    "time": "34.76",
    "is_pb": 0,
    "meet_name": "SE Hertfordshire County Championships 2026",
    "venue": "St Albans",
    "wa_points": "369",
    "round": "H",
    "level": "2"
  },
  {
    "id": 22625,
    "tiref": "1656022",
    "stroke_code": 7,
    "course": "S",
    "date": "24/11/24",
    "time": "38.79",
    "is_pb": 1,
    "meet_name": "Hatfield County Qualifier November 2024",
    "venue": "Hatfield",
    "wa_points": "266",
    "round": "H",
    "level": "3"
  },
  {
    "id": 22626,
    "tiref": "1656022",
    "stroke_code": 7,
    "course": "S",
    "date": "24/11/24",
    "time": "39.39",
    "is_pb": 0,
    "meet_name": "Hatfield County Qualifier November 2024",
    "venue": "Hatfield",
    "wa_points": "254",
    "round": "F",
    "level": "3"
  },
  {
    "id": 22627,
    "tiref": "1656022",
    "stroke_code": 7,
    "course": "S",
    "date": "25/01/25",
    "time": "37.39",
    "is_pb": 1,
    "meet_name": "Swim England Hertfordshire County Championships 25",
    "venue": "St Albans",
    "wa_points": "297",
    "round": "F",
    "level": "2"
  },
  {
    "id": 22628,
    "tiref": "1656022",
    "stroke_code": 7,
    "course": "S",
    "date": "25/01/25",
    "time": "38.03",
    "is_pb": 0,
    "meet_name": "Swim England Hertfordshire County Championships 25",
    "venue": "St Albans",
    "wa_points": "282",
    "round": "H",
    "level": "2"
  },
  {
    "id": 22615,
    "tiref": "1656022",
    "stroke_code": 7,
    "course": "S",
    "date": "25/06/23",
    "time": "49.96",
    "is_pb": 0,
    "meet_name": "City of St Albans SC End of Season Meet 2023",
    "venue": "St Albans",
    "wa_points": "124",
    "round": "F",
    "level": "3"
  },
  {
    "id": 22632,
    "tiref": "1656022",
    "stroke_code": 7,
    "course": "S",
    "date": "29/11/25",
    "time": "35.78",
    "is_pb": 1,
    "meet_name": "City of St Albans SC Winter Meet 2025",
    "venue": "St Albans",
    "wa_points": "339",
    "round": "F",
    "level": "3"
  },
  {
    "id": 22664,
    "tiref": "1656022",
    "stroke_code": 8,
    "course": "L",
    "date": "11/05/25",
    "time": "1:23.50",
    "is_pb": 1,
    "meet_name": "SE East Region Long Course Championships 2025",
    "venue": "Luton",
    "wa_points": "316",
    "round": "F",
    "level": "1"
  },
  {
    "id": 22665,
    "tiref": "1656022",
    "stroke_code": 8,
    "course": "L",
    "date": "11/05/25",
    "time": "1:23.68",
    "is_pb": 0,
    "meet_name": "SE East Region Long Course Championships 2025",
    "venue": "Luton",
    "wa_points": "314",
    "round": "H",
    "level": "1"
  },
  {
    "id": 22662,
    "tiref": "1656022",
    "stroke_code": 8,
    "course": "L",
    "date": "12/05/24",
    "time": "1:37.36",
    "is_pb": 1,
    "meet_name": "Swim England East Region LC Championships 2024",
    "venue": "Norwich",
    "wa_points": "199",
    "round": "H",
    "level": "1"
  },
  {
    "id": 22666,
    "tiref": "1656022",
    "stroke_code": 8,
    "course": "L",
    "date": "14/03/26",
    "time": "1:19.08",
    "is_pb": 1,
    "meet_name": "Putteridge SC Spring LC National Qualifier 2026",
    "venue": "Luton",
    "wa_points": "372",
    "round": "H",
    "level": "1"
  },
  {
    "id": 22663,
    "tiref": "1656022",
    "stroke_code": 8,
    "course": "L",
    "date": "16/03/25",
    "time": "1:24.50",
    "is_pb": 1,
    "meet_name": "Team Luton March Long Course Meet 2025",
    "venue": "Luton",
    "wa_points": "305",
    "round": "H",
    "level": "1"
  },
  {
    "id": 22661,
    "tiref": "1656022",
    "stroke_code": 8,
    "course": "L",
    "date": "17/03/24",
    "time": "1:38.20",
    "is_pb": 1,
    "meet_name": "Team Luton March Long Course Meet 2024",
    "venue": "Luton",
    "wa_points": "194",
    "round": "H",
    "level": "1"
  },
  {
    "id": 22667,
    "tiref": "1656022",
    "stroke_code": 8,
    "course": "L",
    "date": "28/03/26",
    "time": "1:17.41",
    "is_pb": 1,
    "meet_name": "London Legacy Swimming Meet 2026 (Long Course)",
    "venue": "London",
    "wa_points": "396",
    "round": "H",
    "level": "1"
  },
  {
    "id": 22644,
    "tiref": "1656022",
    "stroke_code": 8,
    "course": "S",
    "date": "01/10/23",
    "time": "1:43.73",
    "is_pb": 1,
    "meet_name": "City of St Albans Club Champs 2023",
    "venue": "St Albans",
    "wa_points": "151",
    "round": "F",
    "level": "4"
  },
  {
    "id": 22649,
    "tiref": "1656022",
    "stroke_code": 8,
    "course": "S",
    "date": "02/03/24",
    "time": "1:35.07",
    "is_pb": 0,
    "meet_name": "Watford SC Regional Qualifier 2024",
    "venue": "Watford",
    "wa_points": "196",
    "round": "F",
    "level": "3"
  },
  {
    "id": 22646,
    "tiref": "1656022",
    "stroke_code": 8,
    "course": "S",
    "date": "02/12/23",
    "time": "1:35.94",
    "is_pb": 1,
    "meet_name": "City of St Albans Winter Meet 2023",
    "venue": "St Albans",
    "wa_points": "191",
    "round": "F",
    "level": "3"
  },
  {
    "id": 22658,
    "tiref": "1656022",
    "stroke_code": 8,
    "course": "S",
    "date": "06/12/25",
    "time": "1:16.65",
    "is_pb": 1,
    "meet_name": "National Arena Swimming League - London 2025 R3",
    "venue": "Hornchurch",
    "wa_points": "375",
    "round": "F",
    "level": "2"
  },
  {
    "id": 22656,
    "tiref": "1656022",
    "stroke_code": 8,
    "course": "S",
    "date": "11/10/25",
    "time": "1:18.30",
    "is_pb": 1,
    "meet_name": "National Arena Swimming League - London 2025 R1",
    "venue": "Luton",
    "wa_points": "351",
    "round": "F",
    "level": "2"
  },
  {
    "id": 22641,
    "tiref": "1656022",
    "stroke_code": 8,
    "course": "S",
    "date": "12/03/23",
    "time": "1:52.95",
    "is_pb": 1,
    "meet_name": "City of St Albans Spring Meet 2023",
    "venue": "St Albans",
    "wa_points": "117",
    "round": "F",
    "level": "3"
  },
  {
    "id": 22655,
    "tiref": "1656022",
    "stroke_code": 8,
    "course": "S",
    "date": "14/06/25",
    "time": "1:18.85",
    "is_pb": 1,
    "meet_name": "Watford SC The Terry Davies Legacy Meet 2025",
    "venue": "Watford",
    "wa_points": "344",
    "round": "F",
    "level": "3"
  },
  {
    "id": 22650,
    "tiref": "1656022",
    "stroke_code": 8,
    "course": "S",
    "date": "15/06/24",
    "time": "1:29.39",
    "is_pb": 1,
    "meet_name": "Watford Terry Davies Legacy Meet 2024",
    "venue": "Watford",
    "wa_points": "236",
    "round": "F",
    "level": "3"
  },
  {
    "id": 22659,
    "tiref": "1656022",
    "stroke_code": 8,
    "course": "S",
    "date": "18/01/26",
    "time": "1:16.88",
    "is_pb": 0,
    "meet_name": "SE Hertfordshire County Championships 2026",
    "venue": "St Albans",
    "wa_points": "371",
    "round": "F",
    "level": "2"
  },
  {
    "id": 22660,
    "tiref": "1656022",
    "stroke_code": 8,
    "course": "S",
    "date": "18/01/26",
    "time": "1:18.06",
    "is_pb": 0,
    "meet_name": "SE Hertfordshire County Championships 2026",
    "venue": "St Albans",
    "wa_points": "355",
    "round": "H",
    "level": "2"
  },
  {
    "id": 22645,
    "tiref": "1656022",
    "stroke_code": 8,
    "course": "S",
    "date": "18/11/23",
    "time": "1:36.39",
    "is_pb": 1,
    "meet_name": "Watford SC County Qualifier 2023",
    "venue": "Watford",
    "wa_points": "188",
    "round": "F",
    "level": "3"
  },
  {
    "id": 22653,
    "tiref": "1656022",
    "stroke_code": 8,
    "course": "S",
    "date": "19/01/25",
    "time": "1:22.18",
    "is_pb": 1,
    "meet_name": "Swim England Hertfordshire County Championships 25",
    "venue": "St Albans",
    "wa_points": "304",
    "round": "F",
    "level": "2"
  },
  {
    "id": 22654,
    "tiref": "1656022",
    "stroke_code": 8,
    "course": "S",
    "date": "19/01/25",
    "time": "1:23.39",
    "is_pb": 0,
    "meet_name": "Swim England Hertfordshire County Championships 25",
    "venue": "St Albans",
    "wa_points": "291",
    "round": "H",
    "level": "2"
  },
  {
    "id": 22647,
    "tiref": "1656022",
    "stroke_code": 8,
    "course": "S",
    "date": "20/01/24",
    "time": "1:33.65",
    "is_pb": 1,
    "meet_name": "SE Hertfordshire County Championships 2024",
    "venue": "Borehamwood",
    "wa_points": "205",
    "round": "F",
    "level": "2"
  },
  {
    "id": 22648,
    "tiref": "1656022",
    "stroke_code": 8,
    "course": "S",
    "date": "20/01/24",
    "time": "1:36.43",
    "is_pb": 0,
    "meet_name": "SE Hertfordshire County Championships 2024",
    "venue": "Borehamwood",
    "wa_points": "188",
    "round": "H",
    "level": "2"
  },
  {
    "id": 22651,
    "tiref": "1656022",
    "stroke_code": 8,
    "course": "S",
    "date": "21/09/24",
    "time": "1:27.88",
    "is_pb": 1,
    "meet_name": "Co St Albans Autumn Sprint Meet 2024",
    "venue": "St Albans",
    "wa_points": "248",
    "round": "F",
    "level": "3"
  },
  {
    "id": 22640,
    "tiref": "1656022",
    "stroke_code": 8,
    "course": "S",
    "date": "22/10/22",
    "time": "2:03.60",
    "is_pb": 1,
    "meet_name": "Cheshunt SC 17th Annual Autumn Open Meet",
    "venue": "Harlow",
    "wa_points": "89",
    "round": "H",
    "level": "3"
  },
  {
    "id": 22643,
    "tiref": "1656022",
    "stroke_code": 8,
    "course": "S",
    "date": "23/09/23",
    "time": "1:44.43",
    "is_pb": 1,
    "meet_name": "Co St Albans SC Sprint & Skins Competition 2023",
    "venue": "St Albans",
    "wa_points": "148",
    "round": "F",
    "level": "3"
  },
  {
    "id": 22642,
    "tiref": "1656022",
    "stroke_code": 8,
    "course": "S",
    "date": "24/06/23",
    "time": "1:48.23",
    "is_pb": 1,
    "meet_name": "City of St Albans SC End of Season Meet 2023",
    "venue": "St Albans",
    "wa_points": "133",
    "round": "F",
    "level": "3"
  },
  {
    "id": 22657,
    "tiref": "1656022",
    "stroke_code": 8,
    "course": "S",
    "date": "29/11/25",
    "time": "1:16.72",
    "is_pb": 1,
    "meet_name": "City of St Albans SC Winter Meet 2025",
    "venue": "St Albans",
    "wa_points": "374",
    "round": "F",
    "level": "3"
  },
  {
    "id": 22652,
    "tiref": "1656022",
    "stroke_code": 8,
    "course": "S",
    "date": "30/11/24",
    "time": "1:26.01",
    "is_pb": 1,
    "meet_name": "City of St Albans SC Winter Open Meet 2024",
    "venue": "St Albans",
    "wa_points": "265",
    "round": "F",
    "level": "3"
  },
  {
    "id": 22690,
    "tiref": "1656022",
    "stroke_code": 9,
    "course": "L",
    "date": "10/05/25",
    "time": "3:00.32",
    "is_pb": 0,
    "meet_name": "SE East Region Long Course Championships 2025",
    "venue": "Luton",
    "wa_points": "336",
    "round": "F",
    "level": "1"
  },
  {
    "id": 22691,
    "tiref": "1656022",
    "stroke_code": 9,
    "course": "L",
    "date": "10/05/25",
    "time": "3:04.73",
    "is_pb": 0,
    "meet_name": "SE East Region Long Course Championships 2025",
    "venue": "Luton",
    "wa_points": "313",
    "round": "H",
    "level": "1"
  },
  {
    "id": 22685,
    "tiref": "1656022",
    "stroke_code": 9,
    "course": "L",
    "date": "11/05/24",
    "time": "3:23.15",
    "is_pb": 1,
    "meet_name": "Swim England East Region LC Championships 2024",
    "venue": "Norwich",
    "wa_points": "235",
    "round": "F",
    "level": "1"
  },
  {
    "id": 22686,
    "tiref": "1656022",
    "stroke_code": 9,
    "course": "L",
    "date": "11/05/24",
    "time": "3:26.92",
    "is_pb": 0,
    "meet_name": "Swim England East Region LC Championships 2024",
    "venue": "Norwich",
    "wa_points": "223",
    "round": "H",
    "level": "1"
  },
  {
    "id": 22689,
    "tiref": "1656022",
    "stroke_code": 9,
    "course": "L",
    "date": "12/04/25",
    "time": "2:59.84",
    "is_pb": 1,
    "meet_name": "London Legacy Swimming Meet 2025",
    "venue": "London",
    "wa_points": "339",
    "round": "F",
    "level": "1"
  },
  {
    "id": 22687,
    "tiref": "1656022",
    "stroke_code": 9,
    "course": "L",
    "date": "15/03/25",
    "time": "3:04.11",
    "is_pb": 1,
    "meet_name": "Team Luton March Long Course Meet 2025",
    "venue": "Luton",
    "wa_points": "316",
    "round": "H",
    "level": "1"
  },
  {
    "id": 22692,
    "tiref": "1656022",
    "stroke_code": 9,
    "course": "L",
    "date": "15/03/26",
    "time": "2:50.41",
    "is_pb": 1,
    "meet_name": "Putteridge SC Spring LC National Qualifier 2026",
    "venue": "Luton",
    "wa_points": "399",
    "round": "H",
    "level": "1"
  },
  {
    "id": 22684,
    "tiref": "1656022",
    "stroke_code": 9,
    "course": "L",
    "date": "16/03/24",
    "time": "3:29.09",
    "is_pb": 1,
    "meet_name": "Team Luton March Long Course Meet 2024",
    "venue": "Luton",
    "wa_points": "216",
    "round": "H",
    "level": "1"
  },
  {
    "id": 22688,
    "tiref": "1656022",
    "stroke_code": 9,
    "course": "L",
    "date": "23/03/25",
    "time": "3:01.96",
    "is_pb": 1,
    "meet_name": "NUEL SC National Qualifier Open Meet 2025",
    "venue": "London",
    "wa_points": "327",
    "round": "F",
    "level": "1"
  },
  {
    "id": 22671,
    "tiref": "1656022",
    "stroke_code": 9,
    "course": "S",
    "date": "03/12/23",
    "time": "3:25.89",
    "is_pb": 1,
    "meet_name": "City of St Albans Winter Meet 2023",
    "venue": "St Albans",
    "wa_points": "198",
    "round": "F",
    "level": "3"
  },
  {
    "id": 22676,
    "tiref": "1656022",
    "stroke_code": 9,
    "course": "S",
    "date": "06/07/24",
    "time": "3:16.97",
    "is_pb": 0,
    "meet_name": "Putteridge SC End of Season Summer Open 2024",
    "venue": "Luton",
    "wa_points": "227",
    "round": "H",
    "level": "3"
  },
  {
    "id": 22673,
    "tiref": "1656022",
    "stroke_code": 9,
    "course": "S",
    "date": "10/03/24",
    "time": "3:18.43",
    "is_pb": 1,
    "meet_name": "City of St Albans Spring Meet 2024",
    "venue": "St Albans",
    "wa_points": "222",
    "round": "F",
    "level": "3"
  },
  {
    "id": 22668,
    "tiref": "1656022",
    "stroke_code": 9,
    "course": "S",
    "date": "11/03/23",
    "time": "3:51.97",
    "is_pb": 1,
    "meet_name": "City of St Albans Spring Meet 2023",
    "venue": "St Albans",
    "wa_points": "138",
    "round": "F",
    "level": "3"
  },
  {
    "id": 22674,
    "tiref": "1656022",
    "stroke_code": 9,
    "course": "S",
    "date": "16/06/24",
    "time": "3:14.25",
    "is_pb": 1,
    "meet_name": "Watford Terry Davies Legacy Meet 2024",
    "venue": "Watford",
    "wa_points": "236",
    "round": "F",
    "level": "3"
  },
  {
    "id": 22680,
    "tiref": "1656022",
    "stroke_code": 9,
    "course": "S",
    "date": "16/11/25",
    "time": "2:52.56",
    "is_pb": 0,
    "meet_name": "Cambridge Grand Prix 2025",
    "venue": "Cambridge",
    "wa_points": "337",
    "round": "H",
    "level": "2"
  },
  {
    "id": 22670,
    "tiref": "1656022",
    "stroke_code": 9,
    "course": "S",
    "date": "19/11/23",
    "time": "3:30.93",
    "is_pb": 1,
    "meet_name": "Watford SC County Qualifier 2023",
    "venue": "Watford",
    "wa_points": "184",
    "round": "F",
    "level": "3"
  },
  {
    "id": 22672,
    "tiref": "1656022",
    "stroke_code": 9,
    "course": "S",
    "date": "21/01/24",
    "time": "3:27.15",
    "is_pb": 0,
    "meet_name": "SE Hertfordshire County Championships 2024",
    "venue": "Borehamwood",
    "wa_points": "195",
    "round": "H",
    "level": "2"
  },
  {
    "id": 22679,
    "tiref": "1656022",
    "stroke_code": 9,
    "course": "S",
    "date": "22/06/25",
    "time": "2:51.55",
    "is_pb": 1,
    "meet_name": "Co St Albans Summer Meet 2025",
    "venue": "St Albans",
    "wa_points": "343",
    "round": "F",
    "level": "3"
  },
  {
    "id": 22675,
    "tiref": "1656022",
    "stroke_code": 9,
    "course": "S",
    "date": "23/06/24",
    "time": "3:15.48",
    "is_pb": 0,
    "meet_name": "City of St Albans Summer Meet 2024",
    "venue": "St Albans",
    "wa_points": "232",
    "round": "F",
    "level": "3"
  },
  {
    "id": 22677,
    "tiref": "1656022",
    "stroke_code": 9,
    "course": "S",
    "date": "23/11/24",
    "time": "3:07.09",
    "is_pb": 1,
    "meet_name": "Hatfield County Qualifier November 2024",
    "venue": "Hatfield",
    "wa_points": "264",
    "round": "H",
    "level": "3"
  },
  {
    "id": 22682,
    "tiref": "1656022",
    "stroke_code": 9,
    "course": "S",
    "date": "24/01/26",
    "time": "2:42.24",
    "is_pb": 1,
    "meet_name": "SE Hertfordshire County Championships 2026",
    "venue": "St Albans",
    "wa_points": "406",
    "round": "H",
    "level": "2"
  },
  {
    "id": 22683,
    "tiref": "1656022",
    "stroke_code": 9,
    "course": "S",
    "date": "24/01/26",
    "time": "2:45.27",
    "is_pb": 0,
    "meet_name": "SE Hertfordshire County Championships 2026",
    "venue": "St Albans",
    "wa_points": "384",
    "round": "F",
    "level": "2"
  },
  {
    "id": 22669,
    "tiref": "1656022",
    "stroke_code": 9,
    "course": "S",
    "date": "24/06/23",
    "time": "3:42.76",
    "is_pb": 1,
    "meet_name": "City of St Albans SC End of Season Meet 2023",
    "venue": "St Albans",
    "wa_points": "156",
    "round": "F",
    "level": "3"
  },
  {
    "id": 22678,
    "tiref": "1656022",
    "stroke_code": 9,
    "course": "S",
    "date": "25/01/25",
    "time": "2:54.68",
    "is_pb": 1,
    "meet_name": "Swim England Hertfordshire County Championships 25",
    "venue": "St Albans",
    "wa_points": "325",
    "round": "H",
    "level": "2"
  },
  {
    "id": 22681,
    "tiref": "1656022",
    "stroke_code": 9,
    "course": "S",
    "date": "30/11/25",
    "time": "2:46.86",
    "is_pb": 1,
    "meet_name": "City of St Albans SC Winter Meet 2025",
    "venue": "St Albans",
    "wa_points": "373",
    "round": "F",
    "level": "3"
  },
  {
    "id": 22724,
    "tiref": "1656022",
    "stroke_code": 10,
    "course": "L",
    "date": "10/05/25",
    "time": "33.96",
    "is_pb": 0,
    "meet_name": "SE East Region Long Course Championships 2025",
    "venue": "Luton",
    "wa_points": "282",
    "round": "H",
    "level": "1"
  },
  {
    "id": 22721,
    "tiref": "1656022",
    "stroke_code": 10,
    "course": "L",
    "date": "11/05/24",
    "time": "35.64",
    "is_pb": 1,
    "meet_name": "Swim England East Region LC Championships 2024",
    "venue": "Norwich",
    "wa_points": "243",
    "round": "H",
    "level": "1"
  },
  {
    "id": 22723,
    "tiref": "1656022",
    "stroke_code": 10,
    "course": "L",
    "date": "12/04/25",
    "time": "33.22",
    "is_pb": 1,
    "meet_name": "London Legacy Swimming Meet 2025",
    "venue": "London",
    "wa_points": "301",
    "round": "F",
    "level": "1"
  },
  {
    "id": 22725,
    "tiref": "1656022",
    "stroke_code": 10,
    "course": "L",
    "date": "14/03/26",
    "time": "31.16",
    "is_pb": 1,
    "meet_name": "Putteridge SC Spring LC National Qualifier 2026",
    "venue": "Luton",
    "wa_points": "365",
    "round": "H",
    "level": "1"
  },
  {
    "id": 22722,
    "tiref": "1656022",
    "stroke_code": 10,
    "course": "L",
    "date": "15/03/25",
    "time": "33.51",
    "is_pb": 1,
    "meet_name": "Team Luton March Long Course Meet 2025",
    "venue": "Luton",
    "wa_points": "293",
    "round": "H",
    "level": "1"
  },
  {
    "id": 22720,
    "tiref": "1656022",
    "stroke_code": 10,
    "course": "L",
    "date": "16/03/24",
    "time": "35.98",
    "is_pb": 1,
    "meet_name": "Team Luton March Long Course Meet 2024",
    "venue": "Luton",
    "wa_points": "237",
    "round": "H",
    "level": "1"
  },
  {
    "id": 22698,
    "tiref": "1656022",
    "stroke_code": 10,
    "course": "S",
    "date": "01/10/23",
    "time": "42.59",
    "is_pb": 0,
    "meet_name": "City of St Albans Club Champs 2023",
    "venue": "St Albans",
    "wa_points": "125",
    "round": "F",
    "level": "4"
  },
  {
    "id": 22706,
    "tiref": "1656022",
    "stroke_code": 10,
    "course": "S",
    "date": "02/03/24",
    "time": "35.99",
    "is_pb": 0,
    "meet_name": "Watford SC Regional Qualifier 2024",
    "venue": "Watford",
    "wa_points": "207",
    "round": "F",
    "level": "3"
  },
  {
    "id": 22703,
    "tiref": "1656022",
    "stroke_code": 10,
    "course": "S",
    "date": "02/12/23",
    "time": "37.27",
    "is_pb": 1,
    "meet_name": "City of St Albans Winter Meet 2023",
    "venue": "St Albans",
    "wa_points": "187",
    "round": "F",
    "level": "3"
  },
  {
    "id": 22716,
    "tiref": "1656022",
    "stroke_code": 10,
    "course": "S",
    "date": "06/07/25",
    "time": "32.27",
    "is_pb": 0,
    "meet_name": "Co St Albans Club Champs 50s & 25s 2025",
    "venue": "St Albans",
    "wa_points": "288",
    "round": "F",
    "level": "4"
  },
  {
    "id": 22708,
    "tiref": "1656022",
    "stroke_code": 10,
    "course": "S",
    "date": "07/06/24",
    "time": "35.13",
    "is_pb": 1,
    "meet_name": "Herts & St Albans SSA Primary Schools Champs 2024",
    "venue": "St Albans",
    "wa_points": "223",
    "round": "F",
    "level": "4"
  },
  {
    "id": 22701,
    "tiref": "1656022",
    "stroke_code": 10,
    "course": "S",
    "date": "11/11/23",
    "time": "39.80",
    "is_pb": 0,
    "meet_name": "National Arena Swimming League - London 2023",
    "venue": "St Albans",
    "wa_points": "153",
    "round": "F",
    "level": "2"
  },
  {
    "id": 22715,
    "tiref": "1656022",
    "stroke_code": 10,
    "course": "S",
    "date": "14/06/25",
    "time": "32.11",
    "is_pb": 1,
    "meet_name": "Watford SC The Terry Davies Legacy Meet 2025",
    "venue": "Watford",
    "wa_points": "292",
    "round": "F",
    "level": "3"
  },
  {
    "id": 22699,
    "tiref": "1656022",
    "stroke_code": 10,
    "course": "S",
    "date": "14/10/23",
    "time": "39.02",
    "is_pb": 1,
    "meet_name": "National Arena Swimming League - London 2023",
    "venue": "St Albans",
    "wa_points": "163",
    "round": "F",
    "level": "2"
  },
  {
    "id": 22709,
    "tiref": "1656022",
    "stroke_code": 10,
    "course": "S",
    "date": "15/06/24",
    "time": "35.70",
    "is_pb": 0,
    "meet_name": "Watford Terry Davies Legacy Meet 2024",
    "venue": "Watford",
    "wa_points": "212",
    "round": "F",
    "level": "3"
  },
  {
    "id": 22695,
    "tiref": "1656022",
    "stroke_code": 10,
    "course": "S",
    "date": "17/06/23",
    "time": "41.85",
    "is_pb": 1,
    "meet_name": "ESS Charlie Junior Invitational Meet 2023",
    "venue": "Enfield",
    "wa_points": "132",
    "round": "F",
    "level": "4"
  },
  {
    "id": 22707,
    "tiref": "1656022",
    "stroke_code": 10,
    "course": "S",
    "date": "18/05/24",
    "time": "35.99",
    "is_pb": 0,
    "meet_name": "Cheshunt SC May Anniversary Meet 2024",
    "venue": "Harlow",
    "wa_points": "207",
    "round": "H",
    "level": "3"
  },
  {
    "id": 22702,
    "tiref": "1656022",
    "stroke_code": 10,
    "course": "S",
    "date": "18/11/23",
    "time": "39.55",
    "is_pb": 0,
    "meet_name": "Watford SC County Qualifier 2023",
    "venue": "Watford",
    "wa_points": "156",
    "round": "F",
    "level": "3"
  },
  {
    "id": 22693,
    "tiref": "1656022",
    "stroke_code": 10,
    "course": "S",
    "date": "19/05/23",
    "time": "44.70",
    "is_pb": 1,
    "meet_name": "HSSA StASSA Primary Schools Champs 2023",
    "venue": "St Albans",
    "wa_points": "108",
    "round": "F",
    "level": "4"
  },
  {
    "id": 22694,
    "tiref": "1656022",
    "stroke_code": 10,
    "course": "S",
    "date": "20/05/23",
    "time": "45.35",
    "is_pb": 0,
    "meet_name": "Cheshunt SC Anniversary Open Meet 2023",
    "venue": "Harlow",
    "wa_points": "103",
    "round": "H",
    "level": "3"
  },
  {
    "id": 22710,
    "tiref": "1656022",
    "stroke_code": 10,
    "course": "S",
    "date": "21/09/24",
    "time": "34.52",
    "is_pb": 1,
    "meet_name": "Co St Albans Autumn Sprint Meet 2024",
    "venue": "St Albans",
    "wa_points": "235",
    "round": "F",
    "level": "3"
  },
  {
    "id": 22700,
    "tiref": "1656022",
    "stroke_code": 10,
    "course": "S",
    "date": "21/10/23",
    "time": "40.18",
    "is_pb": 0,
    "meet_name": "Cheshunt SC 18th Annual Autumn Open Meet 2023",
    "venue": "Harlow",
    "wa_points": "149",
    "round": "H",
    "level": "3"
  },
  {
    "id": 22697,
    "tiref": "1656022",
    "stroke_code": 10,
    "course": "S",
    "date": "23/09/23",
    "time": "41.86",
    "is_pb": 0,
    "meet_name": "Co St Albans SC Sprint & Skins Competition 2023",
    "venue": "St Albans",
    "wa_points": "132",
    "round": "F",
    "level": "3"
  },
  {
    "id": 22718,
    "tiref": "1656022",
    "stroke_code": 10,
    "course": "S",
    "date": "24/01/26",
    "time": "30.21",
    "is_pb": 1,
    "meet_name": "SE Hertfordshire County Championships 2026",
    "venue": "St Albans",
    "wa_points": "351",
    "round": "F",
    "level": "2"
  },
  {
    "id": 22719,
    "tiref": "1656022",
    "stroke_code": 10,
    "course": "S",
    "date": "24/01/26",
    "time": "30.43",
    "is_pb": 0,
    "meet_name": "SE Hertfordshire County Championships 2026",
    "venue": "St Albans",
    "wa_points": "343",
    "round": "H",
    "level": "2"
  },
  {
    "id": 22711,
    "tiref": "1656022",
    "stroke_code": 10,
    "course": "S",
    "date": "24/11/24",
    "time": "34.35",
    "is_pb": 1,
    "meet_name": "Hatfield County Qualifier November 2024",
    "venue": "Hatfield",
    "wa_points": "239",
    "round": "F",
    "level": "3"
  },
  {
    "id": 22712,
    "tiref": "1656022",
    "stroke_code": 10,
    "course": "S",
    "date": "24/11/24",
    "time": "34.37",
    "is_pb": 0,
    "meet_name": "Hatfield County Qualifier November 2024",
    "venue": "Hatfield",
    "wa_points": "238",
    "round": "H",
    "level": "3"
  },
  {
    "id": 22696,
    "tiref": "1656022",
    "stroke_code": 10,
    "course": "S",
    "date": "25/06/23",
    "time": "42.14",
    "is_pb": 0,
    "meet_name": "City of St Albans SC End of Season Meet 2023",
    "venue": "St Albans",
    "wa_points": "129",
    "round": "F",
    "level": "3"
  },
  {
    "id": 22713,
    "tiref": "1656022",
    "stroke_code": 10,
    "course": "S",
    "date": "26/01/25",
    "time": "33.59",
    "is_pb": 1,
    "meet_name": "Swim England Hertfordshire County Championships 25",
    "venue": "St Albans",
    "wa_points": "255",
    "round": "F",
    "level": "2"
  },
  {
    "id": 22714,
    "tiref": "1656022",
    "stroke_code": 10,
    "course": "S",
    "date": "26/01/25",
    "time": "33.99",
    "is_pb": 0,
    "meet_name": "Swim England Hertfordshire County Championships 25",
    "venue": "St Albans",
    "wa_points": "246",
    "round": "H",
    "level": "2"
  },
  {
    "id": 22704,
    "tiref": "1656022",
    "stroke_code": 10,
    "course": "S",
    "date": "27/01/24",
    "time": "35.81",
    "is_pb": 1,
    "meet_name": "SE Hertfordshire County Championships 2024",
    "venue": "Borehamwood",
    "wa_points": "211",
    "round": "F",
    "level": "2"
  },
  {
    "id": 22705,
    "tiref": "1656022",
    "stroke_code": 10,
    "course": "S",
    "date": "27/01/24",
    "time": "36.04",
    "is_pb": 0,
    "meet_name": "SE Hertfordshire County Championships 2024",
    "venue": "Borehamwood",
    "wa_points": "207",
    "round": "H",
    "level": "2"
  },
  {
    "id": 22717,
    "tiref": "1656022",
    "stroke_code": 10,
    "course": "S",
    "date": "29/11/25",
    "time": "30.67",
    "is_pb": 1,
    "meet_name": "City of St Albans SC Winter Meet 2025",
    "venue": "St Albans",
    "wa_points": "335",
    "round": "F",
    "level": "3"
  },
  {
    "id": 22746,
    "tiref": "1656022",
    "stroke_code": 11,
    "course": "L",
    "date": "05/05/25",
    "time": "1:15.24",
    "is_pb": 1,
    "meet_name": "SE East Region Long Course Championships 2025",
    "venue": "Norwich",
    "wa_points": "283",
    "round": "H",
    "level": "1"
  },
  {
    "id": 22745,
    "tiref": "1656022",
    "stroke_code": 11,
    "course": "L",
    "date": "06/05/24",
    "time": "1:24.85",
    "is_pb": 1,
    "meet_name": "Swim England East Region LC Championships 2024",
    "venue": "Norwich",
    "wa_points": "197",
    "round": "H",
    "level": "1"
  },
  {
    "id": 22747,
    "tiref": "1656022",
    "stroke_code": 11,
    "course": "L",
    "date": "28/03/26",
    "time": "1:07.85",
    "is_pb": 1,
    "meet_name": "London Legacy Swimming Meet 2026 (Long Course)",
    "venue": "London",
    "wa_points": "387",
    "round": "H",
    "level": "1"
  },
  {
    "id": 22732,
    "tiref": "1656022",
    "stroke_code": 11,
    "course": "S",
    "date": "02/03/24",
    "time": "1:20.70",
    "is_pb": 1,
    "meet_name": "Watford SC Regional Qualifier 2024",
    "venue": "Watford",
    "wa_points": "206",
    "round": "F",
    "level": "3"
  },
  {
    "id": 22733,
    "tiref": "1656022",
    "stroke_code": 11,
    "course": "S",
    "date": "10/03/24",
    "time": "1:23.72",
    "is_pb": 0,
    "meet_name": "City of St Albans Spring Meet 2024",
    "venue": "St Albans",
    "wa_points": "185",
    "round": "F",
    "level": "3"
  },
  {
    "id": 22741,
    "tiref": "1656022",
    "stroke_code": 11,
    "course": "S",
    "date": "11/10/25",
    "time": "1:10.46",
    "is_pb": 1,
    "meet_name": "National Arena Swimming League - London 2025 R1",
    "venue": "Luton",
    "wa_points": "310",
    "round": "F",
    "level": "2"
  },
  {
    "id": 22734,
    "tiref": "1656022",
    "stroke_code": 11,
    "course": "S",
    "date": "15/06/24",
    "time": "1:22.18",
    "is_pb": 0,
    "meet_name": "Watford Terry Davies Legacy Meet 2024",
    "venue": "Watford",
    "wa_points": "195",
    "round": "F",
    "level": "3"
  },
  {
    "id": 22727,
    "tiref": "1656022",
    "stroke_code": 11,
    "course": "S",
    "date": "16/09/23",
    "time": "1:27.75",
    "is_pb": 1,
    "meet_name": "City of St Albans Club Champs 2023",
    "venue": "St Albans",
    "wa_points": "160",
    "round": "F",
    "level": "4"
  },
  {
    "id": 22742,
    "tiref": "1656022",
    "stroke_code": 11,
    "course": "S",
    "date": "16/11/25",
    "time": "1:10.30",
    "is_pb": 1,
    "meet_name": "Cambridge Grand Prix 2025",
    "venue": "Cambridge",
    "wa_points": "312",
    "round": "H",
    "level": "2"
  },
  {
    "id": 22743,
    "tiref": "1656022",
    "stroke_code": 11,
    "course": "S",
    "date": "17/01/26",
    "time": "1:07.86",
    "is_pb": 1,
    "meet_name": "SE Hertfordshire County Championships 2026",
    "venue": "St Albans",
    "wa_points": "347",
    "round": "F",
    "level": "2"
  },
  {
    "id": 22744,
    "tiref": "1656022",
    "stroke_code": 11,
    "course": "S",
    "date": "17/01/26",
    "time": "1:08.14",
    "is_pb": 0,
    "meet_name": "SE Hertfordshire County Championships 2026",
    "venue": "St Albans",
    "wa_points": "343",
    "round": "H",
    "level": "2"
  },
  {
    "id": 22738,
    "tiref": "1656022",
    "stroke_code": 11,
    "course": "S",
    "date": "18/01/25",
    "time": "1:16.38",
    "is_pb": 0,
    "meet_name": "Swim England Hertfordshire County Championships 25",
    "venue": "St Albans",
    "wa_points": "243",
    "round": "F",
    "level": "2"
  },
  {
    "id": 22739,
    "tiref": "1656022",
    "stroke_code": 11,
    "course": "S",
    "date": "18/01/25",
    "time": "1:17.37",
    "is_pb": 0,
    "meet_name": "Swim England Hertfordshire County Championships 25",
    "venue": "St Albans",
    "wa_points": "234",
    "round": "H",
    "level": "2"
  },
  {
    "id": 22729,
    "tiref": "1656022",
    "stroke_code": 11,
    "course": "S",
    "date": "19/11/23",
    "time": "1:29.16",
    "is_pb": 0,
    "meet_name": "Watford SC County Qualifier 2023",
    "venue": "Watford",
    "wa_points": "153",
    "round": "F",
    "level": "3"
  },
  {
    "id": 22730,
    "tiref": "1656022",
    "stroke_code": 11,
    "course": "S",
    "date": "21/01/24",
    "time": "1:24.89",
    "is_pb": 1,
    "meet_name": "SE Hertfordshire County Championships 2024",
    "venue": "Borehamwood",
    "wa_points": "177",
    "round": "F",
    "level": "2"
  },
  {
    "id": 22731,
    "tiref": "1656022",
    "stroke_code": 11,
    "course": "S",
    "date": "21/01/24",
    "time": "1:25.13",
    "is_pb": 0,
    "meet_name": "SE Hertfordshire County Championships 2024",
    "venue": "Borehamwood",
    "wa_points": "176",
    "round": "H",
    "level": "2"
  },
  {
    "id": 22735,
    "tiref": "1656022",
    "stroke_code": 11,
    "course": "S",
    "date": "21/09/24",
    "time": "1:16.27",
    "is_pb": 1,
    "meet_name": "Co St Albans Autumn Sprint Meet 2024",
    "venue": "St Albans",
    "wa_points": "244",
    "round": "F",
    "level": "3"
  },
  {
    "id": 22740,
    "tiref": "1656022",
    "stroke_code": 11,
    "course": "S",
    "date": "22/06/25",
    "time": "1:12.60",
    "is_pb": 1,
    "meet_name": "Co St Albans Summer Meet 2025",
    "venue": "St Albans",
    "wa_points": "283",
    "round": "F",
    "level": "3"
  },
  {
    "id": 22728,
    "tiref": "1656022",
    "stroke_code": 11,
    "course": "S",
    "date": "23/09/23",
    "time": "1:34.11",
    "is_pb": 0,
    "meet_name": "Co St Albans SC Sprint & Skins Competition 2023",
    "venue": "St Albans",
    "wa_points": "130",
    "round": "F",
    "level": "3"
  },
  {
    "id": 22736,
    "tiref": "1656022",
    "stroke_code": 11,
    "course": "S",
    "date": "23/11/24",
    "time": "1:16.15",
    "is_pb": 1,
    "meet_name": "Hatfield County Qualifier November 2024",
    "venue": "Hatfield",
    "wa_points": "245",
    "round": "F",
    "level": "3"
  },
  {
    "id": 22737,
    "tiref": "1656022",
    "stroke_code": 11,
    "course": "S",
    "date": "23/11/24",
    "time": "1:16.68",
    "is_pb": 0,
    "meet_name": "Hatfield County Qualifier November 2024",
    "venue": "Hatfield",
    "wa_points": "240",
    "round": "H",
    "level": "3"
  },
  {
    "id": 22726,
    "tiref": "1656022",
    "stroke_code": 11,
    "course": "S",
    "date": "24/06/23",
    "time": "1:40.26",
    "is_pb": 1,
    "meet_name": "City of St Albans SC End of Season Meet 2023",
    "venue": "St Albans",
    "wa_points": "107",
    "round": "F",
    "level": "3"
  },
  {
    "id": 22756,
    "tiref": "1656022",
    "stroke_code": 12,
    "course": "L",
    "date": "14/03/26",
    "time": "2:38.37",
    "is_pb": 1,
    "meet_name": "Putteridge SC Spring LC National Qualifier 2026",
    "venue": "Luton",
    "wa_points": "338",
    "round": "H",
    "level": "1"
  },
  {
    "id": 22755,
    "tiref": "1656022",
    "stroke_code": 12,
    "course": "L",
    "date": "16/03/25",
    "time": "2:53.36",
    "is_pb": 1,
    "meet_name": "Team Luton March Long Course Meet 2025",
    "venue": "Luton",
    "wa_points": "257",
    "round": "H",
    "level": "1"
  },
  {
    "id": 22757,
    "tiref": "1656022",
    "stroke_code": 12,
    "course": "L",
    "date": "29/03/26",
    "time": "2:33.42",
    "is_pb": 1,
    "meet_name": "London Legacy Swimming Meet 2026 (Long Course)",
    "venue": "London",
    "wa_points": "372",
    "round": "H",
    "level": "1"
  },
  {
    "id": 22748,
    "tiref": "1656022",
    "stroke_code": 12,
    "course": "S",
    "date": "09/03/24",
    "time": "3:07.97",
    "is_pb": 1,
    "meet_name": "City of St Albans Spring Meet 2024",
    "venue": "St Albans",
    "wa_points": "183",
    "round": "F",
    "level": "3"
  },
  {
    "id": 22751,
    "tiref": "1656022",
    "stroke_code": 12,
    "course": "S",
    "date": "15/06/25",
    "time": "2:40.09",
    "is_pb": 1,
    "meet_name": "Watford SC The Terry Davies Legacy Meet 2025",
    "venue": "Watford",
    "wa_points": "297",
    "round": "F",
    "level": "3"
  },
  {
    "id": 22749,
    "tiref": "1656022",
    "stroke_code": 12,
    "course": "S",
    "date": "22/06/24",
    "time": "3:02.58",
    "is_pb": 1,
    "meet_name": "City of St Albans Summer Meet 2024",
    "venue": "St Albans",
    "wa_points": "200",
    "round": "F",
    "level": "3"
  },
  {
    "id": 22752,
    "tiref": "1656022",
    "stroke_code": 12,
    "course": "S",
    "date": "23/11/25",
    "time": "2:35.90",
    "is_pb": 1,
    "meet_name": "Hatfield County Qualifier November 2025",
    "venue": "Hatfield",
    "wa_points": "321",
    "round": "H",
    "level": "3"
  },
  {
    "id": 22753,
    "tiref": "1656022",
    "stroke_code": 12,
    "course": "S",
    "date": "25/01/26",
    "time": "2:30.38",
    "is_pb": 1,
    "meet_name": "SE Hertfordshire County Championships 2026",
    "venue": "St Albans",
    "wa_points": "358",
    "round": "H",
    "level": "2"
  },
  {
    "id": 22754,
    "tiref": "1656022",
    "stroke_code": 12,
    "course": "S",
    "date": "25/01/26",
    "time": "2:49.75",
    "is_pb": 0,
    "meet_name": "SE Hertfordshire County Championships 2026",
    "venue": "St Albans",
    "wa_points": "249",
    "round": "F",
    "level": "2"
  },
  {
    "id": 22750,
    "tiref": "1656022",
    "stroke_code": 12,
    "course": "S",
    "date": "30/11/24",
    "time": "2:50.54",
    "is_pb": 1,
    "meet_name": "City of St Albans SC Winter Open Meet 2024",
    "venue": "St Albans",
    "wa_points": "245",
    "round": "F",
    "level": "3"
  },
  {
    "id": 22776,
    "tiref": "1656022",
    "stroke_code": 13,
    "course": "L",
    "date": "16/03/25",
    "time": "36.24",
    "is_pb": 1,
    "meet_name": "Team Luton March Long Course Meet 2025",
    "venue": "Luton",
    "wa_points": "274",
    "round": "H",
    "level": "1"
  },
  {
    "id": 22775,
    "tiref": "1656022",
    "stroke_code": 13,
    "course": "L",
    "date": "17/03/24",
    "time": "40.52",
    "is_pb": 1,
    "meet_name": "Team Luton March Long Course Meet 2024",
    "venue": "Luton",
    "wa_points": "196",
    "round": "H",
    "level": "1"
  },
  {
    "id": 22769,
    "tiref": "1656022",
    "stroke_code": 13,
    "course": "S",
    "date": "03/03/24",
    "time": "38.27",
    "is_pb": 1,
    "meet_name": "Watford SC Regional Qualifier 2024",
    "venue": "Watford",
    "wa_points": "192",
    "round": "F",
    "level": "3"
  },
  {
    "id": 22768,
    "tiref": "1656022",
    "stroke_code": 13,
    "course": "S",
    "date": "03/12/23",
    "time": "40.09",
    "is_pb": 1,
    "meet_name": "City of St Albans Winter Meet 2023",
    "venue": "St Albans",
    "wa_points": "167",
    "round": "F",
    "level": "3"
  },
  {
    "id": 22760,
    "tiref": "1656022",
    "stroke_code": 13,
    "course": "S",
    "date": "04/12/22",
    "time": "46.19",
    "is_pb": 1,
    "meet_name": "City of St Albans SC Winter Meet 2022",
    "venue": "St Albans",
    "wa_points": "109",
    "round": "F",
    "level": "3"
  },
  {
    "id": 22773,
    "tiref": "1656022",
    "stroke_code": 13,
    "course": "S",
    "date": "06/07/25",
    "time": "35.06",
    "is_pb": 1,
    "meet_name": "Co St Albans Club Champs 50s & 25s 2025",
    "venue": "St Albans",
    "wa_points": "250",
    "round": "F",
    "level": "4"
  },
  {
    "id": 22770,
    "tiref": "1656022",
    "stroke_code": 13,
    "course": "S",
    "date": "07/06/24",
    "time": "37.34",
    "is_pb": 1,
    "meet_name": "Herts & St Albans SSA Primary Schools Champs 2024",
    "venue": "St Albans",
    "wa_points": "207",
    "round": "F",
    "level": "4"
  },
  {
    "id": 22774,
    "tiref": "1656022",
    "stroke_code": 13,
    "course": "S",
    "date": "08/03/26",
    "time": "33.14",
    "is_pb": 1,
    "meet_name": "Watford SC Regional Qualifier Open Meet",
    "venue": "Watford",
    "wa_points": "296",
    "round": "F",
    "level": "3"
  },
  {
    "id": 22772,
    "tiref": "1656022",
    "stroke_code": 13,
    "course": "S",
    "date": "09/03/25",
    "time": "35.22",
    "is_pb": 1,
    "meet_name": "City of St Albans Spring Meet 2025",
    "venue": "St Albans",
    "wa_points": "247",
    "round": "F",
    "level": "3"
  },
  {
    "id": 22761,
    "tiref": "1656022",
    "stroke_code": 13,
    "course": "S",
    "date": "11/03/23",
    "time": "45.04",
    "is_pb": 1,
    "meet_name": "City of St Albans Spring Meet 2023",
    "venue": "St Albans",
    "wa_points": "118",
    "round": "F",
    "level": "3"
  },
  {
    "id": 22765,
    "tiref": "1656022",
    "stroke_code": 13,
    "course": "S",
    "date": "16/09/23",
    "time": "40.60",
    "is_pb": 1,
    "meet_name": "City of St Albans Club Champs 2023",
    "venue": "St Albans",
    "wa_points": "161",
    "round": "F",
    "level": "4"
  },
  {
    "id": 22763,
    "tiref": "1656022",
    "stroke_code": 13,
    "course": "S",
    "date": "17/06/23",
    "time": "43.20",
    "is_pb": 1,
    "meet_name": "ESS Charlie Junior Invitational Meet 2023",
    "venue": "Enfield",
    "wa_points": "134",
    "round": "F",
    "level": "4"
  },
  {
    "id": 22762,
    "tiref": "1656022",
    "stroke_code": 13,
    "course": "S",
    "date": "19/05/23",
    "time": "45.55",
    "is_pb": 0,
    "meet_name": "HSSA StASSA Primary Schools Champs 2023",
    "venue": "St Albans",
    "wa_points": "114",
    "round": "F",
    "level": "4"
  },
  {
    "id": 22767,
    "tiref": "1656022",
    "stroke_code": 13,
    "course": "S",
    "date": "19/11/23",
    "time": "41.39",
    "is_pb": 0,
    "meet_name": "Watford SC County Qualifier 2023",
    "venue": "Watford",
    "wa_points": "152",
    "round": "F",
    "level": "3"
  },
  {
    "id": 22771,
    "tiref": "1656022",
    "stroke_code": 13,
    "course": "S",
    "date": "21/09/24",
    "time": "36.86",
    "is_pb": 1,
    "meet_name": "Co St Albans Autumn Sprint Meet 2024",
    "venue": "St Albans",
    "wa_points": "215",
    "round": "F",
    "level": "3"
  },
  {
    "id": 22759,
    "tiref": "1656022",
    "stroke_code": 13,
    "course": "S",
    "date": "22/10/22",
    "time": "49.46",
    "is_pb": 1,
    "meet_name": "Cheshunt SC 17th Annual Autumn Open Meet",
    "venue": "Harlow",
    "wa_points": "89",
    "round": "H",
    "level": "3"
  },
  {
    "id": 22766,
    "tiref": "1656022",
    "stroke_code": 13,
    "course": "S",
    "date": "23/09/23",
    "time": "41.27",
    "is_pb": 0,
    "meet_name": "Co St Albans SC Sprint & Skins Competition 2023",
    "venue": "St Albans",
    "wa_points": "153",
    "round": "F",
    "level": "3"
  },
  {
    "id": 22764,
    "tiref": "1656022",
    "stroke_code": 13,
    "course": "S",
    "date": "24/06/23",
    "time": "45.35",
    "is_pb": 0,
    "meet_name": "City of St Albans SC End of Season Meet 2023",
    "venue": "St Albans",
    "wa_points": "115",
    "round": "F",
    "level": "3"
  },
  {
    "id": 22758,
    "tiref": "1656022",
    "stroke_code": 13,
    "course": "S",
    "date": "25/09/22",
    "time": "51.28",
    "is_pb": 1,
    "meet_name": "City of St Albans SC Level 4 Club Champs",
    "venue": "St Albans",
    "wa_points": "80",
    "round": "F",
    "level": "4"
  },
  {
    "id": 22793,
    "tiref": "1656022",
    "stroke_code": 14,
    "course": "L",
    "date": "12/04/25",
    "time": "1:20.10",
    "is_pb": 0,
    "meet_name": "London Legacy Swimming Meet 2025",
    "venue": "London",
    "wa_points": "267",
    "round": "F",
    "level": "1"
  },
  {
    "id": 22792,
    "tiref": "1656022",
    "stroke_code": 14,
    "course": "L",
    "date": "23/03/25",
    "time": "1:18.87",
    "is_pb": 1,
    "meet_name": "NUEL SC National Qualifier Open Meet 2025",
    "venue": "London",
    "wa_points": "280",
    "round": "F",
    "level": "1"
  },
  {
    "id": 22780,
    "tiref": "1656022",
    "stroke_code": 14,
    "course": "S",
    "date": "01/10/23",
    "time": "1:29.86",
    "is_pb": 0,
    "meet_name": "City of St Albans Club Champs 2023",
    "venue": "St Albans",
    "wa_points": "155",
    "round": "F",
    "level": "4"
  },
  {
    "id": 22788,
    "tiref": "1656022",
    "stroke_code": 14,
    "course": "S",
    "date": "01/12/24",
    "time": "1:16.86",
    "is_pb": 1,
    "meet_name": "City of St Albans SC Winter Open Meet 2024",
    "venue": "St Albans",
    "wa_points": "248",
    "round": "F",
    "level": "3"
  },
  {
    "id": 22785,
    "tiref": "1656022",
    "stroke_code": 14,
    "course": "S",
    "date": "03/03/24",
    "time": "1:22.80",
    "is_pb": 1,
    "meet_name": "Watford SC Regional Qualifier 2024",
    "venue": "Watford",
    "wa_points": "198",
    "round": "F",
    "level": "3"
  },
  {
    "id": 22783,
    "tiref": "1656022",
    "stroke_code": 14,
    "course": "S",
    "date": "03/12/23",
    "time": "1:23.47",
    "is_pb": 1,
    "meet_name": "City of St Albans Winter Meet 2023",
    "venue": "St Albans",
    "wa_points": "194",
    "round": "F",
    "level": "3"
  },
  {
    "id": 22790,
    "tiref": "1656022",
    "stroke_code": 14,
    "course": "S",
    "date": "04/10/25",
    "time": "1:11.69",
    "is_pb": 1,
    "meet_name": "Hatfield Autumn Regional Qualifier October 2025",
    "venue": "Hatfield",
    "wa_points": "306",
    "round": "F",
    "level": "3"
  },
  {
    "id": 22791,
    "tiref": "1656022",
    "stroke_code": 14,
    "course": "S",
    "date": "04/10/25",
    "time": "1:12.23",
    "is_pb": 0,
    "meet_name": "Hatfield Autumn Regional Qualifier October 2025",
    "venue": "Hatfield",
    "wa_points": "299",
    "round": "H",
    "level": "3"
  },
  {
    "id": 22789,
    "tiref": "1656022",
    "stroke_code": 14,
    "course": "S",
    "date": "09/03/25",
    "time": "1:14.02",
    "is_pb": 1,
    "meet_name": "City of St Albans Spring Meet 2025",
    "venue": "St Albans",
    "wa_points": "278",
    "round": "F",
    "level": "3"
  },
  {
    "id": 22787,
    "tiref": "1656022",
    "stroke_code": 14,
    "course": "S",
    "date": "15/06/24",
    "time": "1:22.56",
    "is_pb": 0,
    "meet_name": "Watford Terry Davies Legacy Meet 2024",
    "venue": "Watford",
    "wa_points": "200",
    "round": "F",
    "level": "3"
  },
  {
    "id": 22786,
    "tiref": "1656022",
    "stroke_code": 14,
    "course": "S",
    "date": "18/05/24",
    "time": "1:22.01",
    "is_pb": 1,
    "meet_name": "Cheshunt SC May Anniversary Meet 2024",
    "venue": "Harlow",
    "wa_points": "204",
    "round": "H",
    "level": "3"
  },
  {
    "id": 22782,
    "tiref": "1656022",
    "stroke_code": 14,
    "course": "S",
    "date": "19/11/23",
    "time": "1:25.09",
    "is_pb": 1,
    "meet_name": "Watford SC County Qualifier 2023",
    "venue": "Watford",
    "wa_points": "183",
    "round": "F",
    "level": "3"
  },
  {
    "id": 22784,
    "tiref": "1656022",
    "stroke_code": 14,
    "course": "S",
    "date": "20/01/24",
    "time": "1:26.28",
    "is_pb": 0,
    "meet_name": "SE Hertfordshire County Championships 2024",
    "venue": "Borehamwood",
    "wa_points": "175",
    "round": "H",
    "level": "2"
  },
  {
    "id": 22777,
    "tiref": "1656022",
    "stroke_code": 14,
    "course": "S",
    "date": "20/05/23",
    "time": "1:33.89",
    "is_pb": 1,
    "meet_name": "Cheshunt SC Anniversary Open Meet 2023",
    "venue": "Harlow",
    "wa_points": "136",
    "round": "H",
    "level": "3"
  },
  {
    "id": 22781,
    "tiref": "1656022",
    "stroke_code": 14,
    "course": "S",
    "date": "21/10/23",
    "time": "1:29.42",
    "is_pb": 0,
    "meet_name": "Cheshunt SC 18th Annual Autumn Open Meet 2023",
    "venue": "Harlow",
    "wa_points": "157",
    "round": "H",
    "level": "3"
  },
  {
    "id": 22779,
    "tiref": "1656022",
    "stroke_code": 14,
    "course": "S",
    "date": "23/09/23",
    "time": "1:28.45",
    "is_pb": 1,
    "meet_name": "Co St Albans SC Sprint & Skins Competition 2023",
    "venue": "St Albans",
    "wa_points": "163",
    "round": "F",
    "level": "3"
  },
  {
    "id": 22778,
    "tiref": "1656022",
    "stroke_code": 14,
    "course": "S",
    "date": "25/06/23",
    "time": "1:33.67",
    "is_pb": 1,
    "meet_name": "City of St Albans SC End of Season Meet 2023",
    "venue": "St Albans",
    "wa_points": "137",
    "round": "F",
    "level": "3"
  },
  {
    "id": 22797,
    "tiref": "1656022",
    "stroke_code": 15,
    "course": "S",
    "date": "02/03/24",
    "time": "2:58.19",
    "is_pb": 1,
    "meet_name": "Watford SC Regional Qualifier 2024",
    "venue": "Watford",
    "wa_points": "208",
    "round": "F",
    "level": "3"
  },
  {
    "id": 22800,
    "tiref": "1656022",
    "stroke_code": 15,
    "course": "S",
    "date": "05/10/25",
    "time": "2:37.10",
    "is_pb": 1,
    "meet_name": "Hatfield Autumn Regional Qualifier October 2025",
    "venue": "Hatfield",
    "wa_points": "303",
    "round": "H",
    "level": "3"
  },
  {
    "id": 22801,
    "tiref": "1656022",
    "stroke_code": 15,
    "course": "S",
    "date": "07/03/26",
    "time": "2:31.01",
    "is_pb": 1,
    "meet_name": "Watford SC Regional Qualifier Open Meet",
    "venue": "Watford",
    "wa_points": "342",
    "round": "F",
    "level": "3"
  },
  {
    "id": 22799,
    "tiref": "1656022",
    "stroke_code": 15,
    "course": "S",
    "date": "08/03/25",
    "time": "2:41.89",
    "is_pb": 1,
    "meet_name": "City of St Albans Spring Meet 2025",
    "venue": "St Albans",
    "wa_points": "277",
    "round": "F",
    "level": "3"
  },
  {
    "id": 22794,
    "tiref": "1656022",
    "stroke_code": 15,
    "course": "S",
    "date": "12/03/23",
    "time": "3:24.43",
    "is_pb": 1,
    "meet_name": "City of St Albans Spring Meet 2023",
    "venue": "St Albans",
    "wa_points": "137",
    "round": "F",
    "level": "3"
  },
  {
    "id": 22798,
    "tiref": "1656022",
    "stroke_code": 15,
    "course": "S",
    "date": "16/06/24",
    "time": "2:47.97",
    "is_pb": 1,
    "meet_name": "Watford Terry Davies Legacy Meet 2024",
    "venue": "Watford",
    "wa_points": "248",
    "round": "F",
    "level": "3"
  },
  {
    "id": 22796,
    "tiref": "1656022",
    "stroke_code": 15,
    "course": "S",
    "date": "18/11/23",
    "time": "3:01.81",
    "is_pb": 1,
    "meet_name": "Watford SC County Qualifier 2023",
    "venue": "Watford",
    "wa_points": "196",
    "round": "F",
    "level": "3"
  },
  {
    "id": 22795,
    "tiref": "1656022",
    "stroke_code": 15,
    "course": "S",
    "date": "25/06/23",
    "time": "3:12.28",
    "is_pb": 1,
    "meet_name": "City of St Albans SC End of Season Meet 2023",
    "venue": "St Albans",
    "wa_points": "165",
    "round": "F",
    "level": "3"
  },
  {
    "id": 22821,
    "tiref": "1656022",
    "stroke_code": 16,
    "course": "L",
    "date": "05/05/25",
    "time": "2:47.00",
    "is_pb": 0,
    "meet_name": "SE East Region Long Course Championships 2025",
    "venue": "Norwich",
    "wa_points": "307",
    "round": "H",
    "level": "1"
  },
  {
    "id": 22818,
    "tiref": "1656022",
    "stroke_code": 16,
    "course": "L",
    "date": "06/05/24",
    "time": "2:54.60",
    "is_pb": 1,
    "meet_name": "Swim England East Region LC Championships 2024",
    "venue": "Norwich",
    "wa_points": "268",
    "round": "F",
    "level": "1"
  },
  {
    "id": 22819,
    "tiref": "1656022",
    "stroke_code": 16,
    "course": "L",
    "date": "06/05/24",
    "time": "2:56.74",
    "is_pb": 0,
    "meet_name": "Swim England East Region LC Championships 2024",
    "venue": "Norwich",
    "wa_points": "259",
    "round": "H",
    "level": "1"
  },
  {
    "id": 22820,
    "tiref": "1656022",
    "stroke_code": 16,
    "course": "L",
    "date": "15/03/25",
    "time": "2:43.39",
    "is_pb": 1,
    "meet_name": "Team Luton March Long Course Meet 2025",
    "venue": "Luton",
    "wa_points": "328",
    "round": "H",
    "level": "1"
  },
  {
    "id": 22822,
    "tiref": "1656022",
    "stroke_code": 16,
    "course": "L",
    "date": "15/03/26",
    "time": "2:34.29",
    "is_pb": 1,
    "meet_name": "Putteridge SC Spring LC National Qualifier 2026",
    "venue": "Luton",
    "wa_points": "389",
    "round": "H",
    "level": "1"
  },
  {
    "id": 22817,
    "tiref": "1656022",
    "stroke_code": 16,
    "course": "L",
    "date": "16/03/24",
    "time": "3:00.85",
    "is_pb": 1,
    "meet_name": "Team Luton March Long Course Meet 2024",
    "venue": "Luton",
    "wa_points": "241",
    "round": "H",
    "level": "1"
  },
  {
    "id": 22823,
    "tiref": "1656022",
    "stroke_code": 16,
    "course": "L",
    "date": "29/03/26",
    "time": "2:29.88",
    "is_pb": 1,
    "meet_name": "London Legacy Swimming Meet 2026 (Long Course)",
    "venue": "London",
    "wa_points": "425",
    "round": "H",
    "level": "1"
  },
  {
    "id": 22824,
    "tiref": "1656022",
    "stroke_code": 16,
    "course": "L",
    "date": "29/03/26",
    "time": "2:31.65",
    "is_pb": 0,
    "meet_name": "London Legacy Swimming Meet 2026 (Long Course)",
    "venue": "London",
    "wa_points": "410",
    "round": "F",
    "level": "1"
  },
  {
    "id": 22804,
    "tiref": "1656022",
    "stroke_code": 16,
    "course": "S",
    "date": "01/10/23",
    "time": "3:12.03",
    "is_pb": 1,
    "meet_name": "City of St Albans Club Champs 2023",
    "venue": "St Albans",
    "wa_points": "182",
    "round": "F",
    "level": "4"
  },
  {
    "id": 22807,
    "tiref": "1656022",
    "stroke_code": 16,
    "course": "S",
    "date": "03/03/24",
    "time": "2:57.21",
    "is_pb": 1,
    "meet_name": "Watford SC Regional Qualifier 2024",
    "venue": "Watford",
    "wa_points": "231",
    "round": "F",
    "level": "3"
  },
  {
    "id": 22816,
    "tiref": "1656022",
    "stroke_code": 16,
    "course": "S",
    "date": "08/03/26",
    "time": "2:27.36",
    "is_pb": 0,
    "meet_name": "Watford SC Regional Qualifier Open Meet",
    "venue": "Watford",
    "wa_points": "403",
    "round": "F",
    "level": "3"
  },
  {
    "id": 22811,
    "tiref": "1656022",
    "stroke_code": 16,
    "course": "S",
    "date": "08/12/24",
    "time": "2:41.74",
    "is_pb": 1,
    "meet_name": "Team Luton 2024 Winter Development Meet",
    "venue": "Luton",
    "wa_points": "305",
    "round": "H",
    "level": "3"
  },
  {
    "id": 22808,
    "tiref": "1656022",
    "stroke_code": 16,
    "course": "S",
    "date": "10/03/24",
    "time": "2:56.60",
    "is_pb": 1,
    "meet_name": "City of St Albans Spring Meet 2024",
    "venue": "St Albans",
    "wa_points": "234",
    "round": "F",
    "level": "3"
  },
  {
    "id": 22802,
    "tiref": "1656022",
    "stroke_code": 16,
    "course": "S",
    "date": "11/03/23",
    "time": "3:24.71",
    "is_pb": 1,
    "meet_name": "City of St Albans Spring Meet 2023",
    "venue": "St Albans",
    "wa_points": "150",
    "round": "F",
    "level": "3"
  },
  {
    "id": 22813,
    "tiref": "1656022",
    "stroke_code": 16,
    "course": "S",
    "date": "14/06/25",
    "time": "2:35.56",
    "is_pb": 1,
    "meet_name": "Watford SC The Terry Davies Legacy Meet 2025",
    "venue": "Watford",
    "wa_points": "342",
    "round": "F",
    "level": "3"
  },
  {
    "id": 22809,
    "tiref": "1656022",
    "stroke_code": 16,
    "course": "S",
    "date": "15/06/24",
    "time": "2:49.80",
    "is_pb": 1,
    "meet_name": "Watford Terry Davies Legacy Meet 2024",
    "venue": "Watford",
    "wa_points": "263",
    "round": "F",
    "level": "3"
  },
  {
    "id": 22815,
    "tiref": "1656022",
    "stroke_code": 16,
    "course": "S",
    "date": "17/01/26",
    "time": "2:26.55",
    "is_pb": 1,
    "meet_name": "SE Hertfordshire County Championships 2026",
    "venue": "St Albans",
    "wa_points": "410",
    "round": "H",
    "level": "2"
  },
  {
    "id": 22812,
    "tiref": "1656022",
    "stroke_code": 16,
    "course": "S",
    "date": "18/01/25",
    "time": "2:41.64",
    "is_pb": 1,
    "meet_name": "Swim England Hertfordshire County Championships 25",
    "venue": "St Albans",
    "wa_points": "305",
    "round": "H",
    "level": "2"
  },
  {
    "id": 22805,
    "tiref": "1656022",
    "stroke_code": 16,
    "course": "S",
    "date": "18/11/23",
    "time": "3:03.51",
    "is_pb": 1,
    "meet_name": "Watford SC County Qualifier 2023",
    "venue": "Watford",
    "wa_points": "208",
    "round": "F",
    "level": "3"
  },
  {
    "id": 22810,
    "tiref": "1656022",
    "stroke_code": 16,
    "course": "S",
    "date": "24/11/24",
    "time": "2:44.98",
    "is_pb": 1,
    "meet_name": "Hatfield County Qualifier November 2024",
    "venue": "Hatfield",
    "wa_points": "287",
    "round": "H",
    "level": "3"
  },
  {
    "id": 22803,
    "tiref": "1656022",
    "stroke_code": 16,
    "course": "S",
    "date": "25/06/23",
    "time": "3:14.98",
    "is_pb": 1,
    "meet_name": "City of St Albans SC End of Season Meet 2023",
    "venue": "St Albans",
    "wa_points": "174",
    "round": "F",
    "level": "3"
  },
  {
    "id": 22806,
    "tiref": "1656022",
    "stroke_code": 16,
    "course": "S",
    "date": "28/01/24",
    "time": "2:59.87",
    "is_pb": 1,
    "meet_name": "SE Hertfordshire County Championships 2024",
    "venue": "Borehamwood",
    "wa_points": "221",
    "round": "H",
    "level": "2"
  },
  {
    "id": 22814,
    "tiref": "1656022",
    "stroke_code": 16,
    "course": "S",
    "date": "30/11/25",
    "time": "2:28.30",
    "is_pb": 1,
    "meet_name": "City of St Albans SC Winter Meet 2025",
    "venue": "St Albans",
    "wa_points": "395",
    "round": "F",
    "level": "3"
  },
  {
    "id": 22833,
    "tiref": "1656022",
    "stroke_code": 17,
    "course": "L",
    "date": "11/05/24",
    "time": "6:21.25",
    "is_pb": 1,
    "meet_name": "Swim England East Region LC Championships 2024",
    "venue": "Norwich",
    "wa_points": "257",
    "round": "H",
    "level": "1"
  },
  {
    "id": 22834,
    "tiref": "1656022",
    "stroke_code": 17,
    "course": "L",
    "date": "23/03/25",
    "time": "5:48.61",
    "is_pb": 1,
    "meet_name": "NUEL SC National Qualifier Open Meet 2025",
    "venue": "London",
    "wa_points": "336",
    "round": "F",
    "level": "1"
  },
  {
    "id": 22835,
    "tiref": "1656022",
    "stroke_code": 17,
    "course": "L",
    "date": "28/03/26",
    "time": "5:21.45",
    "is_pb": 1,
    "meet_name": "London Legacy Swimming Meet 2026 (Long Course)",
    "venue": "London",
    "wa_points": "429",
    "round": "H",
    "level": "1"
  },
  {
    "id": 22831,
    "tiref": "1656022",
    "stroke_code": 17,
    "course": "S",
    "date": "07/12/25",
    "time": "5:15.40",
    "is_pb": 1,
    "meet_name": "Co St Albans & Verulam Joint Club Champs 2025",
    "venue": "St Albans",
    "wa_points": "412",
    "round": "F",
    "level": "3"
  },
  {
    "id": 22829,
    "tiref": "1656022",
    "stroke_code": 17,
    "course": "S",
    "date": "08/03/25",
    "time": "5:35.74",
    "is_pb": 1,
    "meet_name": "City of St Albans Spring Meet 2025",
    "venue": "St Albans",
    "wa_points": "342",
    "round": "F",
    "level": "3"
  },
  {
    "id": 22825,
    "tiref": "1656022",
    "stroke_code": 17,
    "course": "S",
    "date": "09/03/24",
    "time": "6:06.90",
    "is_pb": 1,
    "meet_name": "City of St Albans Spring Meet 2024",
    "venue": "St Albans",
    "wa_points": "262",
    "round": "F",
    "level": "3"
  },
  {
    "id": 22827,
    "tiref": "1656022",
    "stroke_code": 17,
    "course": "S",
    "date": "10/11/24",
    "time": "5:56.40",
    "is_pb": 1,
    "meet_name": "Co St Albans Long Distance Club Champs 2024",
    "venue": "St Albans",
    "wa_points": "285",
    "round": "F",
    "level": "3"
  },
  {
    "id": 22832,
    "tiref": "1656022",
    "stroke_code": 17,
    "course": "S",
    "date": "18/01/26",
    "time": "5:10.21",
    "is_pb": 1,
    "meet_name": "SE Hertfordshire County Championships 2026",
    "venue": "St Albans",
    "wa_points": "433",
    "round": "H",
    "level": "2"
  },
  {
    "id": 22830,
    "tiref": "1656022",
    "stroke_code": 17,
    "course": "S",
    "date": "21/06/25",
    "time": "5:32.18",
    "is_pb": 1,
    "meet_name": "Co St Albans Summer Meet 2025",
    "venue": "St Albans",
    "wa_points": "353",
    "round": "F",
    "level": "3"
  },
  {
    "id": 22826,
    "tiref": "1656022",
    "stroke_code": 17,
    "course": "S",
    "date": "22/06/24",
    "time": "6:02.81",
    "is_pb": 1,
    "meet_name": "City of St Albans Summer Meet 2024",
    "venue": "St Albans",
    "wa_points": "271",
    "round": "F",
    "level": "3"
  },
  {
    "id": 22828,
    "tiref": "1656022",
    "stroke_code": 17,
    "course": "S",
    "date": "23/11/24",
    "time": "5:51.63",
    "is_pb": 1,
    "meet_name": "Hatfield County Qualifier November 2024",
    "venue": "Hatfield",
    "wa_points": "297",
    "round": "H",
    "level": "3"
  },
  {
    "id": 22841,
    "tiref": "1656022",
    "stroke_code": 18,
    "course": "S",
    "date": "02/07/23",
    "time": "1:26.68",
    "is_pb": 1,
    "meet_name": "Putteridge SC End of Season Summer SC Open 2023",
    "venue": "Luton",
    "wa_points": "183",
    "round": "H",
    "level": "2"
  },
  {
    "id": 22837,
    "tiref": "1656022",
    "stroke_code": 18,
    "course": "S",
    "date": "04/12/22",
    "time": "1:42.08",
    "is_pb": 1,
    "meet_name": "City of St Albans SC Winter Meet 2022",
    "venue": "St Albans",
    "wa_points": "112",
    "round": "F",
    "level": "3"
  },
  {
    "id": 22852,
    "tiref": "1656022",
    "stroke_code": 18,
    "course": "S",
    "date": "06/07/24",
    "time": "1:18.30",
    "is_pb": 1,
    "meet_name": "Putteridge SC End of Season Summer Open 2024",
    "venue": "Luton",
    "wa_points": "249",
    "round": "H",
    "level": "3"
  },
  {
    "id": 22853,
    "tiref": "1656022",
    "stroke_code": 18,
    "course": "S",
    "date": "08/12/24",
    "time": "1:16.33",
    "is_pb": 1,
    "meet_name": "Team Luton 2024 Winter Development Meet",
    "venue": "Luton",
    "wa_points": "269",
    "round": "H",
    "level": "3"
  },
  {
    "id": 22848,
    "tiref": "1656022",
    "stroke_code": 18,
    "course": "S",
    "date": "09/03/24",
    "time": "1:19.69",
    "is_pb": 1,
    "meet_name": "City of St Albans Spring Meet 2024",
    "venue": "St Albans",
    "wa_points": "236",
    "round": "F",
    "level": "3"
  },
  {
    "id": 22856,
    "tiref": "1656022",
    "stroke_code": 18,
    "course": "S",
    "date": "15/06/25",
    "time": "1:13.15",
    "is_pb": 1,
    "meet_name": "Watford SC The Terry Davies Legacy Meet 2025",
    "venue": "Watford",
    "wa_points": "305",
    "round": "F",
    "level": "3"
  },
  {
    "id": 22850,
    "tiref": "1656022",
    "stroke_code": 18,
    "course": "S",
    "date": "16/06/24",
    "time": "1:20.14",
    "is_pb": 0,
    "meet_name": "Watford Terry Davies Legacy Meet 2024",
    "venue": "Watford",
    "wa_points": "232",
    "round": "F",
    "level": "3"
  },
  {
    "id": 22842,
    "tiref": "1656022",
    "stroke_code": 18,
    "course": "S",
    "date": "16/09/23",
    "time": "1:29.30",
    "is_pb": 0,
    "meet_name": "City of St Albans Club Champs 2023",
    "venue": "St Albans",
    "wa_points": "168",
    "round": "F",
    "level": "4"
  },
  {
    "id": 22839,
    "tiref": "1656022",
    "stroke_code": 18,
    "course": "S",
    "date": "17/06/23",
    "time": "1:32.23",
    "is_pb": 1,
    "meet_name": "ESS Charlie Junior Invitational Meet 2023",
    "venue": "Enfield",
    "wa_points": "152",
    "round": "F",
    "level": "4"
  },
  {
    "id": 22849,
    "tiref": "1656022",
    "stroke_code": 18,
    "course": "S",
    "date": "18/05/24",
    "time": "1:22.49",
    "is_pb": 0,
    "meet_name": "Cheshunt SC May Anniversary Meet 2024",
    "venue": "Harlow",
    "wa_points": "213",
    "round": "H",
    "level": "3"
  },
  {
    "id": 22845,
    "tiref": "1656022",
    "stroke_code": 18,
    "course": "S",
    "date": "18/11/23",
    "time": "1:22.89",
    "is_pb": 1,
    "meet_name": "Watford SC County Qualifier 2023",
    "venue": "Watford",
    "wa_points": "210",
    "round": "F",
    "level": "3"
  },
  {
    "id": 22846,
    "tiref": "1656022",
    "stroke_code": 18,
    "course": "S",
    "date": "20/01/24",
    "time": "1:22.20",
    "is_pb": 1,
    "meet_name": "SE Hertfordshire County Championships 2024",
    "venue": "Borehamwood",
    "wa_points": "215",
    "round": "H",
    "level": "2"
  },
  {
    "id": 22847,
    "tiref": "1656022",
    "stroke_code": 18,
    "course": "S",
    "date": "20/01/24",
    "time": "1:22.48",
    "is_pb": 0,
    "meet_name": "SE Hertfordshire County Championships 2024",
    "venue": "Borehamwood",
    "wa_points": "213",
    "round": "F",
    "level": "2"
  },
  {
    "id": 22838,
    "tiref": "1656022",
    "stroke_code": 18,
    "course": "S",
    "date": "20/05/23",
    "time": "1:34.52",
    "is_pb": 1,
    "meet_name": "Cheshunt SC Anniversary Open Meet 2023",
    "venue": "Harlow",
    "wa_points": "141",
    "round": "H",
    "level": "3"
  },
  {
    "id": 22857,
    "tiref": "1656022",
    "stroke_code": 18,
    "course": "S",
    "date": "21/06/25",
    "time": "1:13.60",
    "is_pb": 0,
    "meet_name": "Co St Albans Summer Meet 2025",
    "venue": "St Albans",
    "wa_points": "300",
    "round": "F",
    "level": "3"
  },
  {
    "id": 22844,
    "tiref": "1656022",
    "stroke_code": 18,
    "course": "S",
    "date": "21/10/23",
    "time": "1:26.98",
    "is_pb": 0,
    "meet_name": "Cheshunt SC 18th Annual Autumn Open Meet 2023",
    "venue": "Harlow",
    "wa_points": "181",
    "round": "H",
    "level": "3"
  },
  {
    "id": 22851,
    "tiref": "1656022",
    "stroke_code": 18,
    "course": "S",
    "date": "22/06/24",
    "time": "1:18.59",
    "is_pb": 1,
    "meet_name": "City of St Albans Summer Meet 2024",
    "venue": "St Albans",
    "wa_points": "246",
    "round": "F",
    "level": "3"
  },
  {
    "id": 22836,
    "tiref": "1656022",
    "stroke_code": 18,
    "course": "S",
    "date": "22/10/22",
    "time": "1:46.28",
    "is_pb": 1,
    "meet_name": "Cheshunt SC 17th Annual Autumn Open Meet",
    "venue": "Harlow",
    "wa_points": "99",
    "round": "H",
    "level": "3"
  },
  {
    "id": 22843,
    "tiref": "1656022",
    "stroke_code": 18,
    "course": "S",
    "date": "23/09/23",
    "time": "1:28.35",
    "is_pb": 0,
    "meet_name": "Co St Albans SC Sprint & Skins Competition 2023",
    "venue": "St Albans",
    "wa_points": "173",
    "round": "F",
    "level": "3"
  },
  {
    "id": 22858,
    "tiref": "1656022",
    "stroke_code": 18,
    "course": "S",
    "date": "23/11/25",
    "time": "1:10.09",
    "is_pb": 1,
    "meet_name": "Hatfield County Qualifier November 2025",
    "venue": "Hatfield",
    "wa_points": "347",
    "round": "F",
    "level": "3"
  },
  {
    "id": 22859,
    "tiref": "1656022",
    "stroke_code": 18,
    "course": "S",
    "date": "23/11/25",
    "time": "1:10.79",
    "is_pb": 0,
    "meet_name": "Hatfield County Qualifier November 2025",
    "venue": "Hatfield",
    "wa_points": "337",
    "round": "H",
    "level": "3"
  },
  {
    "id": 22861,
    "tiref": "1656022",
    "stroke_code": 18,
    "course": "S",
    "date": "25/01/26",
    "time": "1:07.84",
    "is_pb": 1,
    "meet_name": "SE Hertfordshire County Championships 2026",
    "venue": "St Albans",
    "wa_points": "383",
    "round": "F",
    "level": "2"
  },
  {
    "id": 22862,
    "tiref": "1656022",
    "stroke_code": 18,
    "course": "S",
    "date": "25/01/26",
    "time": "1:09.30",
    "is_pb": 0,
    "meet_name": "SE Hertfordshire County Championships 2026",
    "venue": "St Albans",
    "wa_points": "359",
    "round": "H",
    "level": "2"
  },
  {
    "id": 22840,
    "tiref": "1656022",
    "stroke_code": 18,
    "course": "S",
    "date": "25/06/23",
    "time": "1:31.60",
    "is_pb": 1,
    "meet_name": "City of St Albans SC End of Season Meet 2023",
    "venue": "St Albans",
    "wa_points": "155",
    "round": "F",
    "level": "3"
  },
  {
    "id": 22854,
    "tiref": "1656022",
    "stroke_code": 18,
    "course": "S",
    "date": "26/01/25",
    "time": "1:13.60",
    "is_pb": 1,
    "meet_name": "Swim England Hertfordshire County Championships 25",
    "venue": "St Albans",
    "wa_points": "300",
    "round": "F",
    "level": "2"
  },
  {
    "id": 22855,
    "tiref": "1656022",
    "stroke_code": 18,
    "course": "S",
    "date": "26/01/25",
    "time": "1:14.48",
    "is_pb": 0,
    "meet_name": "Swim England Hertfordshire County Championships 25",
    "venue": "St Albans",
    "wa_points": "289",
    "round": "H",
    "level": "2"
  },
  {
    "id": 22860,
    "tiref": "1656022",
    "stroke_code": 18,
    "course": "S",
    "date": "29/11/25",
    "time": "1:09.53",
    "is_pb": 1,
    "meet_name": "City of St Albans SC Winter Meet 2025",
    "venue": "St Albans",
    "wa_points": "356",
    "round": "F",
    "level": "3"
  }
]